Workbook

Sheet Resumo
C2: Earnings do Ibovespa e sensibilidades macro
C3: Consolidação das análises contemporâneas do índice e dos setores. Dados disponíveis até setembro de 2026; macro até agosto de 2026.
C6: Cobertura e especificação principal
C7: Item | D7: Valor | E7: Unidade | F7: Observação
C8: Cobertura setorial - início | D8: =MIN('Earnings 12M Fwd'!$C$7:$C$231) | E8: mês | F8: Séries GICS consolidadas
C9: Cobertura setorial - fim | D9: =MAX('Earnings 12M Fwd'!$C$7:$C$231) | E9: mês | F9: Séries GICS consolidadas
C10: Número de observações | D10: =COUNTA('Earnings 12M Fwd'!$C$7:$C$231) | E10: meses | F10: Earnings setoriais
C11: Modelo principal | D11: ex_2013_14 | E11: amostra | F11: Exclui 2013-2014
C14: Modelo contemporâneo do IBOV - BEst EPS direto
C15: Variável | D15: Beta | E15: Beta padronizado | F15: p-valor HAC | G15: Leitura | H15: Amostra
C16: Focus PIB | D16: =SUMIFS('Reg IBOV'!$J$7:$J$26,'Reg IBOV'!$D$7:$D$26,"ex_2013_14",'Reg IBOV'!$I$7:$I$26,"d_focus_pib3") | E16: =SUMIFS('Reg IBOV'!$K$7:$K$26,'Reg IBOV'!$D$7:$D$26,"ex_2013_14",'Reg IBOV'!$I$7:$I$26,"d_focus_pib3") | F16: =SUMIFS('Reg IBOV'!$N$7:$N$26,'Reg IBOV'!$D$7:$D$26,"ex_2013_14",'Reg IBOV'!$I$7:$I$26,"d_focus_pib3") | G16: Principal driver contemporâneo | H16: ex_2013_14
C17: BCOM em USD | D17: =SUMIFS('Reg IBOV'!$J$7:$J$26,'Reg IBOV'!$D$7:$D$26,"ex_2013_14",'Reg IBOV'!$I$7:$I$26,"d_bcom_usd3") | E17: =SUMIFS('Reg IBOV'!$K$7:$K$26,'Reg IBOV'!$D$7:$D$26,"ex_2013_14",'Reg IBOV'!$I$7:$I$26,"d_bcom_usd3") | F17: =SUMIFS('Reg IBOV'!$N$7:$N$26,'Reg IBOV'!$D$7:$D$26,"ex_2013_14",'Reg IBOV'!$I$7:$I$26,"d_bcom_usd3") | G17: Sem significância no modelo completo | H17: ex_2013_14
C18: USD/BRL | D18: =SUMIFS('Reg IBOV'!$J$7:$J$26,'Reg IBOV'!$D$7:$D$26,"ex_2013_14",'Reg IBOV'!$I$7:$I$26,"d_usdbrl3") | E18: =SUMIFS('Reg IBOV'!$K$7:$K$26,'Reg IBOV'!$D$7:$D$26,"ex_2013_14",'Reg IBOV'!$I$7:$I$26,"d_usdbrl3") | F18: =SUMIFS('Reg IBOV'!$N$7:$N$26,'Reg IBOV'!$D$7:$D$26,"ex_2013_14",'Reg IBOV'!$I$7:$I$26,"d_usdbrl3") | G18: Sem significância no modelo completo | H18: ex_2013_14
C19: IPCA realizado 12m | D19: =SUMIFS('Reg IBOV'!$J$7:$J$26,'Reg IBOV'!$D$7:$D$26,"ex_2013_14",'Reg IBOV'!$I$7:$I$26,"d_ipca12_3_available") | E19: =SUMIFS('Reg IBOV'!$K$7:$K$26,'Reg IBOV'!$D$7:$D$26,"ex_2013_14",'Reg IBOV'!$I$7:$I$26,"d_ipca12_3_available") | F19: =SUMIFS('Reg IBOV'!$N$7:$N$26,'Reg IBOV'!$D$7:$D$26,"ex_2013_14",'Reg IBOV'!$I$7:$I$26,"d_ipca12_3_available") | G19: Significância marginal | H19: ex_2013_14
C20: Swap pré-DI 360d | D20: =SUMIFS('Reg IBOV'!$J$7:$J$26,'Reg IBOV'!$D$7:$D$26,"ex_2013_14",'Reg IBOV'!$I$7:$I$26,"d_swap360_3") | E20: =SUMIFS('Reg IBOV'!$K$7:$K$26,'Reg IBOV'!$D$7:$D$26,"ex_2013_14",'Reg IBOV'!$I$7:$I$26,"d_swap360_3") | F20: =SUMIFS('Reg IBOV'!$N$7:$N$26,'Reg IBOV'!$D$7:$D$26,"ex_2013_14",'Reg IBOV'!$I$7:$I$26,"d_swap360_3") | G20: Sinal positivo, mas instável entre janelas | H20: ex_2013_14
C21: R² do modelo | D21: =SUMIFS('Reg IBOV'!$G$7:$G$26,'Reg IBOV'!$D$7:$D$26,"ex_2013_14",'Reg IBOV'!$I$7:$I$26,"d_focus_pib3") | G21: Poder explicativo do modelo completo | H21: ex_2013_14
C24: Conclusões até aqui
C25: Tema | D25: Evidência | E25: Valor | F25: Unidade | G25: Interpretação | H25: Referência
C26: Focus PIB | D26: Beta padronizado do IBOV | E26: =E16 | F26: desvios-padrão | G26: É o driver mais consistente do índice. | H26: Reg IBOV
C27: Inflação | D27: ΔR²: IPCA realizado menos Focus | E27: =SUMIFS('Inflacao'!$K$15:$K$26,'Inflacao'!$C$15:$C$26,"ex_2013_14",'Inflacao'!$D$15:$D$26,"d_ipca12_3_available")-SUMIFS('Inflacao'!$K$15:$K$26,'Inflacao'!$C$15:$C$26,"ex_2013_14",'Inflacao'!$D$15:$D$26,"d_focus_ipca3") | F27: p.p. de R² | G27: O realizado melhora um pouco o ajuste, mas a diferença é pequena. | H27: Inflacao
C28: Swap pré-DI | D28: Beta na amostra limpa | E28: =SUMIFS('Swap Robustez'!$H$21:$H$68,'Swap Robustez'!$C$21:$C$68,"IBOV BEst EPS",'Swap Robustez'!$D$21:$D$68,"clean",'Swap Robustez'!$E$21:$E$68,"full") | F28: % revisão por 1 p.p. | G28: O sinal positivo não é robusto o suficiente para leitura causal. | H28: Swap Robustez
C29: Setores | D29: Maior beta Focus padronizado | E29: =SUMIFS('Reg Setores'!$L$7:$L$114,'Reg Setores'!$D$7:$D$114,"ex_2013_14",'Reg Setores'!$C$7:$C$114,"Energy") | F29: desvios-padrão | G29: Energia lidera na amostra principal. | H29: Painel Setorial
C30: Ex-commodities | D30: Diferença de beta vs. IBOV | E30: =SUMIFS('Ex-Commodities'!$Q$19:$Q$24,'Ex-Commodities'!$C$19:$C$24,"ex_2013_14") | F30: % revisão por 1 p.p. | G30: O beta ex-commodities é menor, não maior. | H30: Ex-Commodities
C31: Energia | D31: Correlação das revisions com Petrobras | E31: 0.995009 | F31: correlação | G31: A liderança de Energia é majoritariamente Petrobras. | H31: Energia
C33: Nota metodológica | D33: As regressões são contemporâneas e associativas. Coeficientes não devem ser lidos como efeitos causais. Resultados setoriais usam BEst Net Income agregado; o modelo direto do índice usa BEst EPS.

Sheet Painel Setorial
C2: Sensibilidades contemporâneas por setor
C3: Amostra principal exclui 2013-2014. Betas padronizados permitem comparar a magnitude entre setores.
C6: Resultados do modelo completo
C8: Setor | D8: R² | E8: Focus beta | F8: Focus beta pad. | G8: Focus p | H8: Focus q BH | I8: Swap beta | J8: Swap beta pad. | K8: Swap p | L8: Swap q BH
C9: Energy | D9: =SUMIFS('Reg Setores'!$H$7:$H$114,'Reg Setores'!$D$7:$D$114,"ex_2013_14",'Reg Setores'!$C$7:$C$114,$C9) | E9: =SUMIFS('Reg Setores'!$K$7:$K$114,'Reg Setores'!$D$7:$D$114,"ex_2013_14",'Reg Setores'!$C$7:$C$114,$C9) | F9: =SUMIFS('Reg Setores'!$L$7:$L$114,'Reg Setores'!$D$7:$D$114,"ex_2013_14",'Reg Setores'!$C$7:$C$114,$C9) | G9: =SUMIFS('Reg Setores'!$N$7:$N$114,'Reg Setores'!$D$7:$D$114,"ex_2013_14",'Reg Setores'!$C$7:$C$114,$C9) | H9: =SUMIFS('Reg Setores'!$AM$7:$AM$114,'Reg Setores'!$D$7:$D$114,"ex_2013_14",'Reg Setores'!$C$7:$C$114,$C9) | I9: =SUMIFS('Reg Setores'!$AE$7:$AE$114,'Reg Setores'!$D$7:$D$114,"ex_2013_14",'Reg Setores'!$C$7:$C$114,$C9) | J9: =SUMIFS('Reg Setores'!$AF$7:$AF$114,'Reg Setores'!$D$7:$D$114,"ex_2013_14",'Reg Setores'!$C$7:$C$114,$C9) | K9: =SUMIFS('Reg Setores'!$AH$7:$AH$114,'Reg Setores'!$D$7:$D$114,"ex_2013_14",'Reg Setores'!$C$7:$C$114,$C9) | L9: =SUMIFS('Reg Setores'!$AQ$7:$AQ$114,'Reg Setores'!$D$7:$D$114,"ex_2013_14",'Reg Setores'!$C$7:$C$114,$C9)
C10: Real Estate | D10: =SUMIFS('Reg Setores'!$H$7:$H$114,'Reg Setores'!$D$7:$D$114,"ex_2013_14",'Reg Setores'!$C$7:$C$114,$C10) | E10: =SUMIFS('Reg Setores'!$K$7:$K$114,'Reg Setores'!$D$7:$D$114,"ex_2013_14",'Reg Setores'!$C$7:$C$114,$C10) | F10: =SUMIFS('Reg Setores'!$L$7:$L$114,'Reg Setores'!$D$7:$D$114,"ex_2013_14",'Reg Setores'!$C$7:$C$114,$C10) | G10: =SUMIFS('Reg Setores'!$N$7:$N$114,'Reg Setores'!$D$7:$D$114,"ex_2013_14",'Reg Setores'!$C$7:$C$114,$C10) | H10: =SUMIFS('Reg Setores'!$AM$7:$AM$114,'Reg Setores'!$D$7:$D$114,"ex_2013_14",'Reg Setores'!$C$7:$C$114,$C10) | I10: =SUMIFS('Reg Setores'!$AE$7:$AE$114,'Reg Setores'!$D$7:$D$114,"ex_2013_14",'Reg Setores'!$C$7:$C$114,$C10) | J10: =SUMIFS('Reg Setores'!$AF$7:$AF$114,'Reg Setores'!$D$7:$D$114,"ex_2013_14",'Reg Setores'!$C$7:$C$114,$C10) | K10: =SUMIFS('Reg Setores'!$AH$7:$AH$114,'Reg Setores'!$D$7:$D$114,"ex_2013_14",'Reg Setores'!$C$7:$C$114,$C10) | L10: =SUMIFS('Reg Setores'!$AQ$7:$AQ$114,'Reg Setores'!$D$7:$D$114,"ex_2013_14",'Reg Setores'!$C$7:$C$114,$C10)
C11: Consumer Discretionary | D11: =SUMIFS('Reg Setores'!$H$7:$H$114,'Reg Setores'!$D$7:$D$114,"ex_2013_14",'Reg Setores'!$C$7:$C$114,$C11) | E11: =SUMIFS('Reg Setores'!$K$7:$K$114,'Reg Setores'!$D$7:$D$114,"ex_2013_14",'Reg Setores'!$C$7:$C$114,$C11) | F11: =SUMIFS('Reg Setores'!$L$7:$L$114,'Reg Setores'!$D$7:$D$114,"ex_2013_14",'Reg Setores'!$C$7:$C$114,$C11) | G11: =SUMIFS('Reg Setores'!$N$7:$N$114,'Reg Setores'!$D$7:$D$114,"ex_2013_14",'Reg Setores'!$C$7:$C$114,$C11) | H11: =SUMIFS('Reg Setores'!$AM$7:$AM$114,'Reg Setores'!$D$7:$D$114,"ex_2013_14",'Reg Setores'!$C$7:$C$114,$C11) | I11: =SUMIFS('Reg Setores'!$AE$7:$AE$114,'Reg Setores'!$D$7:$D$114,"ex_2013_14",'Reg Setores'!$C$7:$C$114,$C11) | J11: =SUMIFS('Reg Setores'!$AF$7:$AF$114,'Reg Setores'!$D$7:$D$114,"ex_2013_14",'Reg Setores'!$C$7:$C$114,$C11) | K11: =SUMIFS('Reg Setores'!$AH$7:$AH$114,'Reg Setores'!$D$7:$D$114,"ex_2013_14",'Reg Setores'!$C$7:$C$114,$C11) | L11: =SUMIFS('Reg Setores'!$AQ$7:$AQ$114,'Reg Setores'!$D$7:$D$114,"ex_2013_14",'Reg Setores'!$C$7:$C$114,$C11)
C12: Industrials | D12: =SUMIFS('Reg Setores'!$H$7:$H$114,'Reg Setores'!$D$7:$D$114,"ex_2013_14",'Reg Setores'!$C$7:$C$114,$C12) | E12: =SUMIFS('Reg Setores'!$K$7:$K$114,'Reg Setores'!$D$7:$D$114,"ex_2013_14",'Reg Setores'!$C$7:$C$114,$C12) | F12: =SUMIFS('Reg Setores'!$L$7:$L$114,'Reg Setores'!$D$7:$D$114,"ex_2013_14",'Reg Setores'!$C$7:$C$114,$C12) | G12: =SUMIFS('Reg Setores'!$N$7:$N$114,'Reg Setores'!$D$7:$D$114,"ex_2013_14",'Reg Setores'!$C$7:$C$114,$C12) | H12: =SUMIFS('Reg Setores'!$AM$7:$AM$114,'Reg Setores'!$D$7:$D$114,"ex_2013_14",'Reg Setores'!$C$7:$C$114,$C12) | I12: =SUMIFS('Reg Setores'!$AE$7:$AE$114,'Reg Setores'!$D$7:$D$114,"ex_2013_14",'Reg Setores'!$C$7:$C$114,$C12) | J12: =SUMIFS('Reg Setores'!$AF$7:$AF$114,'Reg Setores'!$D$7:$D$114,"ex_2013_14",'Reg Setores'!$C$7:$C$114,$C12) | K12: =SUMIFS('Reg Setores'!$AH$7:$AH$114,'Reg Setores'!$D$7:$D$114,"ex_2013_14",'Reg Setores'!$C$7:$C$114,$C12) | L12: =SUMIFS('Reg Setores'!$AQ$7:$AQ$114,'Reg Setores'!$D$7:$D$114,"ex_2013_14",'Reg Setores'!$C$7:$C$114,$C12)
C13: Financials | D13: =SUMIFS('Reg Setores'!$H$7:$H$114,'Reg Setores'!$D$7:$D$114,"ex_2013_14",'Reg Setores'!$C$7:$C$114,$C13) | E13: =SUMIFS('Reg Setores'!$K$7:$K$114,'Reg Setores'!$D$7:$D$114,"ex_2013_14",'Reg Setores'!$C$7:$C$114,$C13) | F13: =SUMIFS('Reg Setores'!$L$7:$L$114,'Reg Setores'!$D$7:$D$114,"ex_2013_14",'Reg Setores'!$C$7:$C$114,$C13) | G13: =SUMIFS('Reg Setores'!$N$7:$N$114,'Reg Setores'!$D$7:$D$114,"ex_2013_14",'Reg Setores'!$C$7:$C$114,$C13) | H13: =SUMIFS('Reg Setores'!$AM$7:$AM$114,'Reg Setores'!$D$7:$D$114,"ex_2013_14",'Reg Setores'!$C$7:$C$114,$C13) | I13: =SUMIFS('Reg Setores'!$AE$7:$AE$114,'Reg Setores'!$D$7:$D$114,"ex_2013_14",'Reg Setores'!$C$7:$C$114,$C13) | J13: =SUMIFS('Reg Setores'!$AF$7:$AF$114,'Reg Setores'!$D$7:$D$114,"ex_2013_14",'Reg Setores'!$C$7:$C$114,$C13) | K13: =SUMIFS('Reg Setores'!$AH$7:$AH$114,'Reg Setores'!$D$7:$D$114,"ex_2013_14",'Reg Setores'!$C$7:$C$114,$C13) | L13: =SUMIFS('Reg Setores'!$AQ$7:$AQ$114,'Reg Setores'!$D$7:$D$114,"ex_2013_14",'Reg Setores'!$C$7:$C$114,$C13)
C14: Materials | D14: =SUMIFS('Reg Setores'!$H$7:$H$114,'Reg Setores'!$D$7:$D$114,"ex_2013_14",'Reg Setores'!$C$7:$C$114,$C14) | E14: =SUMIFS('Reg Setores'!$K$7:$K$114,'Reg Setores'!$D$7:$D$114,"ex_2013_14",'Reg Setores'!$C$7:$C$114,$C14) | F14: =SUMIFS('Reg Setores'!$L$7:$L$114,'Reg Setores'!$D$7:$D$114,"ex_2013_14",'Reg Setores'!$C$7:$C$114,$C14) | G14: =SUMIFS('Reg Setores'!$N$7:$N$114,'Reg Setores'!$D$7:$D$114,"ex_2013_14",'Reg Setores'!$C$7:$C$114,$C14) | H14: =SUMIFS('Reg Setores'!$AM$7:$AM$114,'Reg Setores'!$D$7:$D$114,"ex_2013_14",'Reg Setores'!$C$7:$C$114,$C14) | I14: =SUMIFS('Reg Setores'!$AE$7:$AE$114,'Reg Setores'!$D$7:$D$114,"ex_2013_14",'Reg Setores'!$C$7:$C$114,$C14) | J14: =SUMIFS('Reg Setores'!$AF$7:$AF$114,'Reg Setores'!$D$7:$D$114,"ex_2013_14",'Reg Setores'!$C$7:$C$114,$C14) | K14: =SUMIFS('Reg Setores'!$AH$7:$AH$114,'Reg Setores'!$D$7:$D$114,"ex_2013_14",'Reg Setores'!$C$7:$C$114,$C14) | L14: =SUMIFS('Reg Setores'!$AQ$7:$AQ$114,'Reg Setores'!$D$7:$D$114,"ex_2013_14",'Reg Setores'!$C$7:$C$114,$C14)
C15: Utilities | D15: =SUMIFS('Reg Setores'!$H$7:$H$114,'Reg Setores'!$D$7:$D$114,"ex_2013_14",'Reg Setores'!$C$7:$C$114,$C15) | E15: =SUMIFS('Reg Setores'!$K$7:$K$114,'Reg Setores'!$D$7:$D$114,"ex_2013_14",'Reg Setores'!$C$7:$C$114,$C15) | F15: =SUMIFS('Reg Setores'!$L$7:$L$114,'Reg Setores'!$D$7:$D$114,"ex_2013_14",'Reg Setores'!$C$7:$C$114,$C15) | G15: =SUMIFS('Reg Setores'!$N$7:$N$114,'Reg Setores'!$D$7:$D$114,"ex_2013_14",'Reg Setores'!$C$7:$C$114,$C15) | H15: =SUMIFS('Reg Setores'!$AM$7:$AM$114,'Reg Setores'!$D$7:$D$114,"ex_2013_14",'Reg Setores'!$C$7:$C$114,$C15) | I15: =SUMIFS('Reg Setores'!$AE$7:$AE$114,'Reg Setores'!$D$7:$D$114,"ex_2013_14",'Reg Setores'!$C$7:$C$114,$C15) | J15: =SUMIFS('Reg Setores'!$AF$7:$AF$114,'Reg Setores'!$D$7:$D$114,"ex_2013_14",'Reg Setores'!$C$7:$C$114,$C15) | K15: =SUMIFS('Reg Setores'!$AH$7:$AH$114,'Reg Setores'!$D$7:$D$114,"ex_2013_14",'Reg Setores'!$C$7:$C$114,$C15) | L15: =SUMIFS('Reg Setores'!$AQ$7:$AQ$114,'Reg Setores'!$D$7:$D$114,"ex_2013_14",'Reg Setores'!$C$7:$C$114,$C15)
C16: Consumer Staples | D16: =SUMIFS('Reg Setores'!$H$7:$H$114,'Reg Setores'!$D$7:$D$114,"ex_2013_14",'Reg Setores'!$C$7:$C$114,$C16) | E16: =SUMIFS('Reg Setores'!$K$7:$K$114,'Reg Setores'!$D$7:$D$114,"ex_2013_14",'Reg Setores'!$C$7:$C$114,$C16) | F16: =SUMIFS('Reg Setores'!$L$7:$L$114,'Reg Setores'!$D$7:$D$114,"ex_2013_14",'Reg Setores'!$C$7:$C$114,$C16) | G16: =SUMIFS('Reg Setores'!$N$7:$N$114,'Reg Setores'!$D$7:$D$114,"ex_2013_14",'Reg Setores'!$C$7:$C$114,$C16) | H16: =SUMIFS('Reg Setores'!$AM$7:$AM$114,'Reg Setores'!$D$7:$D$114,"ex_2013_14",'Reg Setores'!$C$7:$C$114,$C16) | I16: =SUMIFS('Reg Setores'!$AE$7:$AE$114,'Reg Setores'!$D$7:$D$114,"ex_2013_14",'Reg Setores'!$C$7:$C$114,$C16) | J16: =SUMIFS('Reg Setores'!$AF$7:$AF$114,'Reg Setores'!$D$7:$D$114,"ex_2013_14",'Reg Setores'!$C$7:$C$114,$C16) | K16: =SUMIFS('Reg Setores'!$AH$7:$AH$114,'Reg Setores'!$D$7:$D$114,"ex_2013_14",'Reg Setores'!$C$7:$C$114,$C16) | L16: =SUMIFS('Reg Setores'!$AQ$7:$AQ$114,'Reg Setores'!$D$7:$D$114,"ex_2013_14",'Reg Setores'!$C$7:$C$114,$C16)
C17: Health Care | D17: =SUMIFS('Reg Setores'!$H$7:$H$114,'Reg Setores'!$D$7:$D$114,"ex_2013_14",'Reg Setores'!$C$7:$C$114,$C17) | E17: =SUMIFS('Reg Setores'!$K$7:$K$114,'Reg Setores'!$D$7:$D$114,"ex_2013_14",'Reg Setores'!$C$7:$C$114,$C17) | F17: =SUMIFS('Reg Setores'!$L$7:$L$114,'Reg Setores'!$D$7:$D$114,"ex_2013_14",'Reg Setores'!$C$7:$C$114,$C17) | G17: =SUMIFS('Reg Setores'!$N$7:$N$114,'Reg Setores'!$D$7:$D$114,"ex_2013_14",'Reg Setores'!$C$7:$C$114,$C17) | H17: =SUMIFS('Reg Setores'!$AM$7:$AM$114,'Reg Setores'!$D$7:$D$114,"ex_2013_14",'Reg Setores'!$C$7:$C$114,$C17) | I17: =SUMIFS('Reg Setores'!$AE$7:$AE$114,'Reg Setores'!$D$7:$D$114,"ex_2013_14",'Reg Setores'!$C$7:$C$114,$C17) | J17: =SUMIFS('Reg Setores'!$AF$7:$AF$114,'Reg Setores'!$D$7:$D$114,"ex_2013_14",'Reg Setores'!$C$7:$C$114,$C17) | K17: =SUMIFS('Reg Setores'!$AH$7:$AH$114,'Reg Setores'!$D$7:$D$114,"ex_2013_14",'Reg Setores'!$C$7:$C$114,$C17) | L17: =SUMIFS('Reg Setores'!$AQ$7:$AQ$114,'Reg Setores'!$D$7:$D$114,"ex_2013_14",'Reg Setores'!$C$7:$C$114,$C17)
C18: Communication Services | D18: =SUMIFS('Reg Setores'!$H$7:$H$114,'Reg Setores'!$D$7:$D$114,"ex_2013_14",'Reg Setores'!$C$7:$C$114,$C18) | E18: =SUMIFS('Reg Setores'!$K$7:$K$114,'Reg Setores'!$D$7:$D$114,"ex_2013_14",'Reg Setores'!$C$7:$C$114,$C18) | F18: =SUMIFS('Reg Setores'!$L$7:$L$114,'Reg Setores'!$D$7:$D$114,"ex_2013_14",'Reg Setores'!$C$7:$C$114,$C18) | G18: =SUMIFS('Reg Setores'!$N$7:$N$114,'Reg Setores'!$D$7:$D$114,"ex_2013_14",'Reg Setores'!$C$7:$C$114,$C18) | H18: =SUMIFS('Reg Setores'!$AM$7:$AM$114,'Reg Setores'!$D$7:$D$114,"ex_2013_14",'Reg Setores'!$C$7:$C$114,$C18) | I18: =SUMIFS('Reg Setores'!$AE$7:$AE$114,'Reg Setores'!$D$7:$D$114,"ex_2013_14",'Reg Setores'!$C$7:$C$114,$C18) | J18: =SUMIFS('Reg Setores'!$AF$7:$AF$114,'Reg Setores'!$D$7:$D$114,"ex_2013_14",'Reg Setores'!$C$7:$C$114,$C18) | K18: =SUMIFS('Reg Setores'!$AH$7:$AH$114,'Reg Setores'!$D$7:$D$114,"ex_2013_14",'Reg Setores'!$C$7:$C$114,$C18) | L18: =SUMIFS('Reg Setores'!$AQ$7:$AQ$114,'Reg Setores'!$D$7:$D$114,"ex_2013_14",'Reg Setores'!$C$7:$C$114,$C18)
C19: Information Technology | D19: =SUMIFS('Reg Setores'!$H$7:$H$114,'Reg Setores'!$D$7:$D$114,"ex_2013_14",'Reg Setores'!$C$7:$C$114,$C19) | E19: =SUMIFS('Reg Setores'!$K$7:$K$114,'Reg Setores'!$D$7:$D$114,"ex_2013_14",'Reg Setores'!$C$7:$C$114,$C19) | F19: =SUMIFS('Reg Setores'!$L$7:$L$114,'Reg Setores'!$D$7:$D$114,"ex_2013_14",'Reg Setores'!$C$7:$C$114,$C19) | G19: =SUMIFS('Reg Setores'!$N$7:$N$114,'Reg Setores'!$D$7:$D$114,"ex_2013_14",'Reg Setores'!$C$7:$C$114,$C19) | H19: =SUMIFS('Reg Setores'!$AM$7:$AM$114,'Reg Setores'!$D$7:$D$114,"ex_2013_14",'Reg Setores'!$C$7:$C$114,$C19) | I19: =SUMIFS('Reg Setores'!$AE$7:$AE$114,'Reg Setores'!$D$7:$D$114,"ex_2013_14",'Reg Setores'!$C$7:$C$114,$C19) | J19: =SUMIFS('Reg Setores'!$AF$7:$AF$114,'Reg Setores'!$D$7:$D$114,"ex_2013_14",'Reg Setores'!$C$7:$C$114,$C19) | K19: =SUMIFS('Reg Setores'!$AH$7:$AH$114,'Reg Setores'!$D$7:$D$114,"ex_2013_14",'Reg Setores'!$C$7:$C$114,$C19) | L19: =SUMIFS('Reg Setores'!$AQ$7:$AQ$114,'Reg Setores'!$D$7:$D$114,"ex_2013_14",'Reg Setores'!$C$7:$C$114,$C19)
C22: Leitura | D22: Energy | E22: Consumer Discretionary | F22: Financials | G22: Materials
C23: Focus q BH < 10% | D23: Sim | E23: Sim | F23: Sim | G23: Sim
C24: Swap q BH < 10% | D24: Não | E24: Não | F24: Não | G24: Não
C25: Conclusão | D25: Energia lidera, mas o resultado é concentrado em Petrobras.

Sheet Sens Focus-Swap
C2: Matriz de sensibilidade: Focus PIB e swap pré-DI
C3: Impacto estimado sobre a revisão de earnings de três meses do BEst EPS do IBOV. Amostra ex_2013_14.
C6: Parâmetros do modelo
C7: Parâmetro | D7: Valor | E7: p-valor HAC | F7: Unidade | G7: Observação
C8: Beta Focus PIB | D8: =SUMIFS('Reg IBOV'!$J$7:$J$26,'Reg IBOV'!$D$7:$D$26,"ex_2013_14",'Reg IBOV'!$I$7:$I$26,"d_focus_pib3") | E8: =SUMIFS('Reg IBOV'!$N$7:$N$26,'Reg IBOV'!$D$7:$D$26,"ex_2013_14",'Reg IBOV'!$I$7:$I$26,"d_focus_pib3") | F8: % revisão / 1 p.p. | G8: Coeficiente contemporâneo
C9: Beta swap 360d | D9: =SUMIFS('Reg IBOV'!$J$7:$J$26,'Reg IBOV'!$D$7:$D$26,"ex_2013_14",'Reg IBOV'!$I$7:$I$26,"d_swap360_3") | E9: =SUMIFS('Reg IBOV'!$N$7:$N$26,'Reg IBOV'!$D$7:$D$26,"ex_2013_14",'Reg IBOV'!$I$7:$I$26,"d_swap360_3") | F9: % revisão / 1 p.p. | G9: Sinal positivo na amostra principal
C10: R² | D10: =SUMIFS('Reg IBOV'!$G$7:$G$26,'Reg IBOV'!$D$7:$D$26,"ex_2013_14",'Reg IBOV'!$I$7:$I$26,"d_focus_pib3") | F10: proporção | G10: Modelo com cinco variáveis
C11: Amostra | D11: ex_2013_14 | G11: 2013-2014 excluídos
C14: Revisão prevista de earnings em três meses (%) | M14: Matriz arquivada da análise original
C16: Focus Δ (p.p.) | D16: -3 | E16: -2 | F16: -1 | G16: 0 | H16: 1 | I16: 2 | J16: 3 | M16: focus_delta_pp | N16: swap_-3.00pp | O16: swap_-2.00pp | P16: swap_-1.00pp | Q16: swap_+0.00pp | R16: swap_+1.00pp | S16: swap_+2.00pp | T16: swap_+3.00pp
C17: -1 | D17: =$D$8*$C17+$D$9*D$16 | E17: =$D$8*$C17+$D$9*E$16 | F17: =$D$8*$C17+$D$9*F$16 | G17: =$D$8*$C17+$D$9*G$16 | H17: =$D$8*$C17+$D$9*H$16 | I17: =$D$8*$C17+$D$9*I$16 | J17: =$D$8*$C17+$D$9*J$16 | M17: -1 | N17: -11.197462 | O17: -9.465982 | P17: -7.7345022 | Q17: -6.0030225 | R17: -4.2715427 | S17: -2.5400629 | T17: -0.80858315
C18: -0.75 | D18: =$D$8*$C18+$D$9*D$16 | E18: =$D$8*$C18+$D$9*E$16 | F18: =$D$8*$C18+$D$9*F$16 | G18: =$D$8*$C18+$D$9*G$16 | H18: =$D$8*$C18+$D$9*H$16 | I18: =$D$8*$C18+$D$9*I$16 | J18: =$D$8*$C18+$D$9*J$16 | M18: -0.75 | N18: -9.6967062 | O18: -7.9652264 | P18: -6.2337466 | Q18: -4.5022669 | R18: -2.7707871 | S18: -1.0393073 | T18: 0.69217247
C19: -0.5 | D19: =$D$8*$C19+$D$9*D$16 | E19: =$D$8*$C19+$D$9*E$16 | F19: =$D$8*$C19+$D$9*F$16 | G19: =$D$8*$C19+$D$9*G$16 | H19: =$D$8*$C19+$D$9*H$16 | I19: =$D$8*$C19+$D$9*I$16 | J19: =$D$8*$C19+$D$9*J$16 | M19: -0.5 | N19: -8.1959506 | O19: -6.4644708 | P19: -4.732991 | Q19: -3.0015112 | R19: -1.2700315 | S19: 0.46144831 | T19: 2.1929281
C20: -0.25 | D20: =$D$8*$C20+$D$9*D$16 | E20: =$D$8*$C20+$D$9*E$16 | F20: =$D$8*$C20+$D$9*F$16 | G20: =$D$8*$C20+$D$9*G$16 | H20: =$D$8*$C20+$D$9*H$16 | I20: =$D$8*$C20+$D$9*I$16 | J20: =$D$8*$C20+$D$9*J$16 | M20: -0.25 | N20: -6.6951949 | O20: -4.9637152 | P20: -3.2322354 | Q20: -1.5007556 | R20: 0.23072416 | S20: 1.9622039 | T20: 3.6936837
C21: 0 | D21: =$D$8*$C21+$D$9*D$16 | E21: =$D$8*$C21+$D$9*E$16 | F21: =$D$8*$C21+$D$9*F$16 | G21: =$D$8*$C21+$D$9*G$16 | H21: =$D$8*$C21+$D$9*H$16 | I21: =$D$8*$C21+$D$9*I$16 | J21: =$D$8*$C21+$D$9*J$16 | M21: 0 | N21: -5.1944393 | O21: -3.4629595 | P21: -1.7314798 | Q21: 0 | R21: 1.7314798 | S21: 3.4629595 | T21: 5.1944393
C22: 0.25 | D22: =$D$8*$C22+$D$9*D$16 | E22: =$D$8*$C22+$D$9*E$16 | F22: =$D$8*$C22+$D$9*F$16 | G22: =$D$8*$C22+$D$9*G$16 | H22: =$D$8*$C22+$D$9*H$16 | I22: =$D$8*$C22+$D$9*I$16 | J22: =$D$8*$C22+$D$9*J$16 | M22: 0.25 | N22: -3.6936837 | O22: -1.9622039 | P22: -0.23072416 | Q22: 1.5007556 | R22: 3.2322354 | S22: 4.9637152 | T22: 6.6951949
C23: 0.5 | D23: =$D$8*$C23+$D$9*D$16 | E23: =$D$8*$C23+$D$9*E$16 | F23: =$D$8*$C23+$D$9*F$16 | G23: =$D$8*$C23+$D$9*G$16 | H23: =$D$8*$C23+$D$9*H$16 | I23: =$D$8*$C23+$D$9*I$16 | J23: =$D$8*$C23+$D$9*J$16 | M23: 0.5 | N23: -2.1929281 | O23: -0.46144831 | P23: 1.2700315 | Q23: 3.0015112 | R23: 4.732991 | S23: 6.4644708 | T23: 8.1959506
M25: Checagem | N25: Máximo entre três diferenças
C26: Interpretação | D26: A matriz combina mecanicamente os dois coeficientes. O beta positivo do swap não prova que juros maiores elevam lucros; o sinal perde significância em outras janelas e pode refletir composição, bancos e variáveis omitidas. | N26: =MAX(ABS(D17-N17),ABS(G20-Q20),ABS(J23-T23))

Sheet Inflacao
C2: Teste de inflação: realizado e expectativa Focus
C3: Comparação incremental contra o modelo-base com Focus PIB, BCOM e USD/BRL.
C6: Resultado principal - amostra ex_2013_14
C7: Candidato | D7: ΔR² | E7: Beta pad. | F7: p-valor HAC | G7: Leitura | H7: Uso no modelo final
C8: Focus IPCA | D8: =SUMIFS('Inflacao'!$K$15:$K$26,'Inflacao'!$C$15:$C$26,"ex_2013_14",'Inflacao'!$D$15:$D$26,"d_focus_ipca3") | E8: =SUMIFS('Inflacao'!$Q$15:$Q$26,'Inflacao'!$C$15:$C$26,"ex_2013_14",'Inflacao'!$D$15:$D$26,"d_focus_ipca3") | F8: =SUMIFS('Inflacao'!$P$15:$P$26,'Inflacao'!$C$15:$C$26,"ex_2013_14",'Inflacao'!$D$15:$D$26,"d_focus_ipca3") | G8: Boa associação na amostra principal | H8: Teste alternativo
C9: IPCA realizado 12m | D9: =SUMIFS('Inflacao'!$K$15:$K$26,'Inflacao'!$C$15:$C$26,"ex_2013_14",'Inflacao'!$D$15:$D$26,"d_ipca12_3_available") | E9: =SUMIFS('Inflacao'!$Q$15:$Q$26,'Inflacao'!$C$15:$C$26,"ex_2013_14",'Inflacao'!$D$15:$D$26,"d_ipca12_3_available") | F9: =SUMIFS('Inflacao'!$P$15:$P$26,'Inflacao'!$C$15:$C$26,"ex_2013_14",'Inflacao'!$D$15:$D$26,"d_ipca12_3_available") | G9: Maior ΔR² por pequena margem | H9: Selecionado
C10: Fluxo IPCA 3m | D10: =SUMIFS('Inflacao'!$K$15:$K$26,'Inflacao'!$C$15:$C$26,"ex_2013_14",'Inflacao'!$D$15:$D$26,"ipca3_flow_available") | E10: =SUMIFS('Inflacao'!$Q$15:$Q$26,'Inflacao'!$C$15:$C$26,"ex_2013_14",'Inflacao'!$D$15:$D$26,"ipca3_flow_available") | F10: =SUMIFS('Inflacao'!$P$15:$P$26,'Inflacao'!$C$15:$C$26,"ex_2013_14",'Inflacao'!$D$15:$D$26,"ipca3_flow_available") | G10: Mais fraco nesta especificação | H10: Não selecionado
C12: Resultados completos
C14: sample | D14: candidate | E14: start | F14: end | G14: n | H14: univariate_r2 | I14: base_r2 | J14: augmented_r2 | K14: delta_r2 | L14: delta_adj_r2 | M14: beta | N14: se_hac | O14: t_hac | P14: p_hac | Q14: beta_std
C15: full | D15: d_focus_ipca3 | E15: 39904 | F15: 46235 | G15: 209 | H15: 0.051087078 | I15: 0.19438588 | J15: 0.21666739 | K15: 0.022281511 | L15: 0.018639603 | M15: 4.3769951 | N15: 1.9620999 | O15: 2.2307708 | P15: 0.025696313 | Q15: 0.15618556
C16: full | D16: d_ipca12_3_available | E16: 39904 | F16: 46204 | G16: 208 | H16: 0.034625008 | I16: 0.19439343 | J16: 0.23067588 | K16: 0.036282442 | L16: 0.032828428 | M16: 2.3880205 | N16: 0.92459688 | O16: 2.5827694 | P16: 0.0098010809 | Q16: 0.19433206
C17: full | D17: ipca3_flow_available | E17: 39904 | F17: 46204 | G17: 208 | H17: 0.027085052 | I17: 0.19439343 | J17: 0.24320066 | K17: 0.048807227 | L17: 0.045537401 | M17: 3.4624943 | N17: 1.5639023 | O17: 2.2140093 | P17: 0.02682814 | Q17: 0.22296106
C18: ex_2013_14 | D18: d_focus_ipca3 | E18: 39904 | F18: 46235 | G18: 185 | H18: 0.13375353 | I18: 0.38223352 | J18: 0.45247777 | K18: 0.070244248 | L18: 0.067957937 | M18: 5.1884298 | N18: 1.9986835 | O18: 2.5959236 | P18: 0.0094337029 | Q18: 0.28068346
C19: ex_2013_14 | D19: d_ipca12_3_available | E19: 39904 | F19: 46204 | G19: 184 | H19: 0.071135062 | I19: 0.38220688 | J19: 0.46016632 | K19: 0.077959433 | L19: 0.075788648 | M19: 2.3279407 | N19: 0.89578869 | O19: 2.598761 | P19: 0.0093560885 | Q19: 0.28650397
C20: ex_2013_14 | D20: ipca3_flow_available | E20: 39904 | F20: 46204 | G20: 184 | H20: 0.022127964 | I20: 0.38220688 | J20: 0.4363602 | K20: 0.054153313 | L20: 0.05158576 | M20: 2.4609109 | N20: 1.3191149 | O20: 1.8655773 | P20: 0.062100525 | Q20: 0.23511163
C21: clean | D21: d_focus_ipca3 | E21: 39904 | F21: 46235 | G21: 161 | H21: 0.0066705469 | I21: 0.13793529 | J21: 0.15172719 | K21: 0.013791902 | L21: 0.0084950789 | M21: 1.6472374 | N21: 1.6108481 | O21: 1.0225901 | P21: 0.30650168 | Q21: 0.12354967
C22: clean | D22: d_ipca12_3_available | E22: 39904 | F22: 46204 | G22: 160 | H22: 0.0012211078 | I22: 0.13789605 | J22: 0.15205383 | K22: 0.01415778 | L22: 0.0088333392 | M22: 0.77310877 | N22: 0.78965519 | O22: 0.97904601 | P22: 0.32755724 | Q22: 0.12601101
C23: clean | D23: ipca3_flow_available | E23: 39904 | F23: 46204 | G23: 160 | H23: 0.0028244294 | I23: 0.13789605 | J23: 0.13890137 | K23: 0.0010053187 | L23: -0.0045720544 | M23: 0.24847881 | N23: 1.148877 | O23: 0.21627973 | P23: 0.82876971 | Q23: 0.032574407
C24: since_2015 | D24: d_focus_ipca3 | E24: 42005 | F24: 46235 | G24: 140 | H24: 0.15108406 | I24: 0.45191784 | J24: 0.52673088 | K24: 0.074813037 | L24: 0.072374476 | M24: 5.1843111 | N24: 2.0365908 | O24: 2.545583 | P24: 0.010909542 | Q24: 0.29091184
C25: since_2015 | D25: d_ipca12_3_available | E25: 42005 | F25: 46204 | G25: 139 | H25: 0.087532335 | I25: 0.45193942 | J25: 0.53098738 | K25: 0.079047957 | L25: 0.076685168 | M25: 2.2659847 | N25: 0.88703712 | O25: 2.5545546 | P25: 0.010632377 | Q25: 0.28928017
C26: since_2015 | D26: ipca3_flow_available | E26: 42005 | F26: 46204 | G26: 139 | H26: 0.023783784 | I26: 0.45193942 | J26: 0.50221027 | K26: 0.050270847 | L26: 0.047268567 | M26: 2.3066925 | N26: 1.4161533 | O26: 1.6288438 | P26: 0.1033461 | Q26: 0.22616223

Sheet Ex-Commodities
C2: IBOV versus IBOV ex-commodities
C3: Comparação da sensibilidade contemporânea ao Focus PIB. O agregado ex-commodities não apresenta beta maior.
C6: Amostra principal
C7: Métrica | D7: IBOV | E7: Ex-commodities | F7: Commodities | G7: Diferença ex-commod. - IBOV | H7: p da diferença
C8: Beta Focus | D8: =SUMIFS('Ex-Commodities'!$H$19:$H$24,'Ex-Commodities'!$C$19:$C$24,"ex_2013_14") | E8: =SUMIFS('Ex-Commodities'!$K$19:$K$24,'Ex-Commodities'!$C$19:$C$24,"ex_2013_14") | F8: =SUMIFS('Ex-Commodities'!$N$19:$N$24,'Ex-Commodities'!$C$19:$C$24,"ex_2013_14") | G8: =SUMIFS('Ex-Commodities'!$Q$19:$Q$24,'Ex-Commodities'!$C$19:$C$24,"ex_2013_14") | H8: =SUMIFS('Ex-Commodities'!$R$19:$R$24,'Ex-Commodities'!$C$19:$C$24,"ex_2013_14")
C9: Beta Focus padronizado | D9: =SUMIFS('Ex-Commodities'!$J$19:$J$24,'Ex-Commodities'!$C$19:$C$24,"ex_2013_14") | E9: =SUMIFS('Ex-Commodities'!$M$19:$M$24,'Ex-Commodities'!$C$19:$C$24,"ex_2013_14") | F9: =SUMIFS('Ex-Commodities'!$P$19:$P$24,'Ex-Commodities'!$C$19:$C$24,"ex_2013_14") | G9: =SUMIFS('Ex-Commodities'!$S$19:$S$24,'Ex-Commodities'!$C$19:$C$24,"ex_2013_14") | H9: =SUMIFS('Ex-Commodities'!$R$19:$R$24,'Ex-Commodities'!$C$19:$C$24,"ex_2013_14")
C10: R² | D10: =SUMIFS('Ex-Commodities'!$T$19:$T$24,'Ex-Commodities'!$C$19:$C$24,"ex_2013_14") | E10: =SUMIFS('Ex-Commodities'!$U$19:$U$24,'Ex-Commodities'!$C$19:$C$24,"ex_2013_14") | F10: =SUMIFS('Ex-Commodities'!$V$19:$V$24,'Ex-Commodities'!$C$19:$C$24,"ex_2013_14") | G10: =SUMIFS('Ex-Commodities'!$Q$19:$Q$24,'Ex-Commodities'!$C$19:$C$24,"ex_2013_14") | H10: =SUMIFS('Ex-Commodities'!$R$19:$R$24,'Ex-Commodities'!$C$19:$C$24,"ex_2013_14")
C12: Conclusão | D12: Na amostra ex_2013_14, o beta Focus do IBOV é 5,69; o ex-commodities é 2,03. A diferença é negativa e estatisticamente significativa.
C16: Resultados completos
C18: sample | D18: start | E18: end | F18: n | G18: corr_targets | H18: beta_focus_ibov | I18: p_focus_ibov | J18: beta_std_focus_ibov | K18: beta_focus_excommod | L18: p_focus_excommod | M18: beta_std_focus_excommod | N18: beta_focus_commodities | O18: p_focus_commodities | P18: beta_std_focus_commodities | Q18: beta_focus_difference | R18: p_focus_difference | S18: beta_std_focus_difference | T18: r2_ibov | U18: r2_excommod | V18: r2_commodities | W18: simple_beta_focus_ibov | X18: simple_beta_focus_excommod | Y18: simple_beta_focus_difference | Z18: simple_p_focus_difference
C19: full | D19: 40269 | E19: 46204 | F19: 196 | G19: 0.77273381 | H19: 5.6838321 | I19: 0 | J19: 0.58492857 | K19: 2.0245882 | L19: 0.0014139298 | M19: 0.42979377 | N19: 16.626687 | O19: 2.220446e-16 | P19: 0.63746331 | Q19: -3.659244 | R19: 7.2922024e-10 | S19: -0.54028435 | T19: 0.52953424 | U19: 0.32539094 | V19: 0.49793704 | W19: 5.8144083 | X19: 1.9599463 | Y19: -3.854462 | Z19: 2.2042355e-09
C20: ex_2013_14 | D20: 40269 | E20: 46204 | F20: 172 | G20: 0.7844963 | H20: 5.6862799 | I20: 0 | J20: 0.58372253 | K20: 2.0316214 | L20: 0.0015772984 | M20: 0.43059679 | N20: 16.77568 | O20: 4.4408921e-16 | P20: 0.64422181 | Q20: -3.6546584 | R20: 1.321248e-09 | S20: -0.54454524 | T20: 0.53074521 | U20: 0.33632929 | V20: 0.49961302 | W20: 5.8148233 | X20: 2.0074505 | Y20: -3.8073729 | Z20: 2.2373849e-09
C21: ex_2020_21 | D21: 40269 | E21: 46204 | F21: 172 | G21: 0.64760949 | H21: 2.97663 | I21: 3.0606539e-05 | J21: 0.29643849 | K21: 0.50906147 | L21: 0.44433621 | M21: 0.11300114 | N21: 11.303102 | O21: 0.00062052781 | P21: 0.35441495 | Q21: -2.4675685 | R21: 0.00028699834 | S21: -0.31204424 | T21: 0.17326481 | U21: 0.099670595 | V21: 0.16525826 | W21: 2.5352897 | X21: 0.32743712 | Y21: -2.2078526 | Z21: 0.009434023
C22: clean | D22: 40269 | E22: 46204 | F22: 148 | G22: 0.67186854 | H22: 2.8658246 | I22: 7.3195393e-05 | J22: 0.28039642 | K22: 0.50961196 | L22: 0.45944161 | M22: 0.11264326 | N22: 11.168532 | O22: 0.0011600299 | P22: 0.34430372 | Q22: -2.3562127 | R22: 0.00037619337 | S22: -0.29733856 | T22: 0.16189714 | U22: 0.12049004 | V22: 0.15527248 | W22: 2.3728469 | X22: 0.33233882 | Y22: -2.0405081 | Z22: 0.016598513
C23: since_2015 | D23: 42005 | E23: 46204 | F23: 139 | G23: 0.78369738 | H23: 5.8920577 | I23: 0 | J23: 0.61634097 | K23: 2.3324491 | L23: 0.00047484391 | M23: 0.50656073 | N23: 17.363721 | O23: 0 | P23: 0.66560903 | Q23: -3.5596085 | R23: 1.5808829e-08 | S23: -0.53910681 | T23: 0.57071757 | U23: 0.37196196 | V23: 0.52395601 | W23: 6.0517688 | X23: 2.1637738 | Y23: -3.8879951 | Z23: 8.309966e-10
C24: since_2022 | D24: 44562 | E24: 46204 | F24: 55 | G24: 0.67015668 | H24: 2.1196906 | I24: 0.30324555 | J24: 0.12331172 | K24: 1.0779143 | L24: 0.23086256 | M24: 0.16545087 | N24: 3.2410841 | O24: 0.41723308 | P24: 0.086284 | Q24: -1.0417764 | R24: 0.47132578 | S24: -0.076014163 | T24: 0.4510281 | U24: 0.38146338 | V24: 0.36019949 | W24: 2.2330527 | X24: 1.3714856 | Y24: -0.86156714 | Z24: 0.71055441

Sheet Energia
C2: Energia, Petrobras e Brent
C3: Decomposição da liderança setorial. A série agregada de Energia é fortemente dominada por Petrobras.
C6: Concentração e correlação
C7: Métrica | D7: Valor | E7: Unidade | F7: Amostra | G7: Leitura | H7: Fonte
C8: Correlação revisions Energia-Petrobras | D8: 0.995009 | E8: correlação | F8: primary | G8: Movimentos quase idênticos | H8: Resumo Energia
C9: Meses Energy = Petrobras | D9: 106 | E9: meses | F9: 225 meses | G9: 47,1% do histórico | H9: Resumo Energia
C10: Participação mediana Petrobras | D10: 0.9212272 | E10: % do setor | F10: desde 2023 | G10: 92,1% do agregado | H10: Resumo Energia
C11: R² univariado Energia-Petrobras | D11: 0.99004291 | E11: proporção | F11: primary | G11: Quase toda variação comum | H11: Resumo Energia
C14: Modelo com Brent - principais amostras
C15: Target | D15: Amostra | E15: n | F15: R² | G15: Focus beta | H15: Focus p | I15: Brent beta | J15: Brent beta pad.
C16: Energy reported | D16: primary | E16: =SUMIFS('Reg Energia'!$H$7:$H$74,'Reg Energia'!$C$7:$C$74,$C16,'Reg Energia'!$D$7:$D$74,$D16,'Reg Energia'!$E$7:$E$74,"Brent") | F16: =SUMIFS('Reg Energia'!$I$7:$I$74,'Reg Energia'!$C$7:$C$74,$C16,'Reg Energia'!$D$7:$D$74,$D16,'Reg Energia'!$E$7:$E$74,"Brent") | G16: =SUMIFS('Reg Energia'!$L$7:$L$74,'Reg Energia'!$C$7:$C$74,$C16,'Reg Energia'!$D$7:$D$74,$D16,'Reg Energia'!$E$7:$E$74,"Brent") | H16: =SUMIFS('Reg Energia'!$O$7:$O$74,'Reg Energia'!$C$7:$C$74,$C16,'Reg Energia'!$D$7:$D$74,$D16,'Reg Energia'!$E$7:$E$74,"Brent") | I16: =SUMIFS('Reg Energia'!$AF$7:$AF$74,'Reg Energia'!$C$7:$C$74,$C16,'Reg Energia'!$D$7:$D$74,$D16,'Reg Energia'!$E$7:$E$74,"Brent") | J16: =SUMIFS('Reg Energia'!$AG$7:$AG$74,'Reg Energia'!$C$7:$C$74,$C16,'Reg Energia'!$D$7:$D$74,$D16,'Reg Energia'!$E$7:$E$74,"Brent")
C17: Petrobras | D17: primary | E17: =SUMIFS('Reg Energia'!$H$7:$H$74,'Reg Energia'!$C$7:$C$74,$C17,'Reg Energia'!$D$7:$D$74,$D17,'Reg Energia'!$E$7:$E$74,"Brent") | F17: =SUMIFS('Reg Energia'!$I$7:$I$74,'Reg Energia'!$C$7:$C$74,$C17,'Reg Energia'!$D$7:$D$74,$D17,'Reg Energia'!$E$7:$E$74,"Brent") | G17: =SUMIFS('Reg Energia'!$L$7:$L$74,'Reg Energia'!$C$7:$C$74,$C17,'Reg Energia'!$D$7:$D$74,$D17,'Reg Energia'!$E$7:$E$74,"Brent") | H17: =SUMIFS('Reg Energia'!$O$7:$O$74,'Reg Energia'!$C$7:$C$74,$C17,'Reg Energia'!$D$7:$D$74,$D17,'Reg Energia'!$E$7:$E$74,"Brent") | I17: =SUMIFS('Reg Energia'!$AF$7:$AF$74,'Reg Energia'!$C$7:$C$74,$C17,'Reg Energia'!$D$7:$D$74,$D17,'Reg Energia'!$E$7:$E$74,"Brent") | J17: =SUMIFS('Reg Energia'!$AG$7:$AG$74,'Reg Energia'!$C$7:$C$74,$C17,'Reg Energia'!$D$7:$D$74,$D17,'Reg Energia'!$E$7:$E$74,"Brent")
C18: Ex-Petrobras dynamic | D18: primary | E18: =SUMIFS('Reg Energia'!$H$7:$H$74,'Reg Energia'!$C$7:$C$74,$C18,'Reg Energia'!$D$7:$D$74,$D18,'Reg Energia'!$E$7:$E$74,"Brent") | F18: =SUMIFS('Reg Energia'!$I$7:$I$74,'Reg Energia'!$C$7:$C$74,$C18,'Reg Energia'!$D$7:$D$74,$D18,'Reg Energia'!$E$7:$E$74,"Brent") | G18: =SUMIFS('Reg Energia'!$L$7:$L$74,'Reg Energia'!$C$7:$C$74,$C18,'Reg Energia'!$D$7:$D$74,$D18,'Reg Energia'!$E$7:$E$74,"Brent") | H18: =SUMIFS('Reg Energia'!$O$7:$O$74,'Reg Energia'!$C$7:$C$74,$C18,'Reg Energia'!$D$7:$D$74,$D18,'Reg Energia'!$E$7:$E$74,"Brent") | I18: =SUMIFS('Reg Energia'!$AF$7:$AF$74,'Reg Energia'!$C$7:$C$74,$C18,'Reg Energia'!$D$7:$D$74,$D18,'Reg Energia'!$E$7:$E$74,"Brent") | J18: =SUMIFS('Reg Energia'!$AG$7:$AG$74,'Reg Energia'!$C$7:$C$74,$C18,'Reg Energia'!$D$7:$D$74,$D18,'Reg Energia'!$E$7:$E$74,"Brent")
C19: Energy reported | D19: audit_clean | E19: =SUMIFS('Reg Energia'!$H$7:$H$74,'Reg Energia'!$C$7:$C$74,$C19,'Reg Energia'!$D$7:$D$74,$D19,'Reg Energia'!$E$7:$E$74,"Brent") | F19: =SUMIFS('Reg Energia'!$I$7:$I$74,'Reg Energia'!$C$7:$C$74,$C19,'Reg Energia'!$D$7:$D$74,$D19,'Reg Energia'!$E$7:$E$74,"Brent") | G19: =SUMIFS('Reg Energia'!$L$7:$L$74,'Reg Energia'!$C$7:$C$74,$C19,'Reg Energia'!$D$7:$D$74,$D19,'Reg Energia'!$E$7:$E$74,"Brent") | H19: =SUMIFS('Reg Energia'!$O$7:$O$74,'Reg Energia'!$C$7:$C$74,$C19,'Reg Energia'!$D$7:$D$74,$D19,'Reg Energia'!$E$7:$E$74,"Brent") | I19: =SUMIFS('Reg Energia'!$AF$7:$AF$74,'Reg Energia'!$C$7:$C$74,$C19,'Reg Energia'!$D$7:$D$74,$D19,'Reg Energia'!$E$7:$E$74,"Brent") | J19: =SUMIFS('Reg Energia'!$AG$7:$AG$74,'Reg Energia'!$C$7:$C$74,$C19,'Reg Energia'!$D$7:$D$74,$D19,'Reg Energia'!$E$7:$E$74,"Brent")
C20: Petrobras | D20: audit_clean | E20: =SUMIFS('Reg Energia'!$H$7:$H$74,'Reg Energia'!$C$7:$C$74,$C20,'Reg Energia'!$D$7:$D$74,$D20,'Reg Energia'!$E$7:$E$74,"Brent") | F20: =SUMIFS('Reg Energia'!$I$7:$I$74,'Reg Energia'!$C$7:$C$74,$C20,'Reg Energia'!$D$7:$D$74,$D20,'Reg Energia'!$E$7:$E$74,"Brent") | G20: =SUMIFS('Reg Energia'!$L$7:$L$74,'Reg Energia'!$C$7:$C$74,$C20,'Reg Energia'!$D$7:$D$74,$D20,'Reg Energia'!$E$7:$E$74,"Brent") | H20: =SUMIFS('Reg Energia'!$O$7:$O$74,'Reg Energia'!$C$7:$C$74,$C20,'Reg Energia'!$D$7:$D$74,$D20,'Reg Energia'!$E$7:$E$74,"Brent") | I20: =SUMIFS('Reg Energia'!$AF$7:$AF$74,'Reg Energia'!$C$7:$C$74,$C20,'Reg Energia'!$D$7:$D$74,$D20,'Reg Energia'!$E$7:$E$74,"Brent") | J20: =SUMIFS('Reg Energia'!$AG$7:$AG$74,'Reg Energia'!$C$7:$C$74,$C20,'Reg Energia'!$D$7:$D$74,$D20,'Reg Energia'!$E$7:$E$74,"Brent")
C21: Energy reported | D21: since_2022_ex_seams | E21: =SUMIFS('Reg Energia'!$H$7:$H$74,'Reg Energia'!$C$7:$C$74,$C21,'Reg Energia'!$D$7:$D$74,$D21,'Reg Energia'!$E$7:$E$74,"Brent") | F21: =SUMIFS('Reg Energia'!$I$7:$I$74,'Reg Energia'!$C$7:$C$74,$C21,'Reg Energia'!$D$7:$D$74,$D21,'Reg Energia'!$E$7:$E$74,"Brent") | G21: =SUMIFS('Reg Energia'!$L$7:$L$74,'Reg Energia'!$C$7:$C$74,$C21,'Reg Energia'!$D$7:$D$74,$D21,'Reg Energia'!$E$7:$E$74,"Brent") | H21: =SUMIFS('Reg Energia'!$O$7:$O$74,'Reg Energia'!$C$7:$C$74,$C21,'Reg Energia'!$D$7:$D$74,$D21,'Reg Energia'!$E$7:$E$74,"Brent") | I21: =SUMIFS('Reg Energia'!$AF$7:$AF$74,'Reg Energia'!$C$7:$C$74,$C21,'Reg Energia'!$D$7:$D$74,$D21,'Reg Energia'!$E$7:$E$74,"Brent") | J21: =SUMIFS('Reg Energia'!$AG$7:$AG$74,'Reg Energia'!$C$7:$C$74,$C21,'Reg Energia'!$D$7:$D$74,$D21,'Reg Energia'!$E$7:$E$74,"Brent")
C22: Petrobras | D22: since_2022_ex_seams | E22: =SUMIFS('Reg Energia'!$H$7:$H$74,'Reg Energia'!$C$7:$C$74,$C22,'Reg Energia'!$D$7:$D$74,$D22,'Reg Energia'!$E$7:$E$74,"Brent") | F22: =SUMIFS('Reg Energia'!$I$7:$I$74,'Reg Energia'!$C$7:$C$74,$C22,'Reg Energia'!$D$7:$D$74,$D22,'Reg Energia'!$E$7:$E$74,"Brent") | G22: =SUMIFS('Reg Energia'!$L$7:$L$74,'Reg Energia'!$C$7:$C$74,$C22,'Reg Energia'!$D$7:$D$74,$D22,'Reg Energia'!$E$7:$E$74,"Brent") | H22: =SUMIFS('Reg Energia'!$O$7:$O$74,'Reg Energia'!$C$7:$C$74,$C22,'Reg Energia'!$D$7:$D$74,$D22,'Reg Energia'!$E$7:$E$74,"Brent") | I22: =SUMIFS('Reg Energia'!$AF$7:$AF$74,'Reg Energia'!$C$7:$C$74,$C22,'Reg Energia'!$D$7:$D$74,$D22,'Reg Energia'!$E$7:$E$74,"Brent") | J22: =SUMIFS('Reg Energia'!$AG$7:$AG$74,'Reg Energia'!$C$7:$C$74,$C22,'Reg Energia'!$D$7:$D$74,$D22,'Reg Energia'!$E$7:$E$74,"Brent")
C24: Conclusão | D24: A sensibilidade de Energia ao Focus no histórico vem quase integralmente de Petrobras. Desde 2022, Focus deixa de ser significativo, enquanto Brent ganha força explicativa para Energia e Petrobras.

Sheet Earnings 12M Fwd
C2: Earnings 12 meses forward por setor
C3: BEst Net Income agregado, em BRL. Frequência mensal, janeiro de 2008 a setembro de 2026.
C6: month | D6: date | E6: source_file | F6: IBOV | G6: Communication Services | H6: Consumer Discretionary | I6: Consumer Staples | J6: Energy | K6: Financials | L6: Health Care | M6: Industrials | N6: Information Technology | O6: Materials | P6: Real Estate | Q6: Utilities | R6: Not Classified
C7: 39448 | D7: 39478 | E7: grid_20qvjmd3.xlsx | F7: 9959.8781 | G7: 730.2102 | H7: 310.7799 | I7: 1538.5402 | J7: 29432.834 | K7: 7614.5858 | M7: 659.91204 | O7: 13618.164 | P7: 0 | Q7: 1217.2182 | R7: 1487.481
C8: 39479 | D8: 39507 | E8: grid_20qvjmd3.xlsx | F8: 10289.607 | G8: 799.94292 | H8: 322.53156 | I8: 1573.9043 | J8: 29645.202 | K8: 7762.6191 | M8: 623.17107 | O8: 14526.618 | P8: 0 | Q8: 1242.4285 | R8: 1474.0469
C9: 39508 | D9: 39538 | E9: grid_20qvjmd3.xlsx | F9: 10303.867 | G9: 747.09409 | H9: 295.13034 | I9: 1515.5028 | J9: 30769.554 | K9: 7843.4509 | M9: 615.38921 | O9: 14775.051 | P9: 0 | Q9: 1312.0471 | R9: 1479.4428
C10: 39539 | D10: 39568 | E10: grid_20qvjmd3.xlsx | F10: 10682.523 | G10: 711.0442 | H10: 300.91403 | I10: 1451.0769 | J10: 30957.47 | K10: 7909.4795 | M10: 601.75089 | O10: 15217.403 | P10: 0 | Q10: 1381.0617 | R10: 1445.746
C11: 39569 | D11: 39598 | E11: grid_20qvjmd3.xlsx | F11: 12096.372 | G11: 728.05057 | H11: 316.88361 | I11: 1504.6715 | J11: 32324.668 | K11: 7871.6928 | M11: 560.65459 | O11: 16212.108 | P11: 15.079452 | Q11: 1352.8194 | R11: 1468.2037
C12: 39600 | D12: 39629 | E12: grid_20qvjmd3.xlsx | F12: 12518.425 | G12: 698.83604 | H12: 312.29658 | I12: 1526.8364 | J12: 32989.739 | K12: 7885.199 | M12: 550.09937 | O12: 16313.358 | P12: 32.887671 | Q12: 1312.6731 | R12: 1429.9287
C13: 39630 | D13: 39660 | E13: grid_20qvjmd3.xlsx | F13: 11614.211 | G13: 737.06608 | H13: 294.20667 | I13: 1419.8973 | J13: 34314.985 | K13: 7863.2461 | M13: 526.79196 | O13: 16167.317 | P13: 33.142466 | Q13: 1358.7449 | R13: 1440.5456
C14: 39661 | D14: 39689 | E14: grid_20qvjmd3.xlsx | F14: 12104.025 | G14: 704.56496 | H14: 302.12598 | I14: 1507.0539 | J14: 34896.378 | K14: 7875.0501 | M14: 562.0758 | O14: 17087.953 | P14: 33.380822 | Q14: 1408.5327 | R14: 1464.0215
C15: 39692 | D15: 39721 | E15: grid_20qvjmd3.xlsx | F15: 14266.987 | G15: 648.71691 | H15: 363.48552 | I15: 1740.5418 | J15: 36268.299 | K15: 6828.52 | M15: 570.98461 | O15: 19240.008 | Q15: 1547.7116 | R15: 1549.4413
C16: 39722 | D16: 39752 | E16: grid_20qvjmd3.xlsx | F16: 13115.579 | G16: 651.81029 | H16: 372.63442 | I16: 1602.3352 | J16: 34382.252 | K16: 6519.0678 | M16: 615.47934 | O16: 19187.929 | Q16: 1649.2131 | R16: 1504.1739
C17: 39753 | D17: 39780 | E17: grid_20qvjmd3.xlsx | F17: 11850.102 | G17: 607.49416 | H17: 374.84868 | I17: 1660.5916 | J17: 33491.21 | K17: 6650.3507 | M17: 564.2881 | O17: 18370.268 | Q17: 1679.6568 | R17: 1435.6145
C18: 39783 | D18: 39813 | E18: grid_20qvjmd3.xlsx | F18: 11084.465 | G18: 670.9664 | H18: 379.83185 | I18: 1698.7055 | J18: 29096.401 | K18: 6484.0951 | M18: 578.34412 | O18: 15653.676 | Q18: 1771.2051 | R18: 1351.3939
C19: 39814 | D19: 39843 | E19: grid_20qvjmd3.xlsx | F19: 11033.739 | G19: 640.17612 | H19: 347.01657 | I19: 1563.1346 | J19: 26792.882 | K19: 5406.3233 | M19: 540.54578 | O19: 13243.352 | Q19: 1779.3234 | R19: 1135.9492
C20: 39845 | D20: 39871 | E20: grid_20qvjmd3.xlsx | F20: 11190.357 | G20: 645.2784 | H20: 328.20651 | I20: 1504.9584 | J20: 27042.788 | K20: 5467.7979 | M20: 525.43514 | O20: 12737.026 | Q20: 1765.0099 | R20: 1192.0434
C21: 39873 | D21: 39903 | E21: grid_20qvjmd3.xlsx | F21: 9959.6275 | G21: 630.3768 | H21: 340.80954 | I21: 1622.1641 | J21: 24508.116 | K21: 5928.7117 | M21: 546.01697 | O21: 9925.1371 | Q21: 1873.3138 | R21: 820.10453
C22: 39904 | D22: 39933 | E22: grid_20qvjmd3.xlsx | F22: 9074.784 | G22: 629.58648 | H22: 333.6687 | I22: 1658.3479 | J22: 23604.085 | K22: 6085.9008 | M22: 525.99031 | O22: 9126.5962 | Q22: 1866.2613 | R22: 727.80768
C23: 39934 | D23: 39962 | E23: grid_20qvjmd3.xlsx | F23: 9195.7719 | G23: 638.47895 | H23: 339.31323 | I23: 1772.2349 | J23: 25104.484 | K23: 6117.9407 | M23: 493.3957 | O23: 8106.9492 | Q23: 1833.8755 | R23: 660.49468
C24: 39965 | D24: 39994 | E24: grid_20qvjmd3.xlsx | F24: 8893.8981 | G24: 664.9811 | H24: 352.41646 | I24: 1886.2962 | J24: 25090.749 | K24: 6197.1161 | M24: 451.67579 | O24: 7502.1873 | Q24: 1790.4215 | R24: 680.26612
C25: 39995 | D25: 40025 | E25: grid_20qvjmd3.xlsx | F25: 8563.7339 | G25: 662.31383 | H25: 353.15989 | I25: 1900.1433 | J25: 25347.72 | K25: 6435.6718 | M25: 443.422 | O25: 7340.7243 | Q25: 1799.9765 | R25: 615.99822
C26: 40026 | D26: 40056 | E26: grid_20qvjmd3.xlsx | F26: 8388.6174 | G26: 670.24742 | H26: 378.10991 | I26: 1999.4413 | J26: 25339.542 | K26: 6759.6343 | M26: 443.33358 | O26: 7170.4337 | Q26: 1775.9242 | R26: 596.93812
... C42: 40513 | D42: 40543 | E42: grid_20qvjmd3.xlsx | F42: 12597.863 | G42: 1081.8309 | H42: 796.76356 | I42: 2149.2761 | J42: 28108.46 | K42: 8337.9013 | M42: 490.4191 | O42: 20834.845 | Q42: 1741.8561 | R42: 1154.9933
C43: 40544 | D43: 40574 | E43: grid_u4lflnxf.xlsx | F43: 13177.516 | G43: 1126.5085 | H43: 813.82382 | I43: 1953.6148 | J43: 27471.717 | K43: 8650.6158 | L43: 554.65455 | M43: 495.63938 | O43: 21251.872 | Q43: 1773.2684 | R43: 1189.0901
C44: 40575 | D44: 40602 | E44: grid_u4lflnxf.xlsx | F44: 13431.267 | G44: 1141.2273 | H44: 825.20486 | I44: 1968.4379 | J44: 26929.303 | K44: 8864.1093 | L44: 554.50537 | M44: 496.29057 | O44: 21797.318 | Q44: 1900.2079 | R44: 1206.2501
C45: 40603 | D45: 40633 | E45: grid_u4lflnxf.xlsx | F45: 13213.049 | G45: 1183.8905 | H45: 816.07302 | I45: 2026.2886 | J45: 27197.922 | K45: 8887.4956 | L45: 549.84882 | M45: 503.51999 | O45: 21365.347 | Q45: 1844.7872 | R45: 1196.9227
C46: 40634 | D46: 40662 | E46: grid_u4lflnxf.xlsx | F46: 13174.745 | G46: 1236.4062 | H46: 771.07094 | I46: 2106.0355 | J46: 27678.808 | K46: 8780.3506 | L46: 561.7208 | M46: 537.49559 | O46: 22602.416 | Q46: 1807.6412 | R46: 1192.0052
C47: 40664 | D47: 40694 | E47: grid_u4lflnxf.xlsx | F47: 12498.057 | G47: 1319.9249 | H47: 790.07586 | I47: 2435.7214 | J47: 26793.304 | K47: 8103.5484 | L47: 553.04753 | M47: 520.88829 | O47: 21850.633 | Q47: 1752.098 | R47: 1139.2069
C48: 40695 | D48: 40724 | E48: grid_u4lflnxf.xlsx | F48: 13424.289 | G48: 2389.7871 | H48: 787.44199 | I48: 2510.4604 | J48: 28449.118 | K48: 9452.6372 | L48: 525.4246 | M48: 515.06246 | O48: 22756.224 | Q48: 1795.0594 | R48: 921.37192
C49: 40725 | D49: 40753 | E49: grid_u4lflnxf.xlsx | F49: 14082.429 | G49: 2929.4215 | H49: 786.70871 | I49: 2490.1949 | J49: 29939.869 | K49: 9316.5436 | L49: 545.86818 | M49: 494.3744 | O49: 23901.656 | Q49: 1759.9509 | R49: 847.72284
C50: 40756 | D50: 40786 | E50: grid_u4lflnxf.xlsx | F50: 13480.664 | G50: 2994.2119 | H50: 768.66495 | I50: 2898.598 | J50: 31037.45 | K50: 9078.7949 | L50: 438.47068 | M50: 491.55847 | O50: 22698.704 | Q50: 1807.9884 | R50: 826.00672
C51: 40787 | D51: 40816 | E51: grid_u4lflnxf.xlsx | F51: 13359.183 | G51: 2948.7514 | H51: 762.29801 | I51: 3004.3039 | J51: 28543.005 | K51: 9527.1469 | L51: 403.33234 | M51: 472.16287 | O51: 21510.873 | P51: 460.51956 | Q51: 1855.7692 | R51: 872.95498
C52: 40817 | D52: 40847 | E52: grid_u4lflnxf.xlsx | F52: 12887.068 | G52: 2977.0702 | H52: 752.13183 | I52: 2899.0166 | J52: 26850.87 | K52: 9437.5241 | L52: 383.61716 | M52: 466.67072 | O52: 20890.485 | P52: 475.93034 | Q52: 1821.7665 | R52: 876.13191
C53: 40848 | D53: 40877 | E53: grid_u4lflnxf.xlsx | F53: 13114.066 | G53: 3089.3269 | H53: 766.41211 | I53: 2909.4206 | J53: 27913.406 | K53: 9473.3468 | L53: 292.51458 | M53: 498.0255 | O53: 20853.436 | P53: 485.39128 | Q53: 1773.6944 | R53: 935.79669
C54: 40878 | D54: 40907 | E54: grid_u4lflnxf.xlsx | F54: 12652.236 | G54: 3118.0787 | H54: 825.73919 | I54: 3072.8995 | J54: 27142.859 | K54: 9585.3142 | L54: 293.79917 | M54: 537.61278 | O54: 19816.883 | P54: 485.74471 | Q54: 1776.3335 | R54: 947.72285
C55: 40909 | D55: 40939 | E55: grid_u4lflnxf.xlsx | F55: 11926.745 | G55: 2908.9099 | H55: 732.43135 | I55: 3225.8924 | J55: 26838.628 | K55: 9646.2866 | L55: 310.00596 | M55: 516.6193 | O55: 19404.559 | P55: 486.68823 | Q55: 1805.4298 | R55: 935.73725
C56: 40940 | D56: 40968 | E56: grid_u4lflnxf.xlsx | F56: 10690.21 | G56: 2889.3263 | H56: 702.84712 | I56: 3167.959 | J56: 24956.172 | K56: 9593.8834 | L56: 319.11295 | M56: 521.61935 | O56: 16928.694 | P56: 495.14552 | Q56: 1838.0278 | R56: 965.98851
C57: 40969 | D57: 40998 | E57: grid_u4lflnxf.xlsx | F57: 10556.646 | G57: 2931.2008 | H57: 702.39977 | I57: 3372.5556 | J57: 25459.278 | K57: 9669.8944 | L57: 321.61388 | M57: 568.5961 | O57: 16516.665 | P57: 508.2415 | Q57: 1820.224 | R57: 989.99782
C58: 41000 | D58: 41029 | E58: grid_u4lflnxf.xlsx | F58: 10530.904 | G58: 2191.1385 | H58: 677.60072 | I58: 3424.3011 | J58: 25130.939 | K58: 9292.8961 | L58: 331.53168 | M58: 605.54558 | O58: 16770.347 | P58: 499.77018 | Q58: 1928.7015 | R58: 980.56303
C59: 41030 | D59: 41060 | E59: grid_u4lflnxf.xlsx | F59: 11208.657 | G59: 2245.8629 | H59: 648.22094 | I59: 3542.587 | J59: 26335.932 | K59: 9753.8214 | L59: 304.45733 | M59: 627.36793 | O59: 18261.909 | P59: 508.76253 | Q59: 1947.3733 | R59: 1088.317
C60: 41061 | D60: 41089 | E60: grid_u4lflnxf.xlsx | F60: 11266.04 | G60: 2193.8774 | H60: 606.04996 | I60: 3484.3772 | J60: 28665.625 | K60: 9520.5167 | L60: 304.47017 | M60: 634.59622 | O60: 19056.944 | P60: 522.47449 | Q60: 1949.2126 | R60: 1210.8092
C61: 41091 | D61: 41121 | E61: grid_u4lflnxf.xlsx | F61: 10632.074 | G61: 2073.6008 | H61: 575.45311 | I61: 3460.7078 | J61: 28941.704 | K61: 9447.5692 | L61: 314.10276 | M61: 621.2166 | O61: 16550.547 | P61: 495.20984 | Q61: 2019.2053 | R61: 1202.3288
C62: 41122 | D62: 41152 | E62: grid_u4lflnxf.xlsx | F62: 10076.846 | G62: 2040.0224 | H62: 512.82624 | I62: 3321.3239 | J62: 28081.102 | K62: 9605.4211 | L62: 309.60268 | M62: 617.02882 | O62: 14858.327 | P62: 536.06384 | Q62: 2057.5546 | R62: 1212.2336
... C150: 43800 | D150: 43830 | E150: grid_ovzcidwu.xlsx | F150: 15200.473 | G150: 4291.4924 | H150: 1074.4851 | I150: 7417.559 | J150: 36095.3 | K150: 19373.315 | L150: 805.7407 | M150: 1372.9495 | O150: 23500.078 | P150: 578.83258 | Q150: 2642.5137 | R150: 850.49997
C151: 43831 | D151: 43861 | E151: grid_1mk3z2wn.xlsx | F151: 14075.163 | G151: 4265.2069 | H151: 1062.9496 | I151: 6820.1076 | J151: 36691.547 | K151: 18147.423 | L151: 842.96443 | M151: 1382.8478 | N151: 342.39957 | O151: 23493.029 | P151: 601.51601 | Q151: 2738.5197 | R151: 862.61651
C152: 43862 | D152: 43889 | E152: grid_1mk3z2wn.xlsx | F152: 13998.757 | G152: 4170.3283 | H152: 1051.7615 | I152: 6335.7452 | J152: 36448.813 | K152: 18278.69 | L152: 881.39874 | M152: 1446.4256 | N152: 347.19808 | O152: 23371.976 | P152: 630.87827 | Q152: 2835.0404 | R152: 899.66645
C153: 43891 | D153: 43921 | E153: grid_1mk3z2wn.xlsx | F153: 12131.025 | G153: 4350.7815 | H153: 882.33511 | I153: 5745.0428 | J153: 13820.348 | K153: 18100.116 | L153: 902.53098 | M153: 1376.007 | N153: 341.94287 | O153: 24994.925 | P153: 446.22549 | Q153: 2871.614 | R153: 894.26328
C154: 43922 | D154: 43951 | E154: grid_1mk3z2wn.xlsx | F154: 10238.656 | G154: 4202.8749 | H154: 764.41358 | I154: 5002.4243 | J154: 6703.71 | K154: 16567.085 | L154: 871.31283 | M154: 1097.4057 | N154: 347.04444 | O154: 22781.884 | P154: 349.74354 | Q154: 2750.2464 | R154: 827.81648
C155: 43952 | D155: 43980 | E155: grid_1mk3z2wn.xlsx | F155: 9576.3666 | G155: 4139.7255 | H155: 742.49649 | I155: 4706.4042 | J155: 2076.5147 | K155: 15067.297 | L155: 846.01132 | M155: 929.34032 | N155: 357.78735 | O155: 25110.391 | P155: 364.29286 | Q155: 2412.206 | R155: 890.99451
C156: 43983 | D156: 44012 | E156: grid_1mk3z2wn.xlsx | F156: 8906.9786 | G156: 4043.967 | H156: 711.43505 | I156: 4715.4942 | J156: -1170.5429 | K156: 13286.835 | L156: 860.78013 | M156: 847.10791 | N156: 356.7541 | O156: 26414.781 | P156: 404.49805 | Q156: 2660.9604 | R156: 880.64192
C157: 44013 | D157: 44043 | E157: grid_1mk3z2wn.xlsx | F157: 9429.4736 | G157: 3809.0113 | H157: 751.04809 | I157: 4503.9625 | J157: 2054.6893 | K157: 12861.2 | L157: 853.14803 | M157: 1030.1115 | N157: 363.54568 | O157: 28718.037 | P157: 413.94117 | Q157: 2767.051 | R157: 950.38969
C158: 44044 | D158: 44074 | E158: grid_1mk3z2wn.xlsx | F158: 10412.27 | G158: 3997.8642 | H158: 759.26739 | I158: 4586.6889 | J158: 6956.8558 | K158: 13010.752 | L158: 845.46534 | M158: 1052.5888 | N158: 352.22026 | O158: 30758.191 | P158: 419.41778 | Q158: 3080.7231 | R158: 976.07992
C159: 44075 | D159: 44104 | E159: grid_1mk3z2wn.xlsx | F159: 11661.71 | G159: 4032.694 | H159: 815.67057 | I159: 4663.0707 | J159: 10949.882 | K159: 13822.788 | L159: 843.85826 | M159: 1190.8301 | N159: 348.42004 | O159: 35406.708 | P159: 384.76507 | Q159: 2919.8038 | R159: 979.93799
C160: 44105 | D160: 44134 | E160: grid_1mk3z2wn.xlsx | F160: 14070.599 | G160: 4176.3404 | H160: 822.99266 | I160: 4797.9613 | J160: 19121.652 | K160: 14682.199 | L160: 891.068 | M160: 1396.6689 | N160: 381.8674 | O160: 42781.4 | P160: 451.87204 | Q160: 2916.6318 | R160: 1105.2988
C161: 44136 | D161: 44165 | E161: grid_1mk3z2wn.xlsx | F161: 16663.022 | G161: 4089.6057 | H161: 914.18142 | I161: 5000.6226 | J161: 26183.026 | K161: 15810.498 | L161: 919.08933 | M161: 1339.2928 | N161: 392.04877 | O161: 47451.572 | P161: 476.08864 | Q161: 2827.0742 | R161: 1092.7449
C162: 44166 | D162: 44196 | E162: grid_1mk3z2wn.xlsx | F162: 17136.888 | G162: 4461.2085 | H162: 942.31622 | I162: 5296.9762 | J162: 33166.803 | K162: 15882.531 | L162: 979.66065 | M162: 1429.5836 | N162: 402 | O162: 47321.955 | P162: 452.36893 | Q162: 2982.2684 | R162: 981.83993
... C180: 44713 | D180: 44742 | E180: grid_1mk3z2wn.xlsx | F180: 36390.79 | G180: 4302.2694 | H180: 1421.5268 | I180: 7740.7565 | J180: 118723.99 | K180: 21569.05 | L180: 1681.8909 | M180: 2310.8956 | N180: 543.53118 | O180: 64153.03 | P180: 575.60405 | Q180: 4546.0296 | R180: 1127.1965
C181: 44743 | D181: 44771 | E181: grid_1mk3z2wn.xlsx | F181: 36053.563 | G181: 4118.0906 | H181: 1437.0798 | I181: 7620.8807 | J181: 121159.62 | K181: 21723.893 | L181: 1727.1447 | M181: 2494.0997 | N181: 542.47821 | O181: 57236.583 | P181: 593.38365 | Q181: 4364.0308
C182: 44774 | D182: 44804 | E182: grid_1mk3z2wn.xlsx | F182: 34794.354 | G182: 3793.6175 | H182: 1419.8494 | I182: 7713.3849 | J182: 124115.28 | K182: 21942.308 | L182: 1703.9186 | M182: 2437.8257 | N182: 524.21579 | O182: 54872.669 | P182: 606.47838 | Q182: 3871.2364
C183: 44805 | D183: 44834 | E183: grid_1mk3z2wn.xlsx | F183: 33165.195 | G183: 3663.6892 | H183: 1390.6182 | I183: 7447.2927 | J183: 117964.73 | K183: 22450.693 | L183: 1721.1553 | M183: 2701.1714 | N183: 545.75418 | O183: 54873.926 | P183: 609.69803 | Q183: 4159.2104
C184: 44835 | D184: 44865 | E184: grid_1mk3z2wn.xlsx | F184: 30334.773 | G184: 3631.0802 | H184: 1466.7868 | I184: 7308.0933 | J184: 115200.81 | K184: 22193.949 | L184: 1760.4444 | M184: 2833.4545 | N184: 559.47009 | O184: 47019.733 | P184: 611.00641 | Q184: 4478.8281
C185: 44866 | D185: 44895 | E185: grid_1mk3z2wn.xlsx | F185: 31015.116 | G185: 3694.1481 | H185: 1586.7141 | I185: 7568.4711 | J185: 107975.05 | K185: 21687.512 | L185: 1841.781 | M185: 3005.1879 | N185: 592.93855 | O185: 48047.743 | P185: 622.45723 | Q185: 4674.7747
C186: 44896 | D186: 44925 | E186: grid_1mk3z2wn.xlsx | F186: 28805.766 | G186: 3714.9072 | H186: 1198.688 | I186: 7030.6355 | J186: 93337.229 | K186: 21768.336 | L186: 1881.3476 | M186: 3104.9064 | N186: 626.8116 | O186: 45839.864 | P186: 639.52823 | Q186: 4271.0148
C187: 44927 | D187: 44957 | E187: grid_22fp35k1.xlsx | F187: 27839.459 | G187: 3704.974 | H187: 1216.3459 | I187: 6173.2731 | J187: 80428.65 | K187: 22028.66 | L187: 1719.0504 | M187: 3022.8945 | N187: 655.55895 | O187: 46461.728 | P187: 662.41148 | Q187: 4478.3207
C188: 44958 | D188: 44985 | E188: grid_22fp35k1.xlsx | F188: 29979.202 | G188: 3699.7584 | H188: 1173.2887 | I188: 6445.9836 | J188: 94928.058 | K188: 22522.84 | L188: 1711.6697 | M188: 3140.8279 | N188: 678.48762 | O188: 45574.198 | P188: 697.25189 | Q188: 4488.9835
C189: 44986 | D189: 45016 | E189: grid_22fp35k1.xlsx | F189: 29097.008 | G189: 3689.7627 | H189: 1226.4266 | I189: 6649.6104 | J189: 90862.301 | K189: 22464.83 | L189: 1744.4768 | M189: 3075.4027 | N189: 704.5178 | O189: 47349.174 | P189: 739.21497 | Q189: 4549.6583
C190: 45017 | D190: 45044 | E190: grid_22fp35k1.xlsx | F190: 27118.814 | G190: 3769.0369 | H190: 1234.9342 | I190: 6844.4445 | J190: 89379.473 | K190: 22402.648 | L190: 1745.944 | M190: 3130.0813 | N190: 680.66871 | O190: 40154.821 | P190: 713.82875 | Q190: 4461.6636
C191: 45047 | D191: 45077 | E191: grid_22fp35k1.xlsx | F191: 26330.617 | G191: 3865.7474 | H191: 1186.5941 | I191: 7004.261 | J191: 89818.894 | K191: 22410.969 | L191: 1742.3728 | M191: 3070.5446 | N191: 629.74991 | O191: 38071.857 | P191: 959.33076 | Q191: 5002.4867
C192: 45078 | D192: 45107 | E192: grid_22fp35k1.xlsx | F192: 25589.017 | G192: 4002.803 | H192: 989.12251 | I192: 6936.7041 | J192: 88021.449 | K192: 22718.192 | L192: 1782.5058 | M192: 3122.4154 | N192: 633.84898 | O192: 35018.72 | P192: 963.92451 | Q192: 4396.1741
... C231: 46266 | D231: 46268 | E231: grid_22fp35k1.xlsx | F231: 31592.424 | G231: 7190.7213 | H231: 2837.0093 | I231: 9199.1046 | J231: 110049.06 | K231: 29964.072 | L231: 4335.5365 | M231: 4779.3729 | N231: 1134.473 | O231: 30228.414 | P231: 990.54016 | Q231: 6250.7079

Sheet Earnings Base 100
C2: Earnings 12 meses forward em base 100
C3: Janeiro de 2020 = 100. Séries setoriais e IBOV calculadas a partir do consolidado mensal.
C6: month | D6: date | E6: source_file | F6: IBOV | G6: Communication Services | H6: Consumer Discretionary | I6: Consumer Staples | J6: Energy | K6: Financials | L6: Health Care | M6: Industrials | N6: Information Technology | O6: Materials | P6: Real Estate | Q6: Utilities
C7: 39448 | D7: 39478 | E7: grid_20qvjmd3.xlsx | F7: 70.762078 | G7: 17.120159 | H7: 29.237501 | I7: 22.558884 | J7: 80.216936 | K7: 41.959597 | M7: 47.721233 | O7: 57.966827 | P7: 0 | Q7: 44.448037
C8: 39479 | D8: 39507 | E8: grid_20qvjmd3.xlsx | F8: 73.10471 | G8: 18.755079 | H8: 30.343071 | I8: 23.077412 | J8: 80.795727 | K8: 42.775323 | M8: 45.064327 | O8: 61.833736 | P8: 0 | Q8: 45.368616
C9: 39508 | D9: 39538 | E9: grid_20qvjmd3.xlsx | F9: 73.206024 | G9: 17.516011 | H9: 27.765224 | I9: 22.221098 | J9: 83.860062 | K9: 43.220741 | M9: 44.501586 | O9: 62.891211 | P9: 0 | Q9: 47.910815
C10: 39539 | D10: 39568 | E10: grid_20qvjmd3.xlsx | F10: 75.896261 | G10: 16.670802 | H10: 28.309341 | I10: 21.276451 | J10: 84.372212 | K10: 43.584587 | M10: 43.515337 | O10: 64.774119 | P10: 0 | Q10: 50.430959
C11: 39569 | D11: 39598 | E11: grid_20qvjmd3.xlsx | F11: 85.941257 | G11: 17.069525 | H11: 29.811724 | I11: 22.062284 | J11: 88.098408 | K11: 43.376366 | M11: 40.543477 | O11: 69.008165 | P11: 2.5069078 | Q11: 49.399658
C12: 39600 | D12: 39629 | E12: grid_20qvjmd3.xlsx | F12: 88.939823 | G12: 16.384575 | H12: 29.380186 | I12: 22.387278 | J12: 89.911008 | K12: 43.450791 | M12: 39.780181 | O12: 69.439144 | P12: 5.467464 | Q12: 47.933674
C13: 39630 | D13: 39660 | E13: grid_20qvjmd3.xlsx | F13: 82.515638 | G13: 17.280899 | H13: 27.678327 | I13: 20.819279 | J13: 93.522863 | K13: 43.329821 | M13: 38.094717 | O13: 68.817506 | P13: 5.5098227 | Q13: 49.616034
C14: 39661 | D14: 39689 | E14: grid_20qvjmd3.xlsx | F14: 85.995624 | G14: 16.518893 | H14: 28.423359 | I14: 22.097217 | J14: 95.107405 | K14: 43.394866 | M14: 40.646251 | O14: 72.73627 | P14: 5.5494486 | Q14: 51.434089
C15: 39692 | D15: 39721 | E15: grid_20qvjmd3.xlsx | F15: 101.36286 | G15: 15.209506 | H15: 34.195931 | I15: 25.520739 | J15: 98.84647 | K15: 37.628041 | M15: 41.290488 | O15: 81.896665 | Q15: 56.516357
C16: 39722 | D16: 39752 | E16: grid_20qvjmd3.xlsx | F16: 93.182427 | G16: 15.282032 | H16: 35.056639 | I16: 23.49428 | J16: 93.706193 | K16: 35.922829 | M16: 44.508103 | O16: 81.674988 | Q16: 60.222794
C17: 39753 | D17: 39780 | E17: grid_20qvjmd3.xlsx | F17: 84.191574 | G17: 14.243017 | H17: 35.264952 | I17: 24.348467 | J17: 91.277729 | K17: 36.646253 | M17: 40.806233 | O17: 78.194548 | Q17: 61.33448
C18: 39783 | D18: 39813 | E18: grid_20qvjmd3.xlsx | F18: 78.751945 | G18: 15.731157 | H18: 35.733759 | I18: 24.907312 | J18: 79.300012 | K18: 35.730114 | M18: 41.822687 | O18: 66.631154 | Q18: 64.677465
C19: 39814 | D19: 39843 | E19: grid_20qvjmd3.xlsx | F19: 78.391552 | G19: 15.009263 | H19: 32.646568 | I19: 22.919501 | J19: 73.021947 | K19: 29.791135 | M19: 39.089318 | O19: 56.371411 | Q19: 64.973911
C20: 39845 | D20: 39871 | E20: grid_20qvjmd3.xlsx | F20: 79.504281 | G20: 15.128888 | H20: 30.876959 | I20: 22.066491 | J20: 73.703046 | K20: 30.129885 | M20: 37.996599 | O20: 54.216192 | Q20: 64.451238
C21: 39873 | D21: 39903 | E21: grid_20qvjmd3.xlsx | F21: 70.760297 | G21: 14.779513 | H21: 32.062623 | I21: 23.785023 | J21: 66.794992 | K21: 32.669716 | M21: 39.484964 | O21: 42.247158 | Q21: 68.406075
C22: 39904 | D22: 39933 | E22: grid_20qvjmd3.xlsx | F22: 64.473738 | G22: 14.760983 | H22: 31.390829 | I22: 24.315568 | J22: 64.331126 | K22: 33.535894 | M22: 38.036746 | O22: 38.848103 | Q22: 68.148542
C23: 39934 | D23: 39962 | E23: grid_20qvjmd3.xlsx | F23: 65.333322 | G23: 14.969472 | H23: 31.921854 | I23: 25.985439 | J23: 68.420348 | K23: 33.712448 | M23: 35.679681 | O23: 34.507892 | Q23: 66.96594
C24: 39965 | D24: 39994 | E24: grid_20qvjmd3.xlsx | F24: 63.188596 | G24: 15.590829 | H24: 33.154578 | I24: 27.657865 | J24: 68.382916 | K24: 34.148738 | M24: 32.662725 | O24: 31.933674 | Q24: 65.37917
C25: 39995 | D25: 40025 | E25: grid_20qvjmd3.xlsx | F25: 60.842874 | G25: 15.528293 | H25: 33.224518 | I25: 27.860899 | J25: 69.08327 | K25: 35.463281 | M25: 32.065856 | O25: 31.246393 | Q25: 65.728082
C26: 40026 | D26: 40056 | E26: grid_20qvjmd3.xlsx | F26: 59.598721 | G26: 15.7143 | H26: 35.571762 | I26: 29.316859 | J26: 69.060981 | K26: 37.248452 | M26: 32.059462 | O26: 30.521538 | Q26: 64.849785
... C42: 40513 | D42: 40543 | E42: grid_20qvjmd3.xlsx | F42: 89.504207 | G42: 25.364088 | H42: 74.957791 | I42: 31.513816 | J42: 76.607454 | K42: 45.945372 | M42: 35.46443 | O42: 88.685223 | Q42: 63.605753
C43: 40544 | D43: 40574 | E43: grid_u4lflnxf.xlsx | F43: 93.622475 | G43: 26.411579 | H43: 76.562783 | I43: 28.644927 | J43: 74.872061 | K43: 47.668562 | L43: 65.798097 | M43: 35.841932 | O43: 90.460333 | Q43: 64.752806
C44: 40575 | D44: 40602 | E44: grid_u4lflnxf.xlsx | F44: 95.4253 | G44: 26.756669 | H44: 77.633487 | I44: 28.862271 | J44: 73.393753 | K44: 48.845002 | L44: 65.7804 | M44: 35.889022 | O44: 92.782067 | Q44: 69.388139
C45: 40603 | D45: 40633 | E45: grid_u4lflnxf.xlsx | F45: 93.874926 | G45: 27.756929 | H45: 76.774383 | I45: 29.710509 | J45: 74.125854 | K45: 48.97387 | L45: 65.227999 | M45: 36.411815 | O45: 90.943346 | Q45: 67.364394
C46: 40634 | D46: 40662 | E46: grid_u4lflnxf.xlsx | F46: 93.602783 | G46: 28.988189 | H46: 72.540685 | I46: 30.879799 | J46: 75.436471 | K46: 48.383456 | L46: 66.636359 | M46: 38.868744 | O46: 96.20903 | Q46: 66.007966
C47: 40664 | D47: 40694 | E47: grid_u4lflnxf.xlsx | F47: 88.795109 | G47: 30.946328 | H47: 74.328627 | I47: 35.713826 | J47: 73.023097 | K47: 44.653989 | L47: 65.607458 | M47: 37.667795 | O47: 93.009007 | Q47: 63.979748
C48: 40695 | D48: 40724 | E48: grid_u4lflnxf.xlsx | F48: 95.375727 | G48: 56.029804 | H48: 74.080838 | I48: 36.809689 | J48: 77.535892 | K48: 52.08804 | L48: 62.330578 | M48: 37.246503 | O48: 96.863729 | Q48: 65.548528
C49: 40725 | D49: 40753 | E49: grid_u4lflnxf.xlsx | F49: 100.05162 | G49: 68.681815 | H49: 74.011853 | I49: 36.512546 | J49: 81.598819 | K49: 51.338106 | L49: 64.755779 | M49: 35.750455 | O49: 101.73935 | Q49: 64.266505
C50: 40756 | D50: 40786 | E50: grid_u4lflnxf.xlsx | F50: 95.776255 | G50: 70.200859 | H50: 72.314335 | I50: 42.500767 | J50: 84.590192 | K50: 50.02801 | L50: 52.015324 | M50: 35.546823 | O50: 96.618888 | Q50: 66.020648
C51: 40787 | D51: 40816 | E51: grid_u4lflnxf.xlsx | F51: 94.913168 | G51: 69.135015 | H51: 71.715346 | I51: 44.050682 | J51: 77.791773 | K51: 52.49862 | L51: 47.846899 | M51: 34.144239 | O51: 91.56279 | P51: 76.559818 | Q51: 67.765412
C52: 40817 | D52: 40847 | E52: grid_u4lflnxf.xlsx | F52: 91.558922 | G52: 69.798963 | H52: 70.758934 | I52: 42.506904 | J52: 73.179989 | K52: 52.00476 | L52: 45.508108 | M52: 33.747076 | O52: 88.922057 | P52: 79.121807 | Q52: 66.523768
C53: 40848 | D53: 40877 | E53: grid_u4lflnxf.xlsx | F53: 93.171682 | G53: 72.430879 | H53: 72.102393 | I53: 42.659453 | J53: 76.07585 | K53: 52.202159 | L53: 34.700703 | M53: 36.014483 | O53: 88.764357 | P53: 80.694655 | Q53: 64.768364
C54: 40878 | D54: 40907 | E54: grid_u4lflnxf.xlsx | F54: 89.890505 | G54: 73.104981 | H54: 77.683756 | I54: 45.056467 | J54: 73.975782 | K54: 52.819146 | L54: 34.853093 | M54: 38.877219 | O54: 84.352182 | P54: 80.753413 | Q54: 64.864732
C55: 40909 | D55: 40939 | E55: grid_u4lflnxf.xlsx | F55: 84.736101 | G55: 68.20091 | H55: 68.905556 | I55: 47.299729 | J55: 73.146625 | K55: 53.15513 | L55: 36.775688 | M55: 37.359085 | O55: 82.597094 | P55: 80.910269 | Q55: 65.927215
C56: 40940 | D56: 40968 | E56: grid_u4lflnxf.xlsx | F56: 75.950875 | G56: 67.741762 | H56: 66.122336 | I56: 46.450279 | J56: 68.016136 | K56: 52.866367 | L56: 37.856039 | M56: 37.720662 | O56: 72.058372 | P56: 82.316265 | Q56: 67.117567
C57: 40969 | D57: 40998 | E57: grid_u4lflnxf.xlsx | F57: 75.00194 | G57: 68.723531 | H57: 66.08025 | I57: 49.450181 | J57: 69.387313 | K57: 53.28522 | L57: 38.152722 | M57: 41.117763 | O57: 70.304537 | P57: 84.493428 | Q57: 66.467441
C58: 41000 | D58: 41029 | E58: grid_u4lflnxf.xlsx | F58: 74.819053 | G58: 51.372385 | H58: 63.747209 | I58: 50.208901 | J58: 68.492449 | K58: 51.207799 | L58: 39.329261 | M58: 43.789748 | O58: 71.384355 | P58: 83.0851 | Q58: 70.428615
C59: 41030 | D59: 41060 | E59: grid_u4lflnxf.xlsx | F59: 79.634295 | G59: 52.655426 | H59: 60.983223 | I59: 51.943271 | J59: 71.776566 | K59: 53.747693 | L59: 36.117459 | M59: 45.367821 | O59: 77.73331 | P59: 84.580047 | Q59: 71.110435
C60: 41061 | D60: 41089 | E60: grid_u4lflnxf.xlsx | F60: 80.041983 | G60: 51.436601 | H60: 57.015868 | I60: 51.089769 | J60: 78.125964 | K60: 52.462085 | L60: 36.118982 | M60: 45.890532 | O60: 81.117441 | P60: 86.859615 | Q60: 71.177601
C61: 41091 | D61: 41121 | E61: grid_u4lflnxf.xlsx | F61: 75.537834 | G61: 48.616651 | H61: 54.137383 | I61: 50.742716 | J61: 78.878397 | K61: 52.060113 | L61: 37.261686 | M61: 44.92299 | O61: 70.448756 | P61: 82.326959 | Q61: 73.733459
C62: 41122 | D62: 41152 | E62: grid_u4lflnxf.xlsx | F62: 71.593102 | G62: 47.82939 | H62: 48.245582 | I62: 48.698995 | J62: 76.532893 | K62: 52.929944 | L62: 36.727846 | M62: 44.620153 | O62: 63.245684 | P62: 89.118797 | Q62: 75.133824
... C150: 43800 | D150: 43830 | E150: grid_ovzcidwu.xlsx | F150: 107.995 | G150: 100.61628 | H150: 101.08523 | I150: 108.76015 | J150: 98.374974 | K150: 106.75518 | L150: 95.584188 | M150: 99.284207 | O150: 100.03 | P150: 96.228955 | Q150: 96.494235
C151: 43831 | D151: 43861 | E151: grid_1mk3z2wn.xlsx | F151: 100 | G151: 100 | H151: 100 | I151: 100 | J151: 100 | K151: 100 | L151: 100 | M151: 100 | N151: 100 | O151: 100 | P151: 100 | Q151: 100
C152: 43862 | D152: 43889 | E152: grid_1mk3z2wn.xlsx | F152: 99.457155 | G152: 97.77552 | H152: 98.947446 | I152: 92.898025 | J152: 99.338449 | K152: 100.72334 | L152: 104.55942 | M152: 104.5976 | N152: 101.40144 | O152: 99.484728 | P152: 104.88138 | Q152: 103.52456
C153: 43891 | D153: 43921 | E153: grid_1mk3z2wn.xlsx | F153: 86.187455 | G153: 102.00634 | H153: 83.008178 | I153: 84.236836 | J153: 37.666301 | K153: 99.739316 | L153: 107.06632 | M153: 99.505307 | N153: 99.86662 | O153: 106.39294 | P153: 74.183477 | Q153: 104.86008
C154: 43922 | D154: 43951 | E154: grid_1mk3z2wn.xlsx | F154: 72.742713 | G154: 98.538593 | H154: 71.914375 | I154: 73.348173 | J154: 18.270448 | K154: 91.291662 | L154: 103.36294 | M154: 79.358383 | N154: 101.35656 | O154: 96.972951 | P154: 58.143678 | Q154: 100.42821
C155: 43952 | D155: 43980 | E155: grid_1mk3z2wn.xlsx | F155: 68.037339 | G155: 97.058022 | H155: 69.852463 | I155: 69.007771 | J155: 5.6593817 | K155: 83.027198 | L155: 100.36145 | M155: 67.204814 | N155: 104.4941 | O155: 106.88443 | P155: 60.562455 | Q155: 88.084303
C156: 43983 | D156: 44012 | E156: grid_1mk3z2wn.xlsx | F156: 63.281529 | G156: 94.812915 | H156: 66.930269 | I156: 69.141052 | J156: -3.1902251 | K156: 73.216097 | L156: 102.11346 | M156: 61.258216 | N156: 104.19233 | O156: 112.43668 | P156: 67.24643 | Q156: 97.167838
C157: 44013 | D157: 44043 | E157: grid_1mk3z2wn.xlsx | F157: 66.993706 | G157: 89.304255 | H157: 70.656979 | I157: 66.039465 | J157: 5.5998983 | K157: 70.870667 | L157: 101.20807 | M157: 74.492032 | N157: 106.17586 | O157: 122.24067 | P157: 68.816317 | Q157: 101.04185
C158: 44044 | D158: 44074 | E158: grid_1mk3z2wn.xlsx | F158: 73.976196 | G158: 93.732012 | H158: 71.430233 | I158: 67.252442 | J158: 18.960378 | K158: 71.694764 | L158: 100.29668 | M158: 76.117468 | N158: 102.8682 | O158: 130.92476 | P158: 69.726785 | Q158: 112.49592
C159: 44075 | D159: 44104 | E159: grid_1mk3z2wn.xlsx | F159: 82.853108 | G159: 94.548612 | H159: 76.736522 | I159: 68.372392 | J159: 29.843064 | K159: 76.169426 | L159: 100.10603 | M159: 86.114323 | N159: 101.75832 | O159: 150.71155 | P159: 63.96589 | Q159: 106.61979
C160: 44105 | D160: 44134 | E160: grid_1mk3z2wn.xlsx | F160: 99.967571 | G160: 97.916478 | H160: 77.425368 | I160: 70.350229 | J160: 52.114597 | K160: 80.905144 | L160: 105.70648 | M160: 100.99946 | N160: 111.52683 | O160: 182.10253 | P160: 75.122196 | Q160: 106.50396
C161: 44136 | D161: 44165 | E161: grid_1mk3z2wn.xlsx | F161: 118.38599 | G161: 95.882939 | H161: 86.004209 | I161: 73.321756 | J161: 71.359833 | K161: 87.122549 | L161: 109.03062 | M161: 96.850337 | N161: 114.50037 | O161: 201.9815 | P161: 79.148124 | Q161: 103.23366
C162: 44166 | D162: 44196 | E162: grid_1mk3z2wn.xlsx | F162: 121.75268 | G162: 104.59536 | H162: 88.651071 | I162: 77.667048 | J162: 90.393581 | K162: 87.51948 | L162: 116.21613 | M162: 103.37967 | N162: 117.40669 | O162: 201.42977 | P162: 75.204802 | Q162: 108.90075
... C231: 46266 | D231: 46268 | E231: grid_22fp35k1.xlsx | F231: 224.45511 | G231: 168.59021 | H231: 266.89969 | I231: 134.8821 | J231: 299.93029 | K231: 165.11475 | L231: 514.32022 | M231: 345.61814 | N231: 331.33016 | O231: 128.66972 | P231: 164.67395 | Q231: 228.25134
C233: Base auxiliar do gráfico
C235: month_label | D235: IBOV | E235: Communication Services | F235: Consumer Discretionary | G235: Consumer Staples | H235: Energy | I235: Financials | J235: Health Care | K235: Industrials | L235: Information Technology | M235: Materials | N235: Real Estate | O235: Utilities
C236: 2008-01 | D236: =F7 | E236: =G7 | F236: =H7 | G236: =I7 | H236: =J7 | I236: =K7 | J236: =L7 | K236: =M7 | ... O236: =Q7
C237: 2008-02 | D237: =F8 | E237: =G8 | F237: =H8 | G237: =I8 | H237: =J8 | I237: =K8 | J237: =L8 | K237: =M8 | ... O237: =Q8
C238: 2008-03 | D238: =F9 | E238: =G9 | F238: =H9 | G238: =I9 | H238: =J9 | I238: =K9 | J238: =L9 | K238: =M9 | ... O238: =Q9
C239: 2008-04 | D239: =F10 | E239: =G10 | F239: =H10 | G239: =I10 | H239: =J10 | I239: =K10 | J239: =L10 | K239: =M10 | ... O239: =Q10
C240: 2008-05 | D240: =F11 | E240: =G11 | F240: =H11 | G240: =I11 | H240: =J11 | I240: =K11 | J240: =L11 | K240: =M11 | ... O240: =Q11
C241: 2008-06 | D241: =F12 | E241: =G12 | F241: =H12 | G241: =I12 | H241: =J12 | I241: =K12 | J241: =L12 | K241: =M12 | ... O241: =Q12
C242: 2008-07 | D242: =F13 | E242: =G13 | F242: =H13 | G242: =I13 | H242: =J13 | I242: =K13 | J242: =L13 | K242: =M13 | ... O242: =Q13
C243: 2008-08 | D243: =F14 | E243: =G14 | F243: =H14 | G243: =I14 | H243: =J14 | I243: =K14 | J243: =L14 | K243: =M14 | ... O243: =Q14
C244: 2008-09 | D244: =F15 | E244: =G15 | F244: =H15 | G244: =I15 | H244: =J15 | I244: =K15 | J244: =L15 | K244: =M15 | ... O244: =Q15
C245: 2008-10 | D245: =F16 | E245: =G16 | F245: =H16 | G245: =I16 | H245: =J16 | I245: =K16 | J245: =L16 | K245: =M16 | ... O245: =Q16
C246: 2008-11 | D246: =F17 | E246: =G17 | F246: =H17 | G246: =I17 | H246: =J17 | I246: =K17 | J246: =L17 | K246: =M17 | ... O246: =Q17
C247: 2008-12 | D247: =F18 | E247: =G18 | F247: =H18 | G247: =I18 | H247: =J18 | I247: =K18 | J247: =L18 | K247: =M18 | ... O247: =Q18
... C460: 2026-09 | D460: =F231 | E460: =G231 | F460: =H231 | G460: =I231 | H460: =J231 | I460: =K231 | J460: =L231 | K460: =M231 | ... O460: =Q231

Sheet Revisions 3M
C2: Earnings revisions de três meses
C3: 100 × log(Earnings_t / Earnings_t-3). Valores em percentual logarítmico.
C6: month | D6: date | E6: source_file | F6: IBOV | G6: Communication Services | H6: Consumer Discretionary | I6: Consumer Staples | J6: Energy | K6: Financials | L6: Health Care | M6: Industrials | N6: Information Technology | O6: Materials | P6: Real Estate | Q6: Utilities | R6: Not Classified
C7: 39448 | D7: 39478 | E7: grid_20qvjmd3.xlsx
C8: 39479 | D8: 39507 | E8: grid_20qvjmd3.xlsx
C9: 39508 | D9: 39538 | E9: grid_20qvjmd3.xlsx
C10: 39539 | D10: 39568 | E10: grid_20qvjmd3.xlsx | F10: 7.004419 | G10: -2.6597842 | H10: -3.2260353 | I10: -5.8528082 | J10: 5.0503446 | K10: 3.7996384 | M10: -9.2262992 | O10: 11.103521 | Q10: 12.628445 | R10: -2.8458598
C11: 39569 | D11: 39598 | E11: grid_20qvjmd3.xlsx | F11: 16.177122 | G11: -9.4169869 | H11: -1.7666442 | I11: -4.4984731 | J11: 8.6530376 | K11: 1.3953351 | M11: -10.571606 | O11: 10.977572 | Q11: 8.5122911 | R11: -0.3971906
C12: 39600 | D12: 39629 | E12: grid_20qvjmd3.xlsx | F12: 19.468228 | G12: -6.6774989 | H12: 5.6536205 | I12: 0.74506447 | J12: 6.9670899 | K12: 0.53085475 | M12: -11.215599 | O12: 9.9044318 | Q12: 0.047698664 | R12: -3.4040964
C13: 39630 | D13: 39660 | E13: grid_20qvjmd3.xlsx | F13: 8.3620405 | G13: 3.5942962 | H13: -2.2542113 | I13: -2.1721422 | J13: 10.296783 | K13: -0.586246 | M13: -13.303784 | O13: 6.0552036 | Q13: -1.62912 | R13: -0.36035185
C14: 39661 | D14: 39689 | E14: grid_20qvjmd3.xlsx | F14: 0.063240473 | G14: -3.2789972 | H14: -4.7690444 | I14: 0.15821003 | J14: 7.6552375 | K14: 0.042641409 | M14: 0.25317049 | O14: 5.2615318 | P14: 79.464851 | Q14: 4.0357657 | R14: -0.28526302
C15: 39692 | D15: 39721 | E15: grid_20qvjmd3.xlsx | F15: 13.074671 | G15: -7.4419726 | H15: 15.178614 | I15: 13.099857 | J15: 9.4747465 | K15: -14.38795 | M15: 3.7263324 | O15: 16.500753 | Q15: 16.471185 | R15: 8.0269864
C16: 39722 | D16: 39752 | E16: grid_20qvjmd3.xlsx | F16: 12.157132 | G16: -12.2924 | H16: 23.631533 | I16: 12.087753 | J16: 0.19583469 | K16: -18.746812 | M16: 15.559566 | O16: 17.128965 | Q16: 19.373688 | R16: 4.3221905
C17: 39753 | D17: 39780 | E17: grid_20qvjmd3.xlsx | F17: -2.1201572 | G17: -14.823798 | H17: 21.567833 | I17: 9.7017214 | J17: -4.1100014 | K17: -16.902996 | M17: 0.39282204 | O17: 7.2359767 | Q17: 17.6041 | R17: -1.9594102
C18: 39783 | D18: 39813 | E18: grid_20qvjmd3.xlsx | F18: -25.240373 | G18: 3.372264 | H18: 4.3989215 | I18: -2.4329974 | J18: -22.032956 | K18: -5.1755685 | M18: 1.2806784 | O18: -20.628603 | Q18: 13.488274 | R18: -13.675784
C19: 39814 | D19: 39843 | E19: grid_20qvjmd3.xlsx | F19: -17.284299 | G19: -1.8010223 | H19: -7.1225295 | I19: -2.4768853 | J19: -24.940424 | K19: -18.716214 | M19: -12.982204 | O19: -37.078567 | Q19: 7.5934896 | R19: -28.077523
C20: 39845 | D20: 39871 | E20: grid_20qvjmd3.xlsx | F20: -5.7283972 | G20: 6.0339286 | H20: -13.28794 | I20: -9.8408666 | J20: -21.386269 | K20: -19.579363 | M20: -7.1338182 | O20: -36.622032 | Q20: 4.9566781 | R20: -18.592397
C21: 39873 | D21: 39903 | E21: grid_20qvjmd3.xlsx | F21: -10.70049 | G21: -6.2401325 | H21: -10.840489 | I21: -4.6105341 | J21: -17.161017 | K21: -8.9545327 | M21: -5.7518992 | O21: -45.563516 | Q21: 5.6048786 | R21: -49.946005
C22: 39904 | D22: 39933 | E22: grid_20qvjmd3.xlsx | F22: -19.545819 | G22: -1.6680099 | H22: -3.9223943 | I22: 5.9128658 | J22: -12.671645 | K22: 11.840549 | M22: -2.729654 | O22: -37.230289 | Q22: 4.7703942 | R22: -44.518706
C23: 39934 | D23: 39962 | E23: grid_20qvjmd3.xlsx | F23: -19.630867 | G23: -1.0593136 | H23: 3.3280631 | I23: 16.347614 | J23: -7.4373866 | K23: 11.23496 | M23: -6.2915271 | O23: -45.179154 | Q23: 3.8275198 | R23: -59.04352
C24: 39965 | D24: 39994 | E24: grid_20qvjmd3.xlsx | F24: -11.317423 | G24: 5.3440876 | H24: 3.3489837 | I24: 15.085406 | J24: 2.3494916 | K24: 4.42771 | M24: -18.968542 | O24: -27.987602 | Q24: -4.5257931 | R24: -18.694773
C25: 39995 | D25: 40025 | E25: grid_20qvjmd3.xlsx | F25: -5.7963273 | G25: 5.0676272 | H25: 5.6772306 | I25: 13.610745 | J25: 7.1269009 | K25: 5.5881495 | M25: -17.076088 | O25: -21.775529 | Q25: -3.6163502 | R25: -16.679278
C26: 40026 | D26: 40056 | E26: grid_20qvjmd3.xlsx | F26: -9.1868082 | G26: 4.8558221 | H26: 10.826127 | I26: 12.062642 | J26: 0.93196223 | K26: 9.9743236 | M26: -10.698901 | O26: -12.275548 | Q26: -3.2110536 | R26: -10.117561
... C45: 40603 | D45: 40633 | E45: grid_u4lflnxf.xlsx | F45: 4.7677691 | G45: 9.015118 | H45: 2.3945869 | I45: -5.8925242 | J45: -3.2929993 | K45: 6.3833764 | M45: 2.6363086 | O45: 2.5143455 | Q45: 5.7412671 | R45: 3.5659272
C46: 40634 | D46: 40662 | E46: grid_u4lflnxf.xlsx | F46: -0.021035464 | G46: 9.3085961 | H46: -5.3963529 | I46: 7.5125872 | J46: 0.75100571 | K46: 1.4885825 | L46: 1.2659443 | M46: 8.1071948 | O46: 6.1611781 | Q46: 1.9198385 | R46: 0.24485691
C47: 40664 | D47: 40694 | E47: grid_u4lflnxf.xlsx | F47: -7.2012172 | G47: 14.547061 | H47: -4.3502695 | I47: 21.300265 | J47: -0.50630249 | K47: -8.9708417 | L47: -0.2632546 | M47: 4.8374017 | O47: 0.24429628 | Q47: -8.1149346 | R47: -5.718413
C48: 40695 | D48: 40724 | E48: grid_u4lflnxf.xlsx | F48: 1.5860788 | G48: 70.239825 | H48: -3.5714129 | I48: 21.426029 | J48: 4.4976571 | K48: 6.1648468 | L48: -4.5436674 | M48: 2.2664764 | O48: 6.3068392 | Q48: -2.7325836 | R48: -26.164536
C49: 40725 | D49: 40753 | E49: grid_u4lflnxf.xlsx | F49: 6.6626155 | G49: 86.259598 | H49: 2.007768 | I49: 16.75537 | J49: 7.8523928 | K49: 5.9275363 | L49: -2.8627404 | M49: -8.3627431 | O49: 5.5890962 | Q49: -2.6736854 | R49: -34.08385
C50: 40756 | D50: 40786 | E50: grid_u4lflnxf.xlsx | F50: 7.5683218 | G50: 81.910619 | H50: -2.7473794 | I50: 17.398422 | J50: 14.704254 | K50: 11.363942 | L50: -23.2151 | M50: -5.7954705 | O50: 3.807791 | Q50: 3.1400942 | R50: -32.148471
C51: 40787 | D51: 40816 | E51: grid_u4lflnxf.xlsx | F51: -0.4861661 | G51: 21.017757 | H51: -3.2452146 | I51: 17.957973 | J51: 0.32947191 | K51: 0.78515205 | L51: -26.444582 | M51: -8.6964188 | O51: -5.6280165 | Q51: 3.3261153 | R51: -5.3979784
C52: 40817 | D52: 40847 | E52: grid_u4lflnxf.xlsx | F52: -8.870355 | G52: 1.6134692 | H52: -4.4946443 | I52: 15.201058 | J52: -10.889278 | K52: 1.2901971 | L52: -35.273245 | M52: -5.7669214 | O52: -13.465397 | Q52: 3.4520731 | R52: 3.2962923
C53: 40848 | D53: 40877 | E53: grid_u4lflnxf.xlsx | F53: -2.7570962 | G53: 3.127216 | H53: -0.29351452 | I53: 0.37267592 | J53: -10.608746 | K53: 4.254079 | L53: -40.477843 | M53: 1.3070394 | O53: -8.4789072 | Q53: -1.9150265 | R53: 12.479534
C54: 40878 | D54: 40907 | E54: grid_u4lflnxf.xlsx | F54: -5.4370125 | G54: 5.5835174 | H54: 7.9941413 | I54: 2.2575697 | J54: -5.0297904 | K54: 0.60868581 | L54: -31.686444 | M54: 12.981458 | O54: -8.2024295 | P54: 5.3327861 | Q54: -4.3747849 | R54: 8.2178119
C55: 40909 | D55: 40939 | E55: grid_u4lflnxf.xlsx | F55: -7.7440983 | G55: -2.3161238 | H55: -2.6541995 | I55: 10.683807 | J55: -0.045601699 | K55: 2.1879362 | L55: -21.305354 | M55: 10.168233 | O55: -7.3785719 | P55: 2.2352226 | Q55: -0.90079796 | R55: 6.5818055
C56: 40940 | D56: 40968 | E56: grid_u4lflnxf.xlsx | F56: -20.435709 | G56: -6.6929857 | H56: -8.6580626 | I56: 8.5133588 | J56: -11.19859 | K56: 1.2643504 | L56: 8.7030597 | M56: 4.6286826 | O56: -20.850867 | P56: 1.9896375 | Q56: 3.5628546 | R56: 3.1753699
C57: 40969 | D57: 40998 | E57: grid_u4lflnxf.xlsx | F57: -18.107834 | G57: -6.1804845 | H57: -16.177627 | I57: 9.3049199 | J57: -6.4033734 | K57: 0.87852391 | L57: 9.045524 | M57: 5.6031772 | O57: -18.216434 | P57: 4.527353 | Q57: 2.4408152 | R57: 4.3640635
C58: 41000 | D58: 41029 | E58: grid_u4lflnxf.xlsx | F58: -12.446917 | G58: -28.335714 | H58: -7.7811407 | I58: 5.9687754 | J58: -6.5742493 | K58: -3.7322781 | L58: 6.7131823 | M58: 15.88236 | O58: -14.589577 | P58: 2.6524632 | Q58: 6.6048321 | R58: 4.6792205
C59: 41030 | D59: 41060 | E59: grid_u4lflnxf.xlsx | F59: 4.7358095 | G59: -25.193356 | H59: -8.0907814 | I59: 11.176972 | J59: 5.3813079 | K59: 1.6533388 | L59: -4.7014151 | M59: 18.459506 | O59: 7.5807347 | P59: 2.7129663 | Q59: 5.7788273 | R59: 11.923579
C60: 41061 | D60: 41089 | E60: grid_u4lflnxf.xlsx | F60: 6.5037301 | G60: -28.974167 | H60: -14.754028 | I60: 3.2618535 | J60: 11.861841 | K60: -1.5568264 | L60: -5.4778556 | M60: 10.981858 | O60: 14.306166 | P60: 2.7619437 | Q60: 6.846596 | R60: 20.134143
C61: 41091 | D61: 41121 | E61: grid_u4lflnxf.xlsx | F61: 0.95610756 | G61: -5.5134672 | H61: -16.340047 | I61: 1.0575759 | J61: 14.118388 | K61: 1.6507232 | L61: -5.4003172 | M61: 2.5549978 | O61: -1.3193154 | P61: -0.9166762 | Q61: 4.5857044 | R61: 20.388873
C62: 41122 | D62: 41152 | E62: grid_u4lflnxf.xlsx | F62: -10.644612 | G62: -9.6129004 | H62: -23.429452 | I62: -6.449379 | J62: 6.4162573 | K62: -1.5331506 | L62: 1.6758848 | M62: -1.6617437 | O62: -20.625697 | P62: 5.2271897 | Q62: 5.5036757 | R62: 10.783213
C63: 41153 | D63: 41180 | E63: grid_u4lflnxf.xlsx | F63: -14.081194 | G63: -8.272008 | H63: -20.299693 | I63: 2.3011381 | J63: -17.254039 | K63: -5.5216938 | L63: 5.3579287 | M63: -3.6816128 | O63: -34.407779 | P63: 1.7098369 | Q63: -3.6378943 | R63: -83.835252
C64: 41183 | D64: 41213 | E64: grid_u4lflnxf.xlsx | F64: -11.289718 | G64: 0.14779313 | H64: -15.810116 | I64: 8.7416181 | J64: -15.660673 | K64: -6.7229108 | L64: 4.9409208 | M64: 5.2357507 | O64: -26.158216 | P64: 10.579083 | Q64: -5.2605503 | R64: -81.161968
C65: 41214 | D65: 41243 | E65: grid_u4lflnxf.xlsx | F65: -10.217938 | G65: 3.8786862 | H65: -4.6440659 | I65: 13.798075 | J65: -15.522942 | K65: -7.878972 | L65: 9.9612938 | M65: 8.2562855 | O65: -17.83408 | P65: 5.18917 | Q65: -33.34306 | R65: -79.96632
... C93: 42064 | D93: 42094 | E93: grid_vtqvtw11.xlsx | F93: -5.8635243 | G93: 6.7849282 | H93: -2.6835739 | I93: 4.7724494 | J93: -29.679173 | K93: 3.2986423 | L93: 8.4160836 | M93: 0.028974596 | O93: -84.224408 | P93: -2.3649492 | Q93: -13.21671 | R93: 3.3687952
C94: 42095 | D94: 42124 | E94: grid_vtqvtw11.xlsx | F94: -5.6492015 | G94: 4.5427027 | H94: -3.1170822 | I94: 3.6874104 | J94: -22.697332 | K94: 2.0647602 | L94: 3.1164623 | M94: -1.5827501 | P94: 2.5375082 | Q94: -7.9795766 | R94: 2.5772382
C95: 42125 | D95: 42153 | E95: grid_vtqvtw11.xlsx | F95: -4.4222936 | G95: 14.084534 | H95: 2.6065257 | I95: 2.3645402 | J95: -6.7173422 | K95: 0.80772899 | L95: 3.434007 | M95: -5.5567841 | O95: -253.16041 | P95: -1.1239981 | Q95: 2.5063222 | R95: -0.36893722
C96: 42156 | D96: 42185 | E96: grid_vtqvtw11.xlsx | F96: 2.8588192 | G96: 14.164897 | H96: 4.722845 | I96: 3.5462146 | J96: 7.192168 | K96: 0.59562307 | L96: -0.58916432 | M96: 0.64359624 | O96: -160.80613 | P96: -1.6265375 | Q96: 1.0342236 | R96: 1.7946895
C97: 42186 | D97: 42216 | E97: grid_vtqvtw11.xlsx | F97: 5.0371422 | G97: 16.371969 | H97: 6.6525597 | I97: 4.1862417 | J97: 19.097506 | K97: 0.6328971 | L97: 0.57147663 | M97: 6.4776602 | P97: -10.984221 | Q97: 1.7638754 | R97: -0.0049910049
C98: 42217 | D98: 42247 | E98: grid_vtqvtw11.xlsx | F98: 1.0017779 | G98: 12.334494 | H98: 3.999142 | I98: 6.2191731 | J98: -0.64720024 | K98: -0.23420784 | L98: -2.5401944 | M98: 9.0667383 | O98: 127.51593 | P98: -4.4438164 | Q98: -2.3632749 | R98: -5.7542101
C99: 42248 | D99: 42277 | E99: grid_vtqvtw11.xlsx | F99: -10.665255 | G99: 13.602765 | H99: 6.5609062 | I99: -4.8135151 | J99: -21.493746 | K99: 0.87785599 | L99: 0.92888066 | M99: 12.620443 | O99: 42.400904 | P99: -4.8158518 | Q99: -5.1276621 | R99: -8.3247967
C100: 42278 | D100: 42307 | E100: grid_vtqvtw11.xlsx | F100: -10.806485 | G100: 5.8752074 | H100: 7.2707056 | I100: 3.8040432 | J100: -23.997811 | K100: -4.6029056 | L100: 1.5068097 | M100: 11.593615 | O100: 70.46493 | P100: -3.9137685 | Q100: -7.5027571 | R100: -6.5771721
C101: 42309 | D101: 42338 | E101: grid_vtqvtw11.xlsx | F101: -8.4248997 | G101: 6.7147059 | H101: 5.5940463 | I101: 3.3206375 | J101: -22.325463 | K101: -5.5825191 | L101: 6.0441725 | M101: 13.491602 | O101: 48.22469 | P101: -3.8839451 | Q101: -8.6551296 | R101: -0.13121715
C102: 42339 | D102: 42369 | E102: grid_vtqvtw11.xlsx | F102: -3.2206821 | G102: -2.0870898 | H102: 4.4051469 | I102: 0.67364749 | J102: -11.120286 | K102: -7.8750853 | L102: 11.933632 | M102: 9.6629351 | O102: 114.19041 | P102: 8.6925937 | Q102: -2.0311084 | R102: 1.3933499
C103: 42370 | D103: 42398 | E103: grid_vtqvtw11.xlsx | F103: -6.6830986 | G103: -3.2545168 | H103: 0.49498069 | I103: -3.7838063 | J103: -39.455854 | K103: -3.737025 | L103: 13.114665 | M103: 5.4790348 | O103: -24.099633 | P103: 12.65477 | Q103: 4.5703986 | R103: -6.28755
C104: 42401 | D104: 42429 | E104: grid_vtqvtw11.xlsx | F104: -11.556859 | G104: -0.3488277 | H104: 4.0875241 | I104: -10.59454 | J104: -42.375719 | K104: -3.9620123 | L104: 16.123292 | M104: 0.23984447 | O104: -105.71327 | P104: 6.0942426 | Q104: 7.4143547 | R104: -8.7087371
C105: 42430 | D105: 42460 | E105: grid_vtqvtw11.xlsx | F105: -7.8882135 | G105: 4.0236798 | H105: 3.1892081 | I105: -1.4783713 | J105: -78.098668 | K105: -3.0498722 | L105: 12.604616 | M105: -7.9561924 | O105: -52.625442 | P105: -0.092792883 | Q105: 8.4341294 | R105: -21.484272
C106: 42461 | D106: 42489 | E106: grid_vtqvtw11.xlsx | F106: -4.2360516 | G106: 7.5262142 | H106: 7.3544398 | I106: -4.297055 | J106: -42.411637 | K106: -3.205343 | L106: 18.734929 | M106: -13.095936 | O106: 8.5585868 | P106: 6.3603573 | Q106: 7.8774741 | R106: -17.466453
C107: 42491 | D107: 42521 | E107: grid_vtqvtw11.xlsx | F107: 4.613159 | G107: 7.5606698 | H107: 5.6549006 | I107: 5.5686894 | J107: -15.242492 | K107: -4.0982868 | L107: 16.525216 | M107: -9.8630456 | O107: 150.12333 | P107: 8.4456056 | Q107: 10.090336 | R107: -22.751102
C108: 42522 | D108: 42551 | E108: grid_vtqvtw11.xlsx | F108: 5.2539612 | G108: 6.2291143 | H108: 4.4346902 | I108: 4.9202095 | J108: 39.295873 | K108: -3.4963774 | L108: 9.3932551 | M108: -3.0292272 | O108: 85.087471 | P108: 5.5257673 | Q108: 8.9332255 | R108: -8.1999274
C109: 42552 | D109: 42580 | E109: grid_vtqvtw11.xlsx | F109: 6.8173253 | G109: 0.5086182 | H109: 2.2598869 | I109: -3.2868539 | J109: 51.677939 | K109: -1.6925312 | L109: 4.9791769 | M109: -2.957295 | O109: 68.659668 | P109: -2.9082686 | Q109: 4.0403533 | R109: 4.9457108
... C153: 43891 | D153: 43921 | E153: grid_1mk3z2wn.xlsx | F153: -22.556034 | G153: 1.3720934 | H153: -19.702493 | I153: -25.551266 | J153: -96.002062 | K153: -6.797825 | L153: 11.344104 | M153: 0.22244661 | O153: 6.1669087 | P153: -26.018886 | Q153: 8.3143623 | R153: 5.0175858
C154: 43922 | D154: 43951 | E154: grid_1mk3z2wn.xlsx | F154: -31.824145 | G154: -1.4721912 | H154: -32.969401 | I154: -30.995259 | J154: -169.98853 | K154: -9.1110724 | L154: 3.3076314 | M154: -23.11961 | N154: 1.3474452 | O154: -3.0738106 | P154: -54.225303 | Q154: 0.42730019 | R154: -4.1178735
C155: 43952 | D155: 43980 | E155: grid_1mk3z2wn.xlsx | F155: -37.967029 | G155: -0.73652788 | H155: -34.820352 | I155: -29.728325 | J155: -286.52181 | K155: -19.320928 | L155: -4.0977378 | M155: -44.237571 | N155: 3.0043367 | O155: 7.1744041 | P155: -54.915481 | Q155: -16.151449 | R155: -0.96858222
C156: 43983 | D156: 44012 | E156: grid_1mk3z2wn.xlsx | F156: -30.893115 | G156: -7.3129342 | H156: -21.528781 | I156: -19.748365 | K156: -30.914464 | L156: -4.7363912 | M156: -48.511301 | N156: 4.2403063 | O156: 5.525092 | P156: -9.8177507 | Q156: -7.6187121 | R156: -1.5349139
C157: 44013 | D157: 44043 | E157: grid_1mk3z2wn.xlsx | F157: -8.2330059 | G157: -9.8399139 | H157: -1.763929 | I157: -10.496508 | J157: -118.25365 | K157: -25.320283 | L157: -2.1068 | M157: -6.3281918 | N157: 4.6452122 | O157: 23.155974 | P157: 16.852372 | Q157: 0.60916079 | R157: 13.808062
C158: 44044 | D158: 44074 | E158: grid_1mk3z2wn.xlsx | F158: 8.3686715 | G158: -3.4869194 | H158: 2.2335866 | I158: -2.57658 | J158: 120.90368 | K158: -14.675052 | L158: -0.064556468 | M158: 12.453289 | N158: -1.5682101 | O158: 20.28746 | P158: 14.090939 | Q158: 24.462265 | R158: 9.1206203
C159: 44075 | D159: 44104 | E159: grid_1mk3z2wn.xlsx | F159: 26.947577 | G159: -0.27915133 | H159: 13.672644 | I159: -1.1179532 | K159: 3.9544843 | L159: -1.9854562 | M159: 34.057778 | N159: -2.3637999 | O159: 29.297756 | P159: -5.0013957 | Q159: 9.2829326 | R159: 10.68382
C160: 44105 | D160: 44134 | E160: grid_1mk3z2wn.xlsx | F160: 40.024716 | G160: 9.2065713 | H160: 9.1477599 | I160: 6.3233525 | J160: 223.06966 | K160: 13.242078 | L160: 4.3487668 | M160: 30.442301 | N160: 4.9168462 | O160: 39.857804 | P160: 8.7675186 | Q160: 5.2647336 | R160: 15.099885
C161: 44136 | D161: 44165 | E161: grid_1mk3z2wn.xlsx | F161: 47.020705 | G161: 2.2688288 | H161: 18.567503 | I161: 8.6404043 | J161: 132.53837 | K161: 19.489801 | L161: 8.3496146 | M161: 24.088909 | N161: 10.712951 | O161: 43.355332 | P161: 12.673655 | Q161: -8.5922017 | R161: 11.290364
C162: 44166 | D162: 44196 | E162: grid_1mk3z2wn.xlsx | F162: 38.492248 | G162: 10.098506 | H162: 14.433035 | I162: 12.746195 | J162: 110.82208 | K162: 13.890125 | L162: 14.92217 | M162: 18.273262 | N162: 14.304333 | O162: 29.007305 | P162: 16.186511 | Q162: 2.1167774 | R162: 0.19389966
C163: 44197 | D163: 44225 | E163: grid_1mk3z2wn.xlsx | F163: 32.481205 | G163: 6.6293454 | H163: 13.086794 | I163: 11.52154 | J163: 58.702056 | K163: 8.9757577 | L163: 14.471381 | M163: 11.464158 | N163: 3.4535725 | O163: 28.542817 | P163: -1.4428377 | Q163: -2.4659615 | R163: -17.280883
C164: 44228 | D164: 44253 | E164: grid_1mk3z2wn.xlsx | F164: 24.835414 | G164: 7.8412372 | H164: 3.9936005 | I164: 7.1652596 | J164: 36.837649 | K164: 3.0059543 | L164: 9.5364932 | M164: 13.690182 | N164: 4.7726883 | O164: 22.902055 | P164: -9.7187655 | Q164: 5.6477749 | R164: -15.464703
C165: 44256 | D165: 44286 | E165: grid_1mk3z2wn.xlsx | F165: 34.128884 | G165: 0.97749348 | H165: 10.388184 | I165: 4.1438723 | J165: 28.048688 | K165: 6.2360312 | L165: 9.0920181 | M165: 2.1909466 | N165: 5.4677546 | O165: 37.219833 | P165: -6.8627717 | Q165: 2.5359393 | R165: -13.724227
C166: 44287 | D166: 44316 | E166: grid_1mk3z2wn.xlsx | F166: 35.887542 | G166: 3.4917332 | H166: 8.8415992 | I166: 5.6041761 | J166: 47.787362 | K166: 5.9307684 | L166: 1.0494252 | M166: -2.7160941 | N166: 7.7527697 | O166: 30.266293 | P166: -12.276349 | Q166: 9.1320289 | R166: -4.8695117
C167: 44317 | D167: 44347 | E167: grid_1mk3z2wn.xlsx | F167: 21.060832 | G167: 0.55010965 | H167: 18.18545 | I167: 10.867756 | J167: 38.595802 | K167: 3.327928 | L167: 2.7451979 | M167: -2.7790651 | N167: -33.380053 | O167: 24.799501 | P167: -3.8633528 | Q167: 11.690548 | R167: -16.733388
C168: 44348 | D168: 44377 | E168: grid_1mk3z2wn.xlsx | F168: 13.742794 | G168: 1.1925631 | H168: 13.547156 | I168: 5.5290803 | J168: 35.851015 | K168: 0.3443467 | L168: -3.100529 | M168: 3.3230963 | N168: -32.661196 | O168: 13.610671 | P168: 4.8880584 | Q168: 13.359824 | R168: -26.21337
C169: 44378 | D169: 44407 | E169: grid_1mk3z2wn.xlsx | F169: 4.3901575 | G169: 0.10622697 | H169: 25.947737 | I169: 8.3681425 | J169: 13.262733 | K169: 2.5371222 | L169: 10.035122 | M169: 8.1163489 | N169: 2.2779182 | O169: 10.471509 | P169: 12.257379 | Q169: 13.690114 | R169: -26.513164
C170: 44409 | D170: 44439 | E170: grid_1mk3z2wn.xlsx | F170: 7.3704234 | G170: 6.5503539 | H170: 16.119553 | I170: 2.6276635 | J170: 18.730461 | K170: 7.1214714 | L170: 14.927553 | M170: 12.701695 | N170: 33.022292 | O170: 3.886454 | P170: 7.6254995 | Q170: 2.5121575 | R170: -7.3014991
C171: 44440 | D171: 44469 | E171: grid_1mk3z2wn.xlsx | F171: -3.9156594 | G171: -5.0767259 | H171: 14.933513 | I171: 12.795456 | J171: 7.9167631 | K171: 5.4554431 | L171: 36.149082 | M171: 17.882575 | N171: 15.177989 | O171: -14.994943 | P171: 1.7296746 | Q171: -1.4940792 | R171: -0.66008952
... C180: 44713 | D180: 44742 | E180: grid_1mk3z2wn.xlsx | F180: 12.586167 | G180: -8.8744237 | H180: 13.562671 | I180: 0.27738869 | J180: 16.752791 | K180: 11.283568 | L180: -7.2174917 | M180: 15.336866 | N180: 12.925541 | O180: 6.9628533 | P180: 9.4727206 | Q180: 31.461991 | R180: 2.06275
C181: 44743 | D181: 44771 | E181: grid_1mk3z2wn.xlsx | F181: 4.9641742 | G181: -8.0935122 | H181: 6.0338475 | I181: -9.5894896 | J181: 16.531015 | K181: 10.592278 | L181: -3.1719681 | M181: 21.622378 | N181: 4.8222592 | O181: -13.785004 | P181: 8.8559924 | Q181: 30.966401
C182: 44774 | D182: 44804 | E182: grid_1mk3z2wn.xlsx | F182: -0.60432801 | G182: -15.459997 | H182: -3.6630257 | I182: 0.43245431 | J182: 13.577685 | K182: 5.931581 | L182: -6.3059791 | M182: 18.443457 | N182: -0.44573794 | O182: -15.301693 | P182: 5.7896749 | Q182: 10.72633
C183: 44805 | D183: 44834 | E183: grid_1mk3z2wn.xlsx | F183: -9.2814744 | G183: -16.067204 | H183: -2.198315 | I183: -3.8648852 | J183: -0.64157465 | K183: 4.0062084 | L183: 2.3077015 | M183: 15.605041 | N183: 0.40815829 | O183: -15.623303 | P183: 5.7543791 | Q183: -8.8928993
C184: 44835 | D184: 44865 | E184: grid_1mk3z2wn.xlsx | F184: -17.271102 | G184: -12.585942 | H184: 2.0460974 | I184: -4.1909536 | J184: -5.043203 | K184: 2.1406949 | L184: 1.9096694 | M184: 12.75688 | N184: 3.0842147 | O184: -19.662589 | P184: 2.9266297 | Q184: 2.5965289
C185: 44866 | D185: 44895 | E185: grid_1mk3z2wn.xlsx | F185: -11.498045 | G185: -2.6570083 | H185: 11.111445 | I185: -1.8966041 | J185: -13.931065 | K185: -1.1680047 | L185: 7.7802398 | M185: 20.923353 | N185: 12.318736 | O185: -13.282024 | P185: 2.6005841 | Q185: 18.860704
C186: 44896 | D186: 44925 | E186: grid_1mk3z2wn.xlsx | F186: -14.092541 | G186: 1.3883074 | H186: -14.852077 | I186: -5.7573471 | J186: -23.41666 | K186: -3.0865042 | L186: 8.8992608 | M186: 13.929803 | N186: 13.847736 | O186: -17.988419 | P186: 4.7766958 | Q186: 2.6526226
C187: 44927 | D187: 44957 | E187: grid_22fp35k1.xlsx | F187: -8.5840292 | G187: 2.0146053 | H187: -18.722291 | I187: -16.875322 | J187: -35.930633 | K187: -0.74753411 | L187: -2.3794218 | M187: 6.4718185 | N187: 15.849816 | O187: -1.1938446 | P187: 8.0779483 | Q187: -0.011327839
C188: 44958 | D188: 44985 | E188: grid_22fp35k1.xlsx | F188: -3.3970834 | G188: 0.15175543 | H188: -30.18546 | I188: -16.053385 | J188: -12.878085 | K188: 3.7793293 | L188: -7.3263704 | M188: 4.4146346 | N188: 13.477546 | O188: -5.2853437 | P188: 11.347181 | Q188: -4.055469
C189: 44986 | D189: 45016 | E189: grid_22fp35k1.xlsx | F189: 1.0059766 | G189: -0.67915399 | H189: 2.2877107 | I189: -5.5718836 | J189: -2.6873867 | K189: 3.1494517 | L189: -7.5533662 | M189: -0.95477245 | N189: 11.686759 | O189: 3.2395276 | P189: 14.485801 | Q189: 6.3200672
C190: 45017 | D190: 45044 | E190: grid_22fp35k1.xlsx | F190: -2.6226668 | G190: 1.7143275 | H190: 1.5166472 | I190: 10.320813 | J190: 10.552059 | K190: 1.683484 | L190: 1.5523331 | M190: 3.4844167 | N190: 3.7587472 | O190: -14.588642 | P190: 7.4756161 | Q190: -0.37264338
C191: 45047 | D191: 45077 | E191: grid_22fp35k1.xlsx | F191: -12.977145 | G191: 4.3887518 | H191: 1.1276448 | I191: 8.3061446 | J191: -5.532396 | K191: -0.49793783 | L191: 1.7778515 | M191: -2.2631503 | N191: -7.454345 | O191: -17.986637 | P191: 31.908918 | Q191: 10.830886
C192: 45078 | D192: 45107 | E192: grid_22fp35k1.xlsx | F192: -12.847212 | G192: 8.143273 | H192: -21.504179 | I192: 4.226849 | J192: -3.176466 | K192: 1.1215036 | L192: 2.156543 | M192: 1.5171013 | N192: -10.570288 | O192: -30.166661 | P192: 26.542421 | Q192: -3.4317494
... C231: 46266 | D231: 46268 | E231: grid_22fp35k1.xlsx | F231: 6.428873 | G231: -0.58139501 | H231: 21.023996 | I231: -3.7564046 | J231: 5.5488571 | K231: -2.5865132 | L231: 1.9765511 | M231: 5.1067064 | N231: 1.7675367 | O231: -9.159868 | P231: -2.7329472 | Q231: -4.7958883

Sheet Series Energia
C2: Earnings de Energia e companhias
C3: Séries 12 meses forward do setor de Energia, Petrobras e demais companhias identificadas.
C6: month | D6: Energy reported | E6: IBOV | F6: Brava Energia | G6: Oleo e Gas Participacoes | H6: PRIO | I6: PetroReconcavo | J6: Petrobras | K6: Ex-Petrobras dynamic | L6: Ex-Petrobras core (PRIO + Brava)
C7: 39448 | D7: 29432.834 | E7: 9959.8781 | J7: 29432.834
C8: 39479 | D8: 29645.202 | E8: 10289.607 | J8: 29645.202
C9: 39508 | D9: 30769.554 | E9: 10303.867 | J9: 30769.554
C10: 39539 | D10: 30957.47 | E10: 10682.523 | J10: 30957.47
C11: 39569 | D11: 32324.668 | E11: 12096.372 | J11: 32324.668
C12: 39600 | D12: 32989.739 | E12: 12518.425 | J12: 32989.739
C13: 39630 | D13: 34314.985 | E13: 11614.211 | J13: 34314.985
C14: 39661 | D14: 34896.378 | E14: 12104.025 | J14: 34896.378
C15: 39692 | D15: 36268.299 | E15: 14266.987 | J15: 36268.299
C16: 39722 | D16: 34382.252 | E16: 13115.579 | J16: 34382.252
C17: 39753 | D17: 33491.21 | E17: 11850.102 | J17: 33491.21
C18: 39783 | D18: 29096.401 | E18: 11084.465 | J18: 29096.401
... C30: 40148 | D30: 29662.501 | E30: 9965.8394 | J30: 29662.501
C31: 40179 | D31: 29007.927 | E31: 9673.17 | G31: 240.3313 | J31: 30689.456 | K31: 240.3313
C32: 40210 | D32: 28320.147 | E32: 9709.5848 | G32: 221.15323 | J32: 29840.462 | K32: 221.15323
C33: 40238 | D33: 29012.179 | E33: 10789.075 | G33: 225.7663 | J33: 30621.367 | K33: 225.7663
C34: 40269 | D34: 29635.32 | E34: 11006.907 | G34: 281.71996 | J34: 31462.024 | K34: 281.71996
C35: 40299 | D35: 27099.448 | E35: 10281.777 | G35: 271.82748 | J35: 32083.242 | K35: 271.82748
C36: 40330 | D36: 26950.784 | E36: 9981.9088 | G36: 274.89589 | J36: 32580.901 | K36: 274.89589
C37: 40360 | D37: 27045.602 | E37: 10157.347 | G37: 277.61677 | J37: 33107.762 | K37: 277.61677
C38: 40391 | D38: 26043.181 | E38: 10478.95 | G38: 378.69573 | J38: 32989.905 | K38: 378.69573
C39: 40422 | D39: 25585.353 | E39: 11407.237 | G39: 298.62256 | J39: 33394.589 | K39: 298.62256
C40: 40452 | D40: 25890.219 | E40: 11592.016 | G40: 284.5337 | J40: 34355.658 | K40: 284.5337
C41: 40483 | D41: 26577.397 | E41: 12019.013 | G41: 165.54761 | J41: 34706.055 | K41: 165.54761
C42: 40513 | D42: 28108.46 | E42: 12597.863 | G42: 244 | J42: 35806.298 | K42: 244
... C76: 41548 | D76: 24035.478 | E76: 8664.9238 | G76: -1027.9929 | J76: 27695.652 | K76: -1027.9929
C77: 41579 | D77: 29458.659 | E77: 9251.2241 | J77: 29458.659
C78: 41609 | D78: 30840.199 | E78: 9121.4767 | J78: 30840.199
C79: 41640 | D79: 30005.7 | E79: 10506.299 | J79: 30005.7
C80: 41671 | D80: 29106.51 | E80: 10482.954 | J80: 29106.51
C81: 41699 | D81: 30657.619 | E81: 10863.991 | J81: 30657.619
C82: 41730 | D82: 30669.298 | E82: 10885.271 | J82: 30669.298
C83: 41760 | D83: 29465.003 | E83: 11182.403 | J83: 29465.003
C84: 41791 | D84: 29770.964 | E84: 11057.439 | J84: 29770.964
C85: 41821 | D85: 28583.342 | E85: 11294.308 | J85: 28583.342
C86: 41852 | D86: 29197.087 | E86: 11753.247 | J86: 29197.087
C87: 41883 | D87: 29713.573 | E87: 11234.331 | J87: 29713.573
C88: 41913 | D88: 28417.593 | E88: 10491.685 | J88: 28417.593
... C158: 44044 | D158: 6956.8558 | E158: 10412.27 | J158: 6956.8558
C159: 44075 | D159: 10949.882 | E159: 11661.71 | H159: 701.17808 | J159: 11253.985 | K159: 701.17808
C160: 44105 | D160: 19121.652 | E160: 14070.599 | H160: 689.63288 | J160: 19631.08 | K160: 689.63288
C161: 44136 | D161: 26183.026 | E161: 16663.022 | H161: 734.81644 | J161: 27031.561 | K161: 734.81644
C162: 44166 | D162: 33166.803 | E162: 17136.888 | H162: 1102 | J162: 34519.699 | K162: 1102
C163: 44197 | D163: 34392.614 | E163: 19470.48 | H163: 1117.6451 | J163: 35886.011 | K163: 1117.6451
C164: 44228 | D164: 37844.583 | E164: 21360.558 | H164: 1154.3808 | J164: 40737.33 | K164: 1154.3808
C165: 44256 | D165: 43905.357 | E165: 24107.48 | H165: 1368.4718 | J165: 47324.893 | K165: 1368.4718
C166: 44287 | D166: 55462.963 | E166: 27876.245 | H166: 1380.1291 | J166: 59894.082 | K166: 1380.1291
C167: 44317 | D167: 55670.248 | E167: 26368.087 | H167: 1392.1749 | J167: 59614.136 | K167: 1392.1749
C168: 44348 | D168: 62837.153 | E168: 27658.971 | H168: 1556.0062 | J168: 66787.52 | K168: 1556.0062
C169: 44378 | D169: 63328.964 | E169: 29127.318 | H169: 1647.8959 | J169: 67324.28 | K169: 1647.8959
C170: 44409 | D170: 67138.018 | E170: 28384.94 | H170: 1655.7137 | J170: 71636.606 | K170: 1655.7137
... C174: 44531 | D174: 87803.122 | E174: 27028.519 | H174: 1850.75 | J174: 94144.397 | K174: 1850.75
C175: 44562 | D175: 85992.85 | E175: 28151.212 | F175: 1403.0493 | H175: 1801.6212 | J175: 95603.303 | K175: 3204.6705 | L175: 3204.6705
C176: 44593 | D176: 85366.794 | E176: 30026.343 | F176: 1552.5993 | H176: 1689.4648 | J176: 94753.246 | K176: 3242.0641 | L176: 3242.0641
C177: 44621 | D177: 100411.17 | E177: 32087.099 | F177: 1676.9966 | H177: 2121.6737 | J177: 111657.21 | K177: 3798.6703 | L177: 3798.6703
C178: 44652 | D178: 102698.62 | E178: 34307.499 | F178: 1870.1305 | H178: 2572.0218 | J178: 116580.58 | K178: 4442.1523 | L178: 4442.1523
C179: 44682 | D179: 108357.29 | E179: 35005.263 | F179: 1884.427 | H179: 2686.3586 | J179: 123853.8 | K179: 4570.7855 | L179: 4570.7855
C180: 44713 | D180: 118723.99 | E180: 36390.79 | F180: 1503.3924 | H180: 2744.0457 | J180: 132833.86 | K180: 4247.4381 | L180: 4247.4381
C181: 44743 | D181: 121159.62 | E181: 36053.563 | F181: 1626.6688 | H181: 3076.4571 | J181: 133718.85 | K181: 4703.1258 | L181: 4703.1258
C182: 44774 | D182: 124115.28 | E182: 34794.354 | F182: 2041.5828 | H182: 3930.3295 | J182: 138654.93 | K182: 5971.9123 | L182: 5971.9123
C183: 44805 | D183: 117964.73 | E183: 33165.195 | F183: 2291.6318 | H183: 4103.8617 | J183: 133333.47 | K183: 6395.4935 | L183: 6395.4935
C184: 44835 | D184: 115200.81 | E184: 30334.773 | F184: 2388.497 | H184: 4574.1889 | J184: 134441.04 | K184: 6962.6859 | L184: 6962.6859
C185: 44866 | D185: 107975.05 | E185: 31015.116 | F185: 2540.3874 | H185: 4790.9973 | J185: 127172.72 | K185: 7331.3847 | L185: 7331.3847
C186: 44896 | D186: 93337.229 | E186: 28805.766 | F186: 2371.3011 | H186: 4831.3819 | J186: 111782.29 | K186: 7202.6829 | L186: 7202.6829
... C194: 45139 | D194: 89188.39 | E194: 26642.157 | F194: 1447.8667 | H194: 6945.3367 | J194: 104767 | K194: 8393.2033 | L194: 8393.2033
C195: 45170 | D195: 88112.252 | E195: 27437.449 | F195: 1526.9314 | H195: 7616.5384 | I195: 1546.2849 | J195: 104374.82 | K195: 10689.755 | L195: 9143.4698
C196: 45200 | D196: 94220.012 | E196: 29781.087 | F196: 1863.8703 | H196: 8429.5885 | I196: 1658.0516 | J196: 111768.5 | K196: 11951.51 | L196: 10293.459
C197: 45231 | D197: 95337.092 | E197: 28689.234 | F197: 1935.9068 | H197: 8443.7004 | I197: 1698.3621 | J197: 111996.67 | K197: 12077.969 | L197: 10379.607
C198: 45261 | D198: 100187.54 | E198: 29546.262 | F198: 1816.0971 | H198: 7682.2293 | I198: 1473.3627 | J198: 117169.82 | K198: 10971.689 | L198: 9498.3264
C199: 45292 | D199: 95929.166 | E199: 29813.133 | F199: 1670.5118 | H199: 7507.269 | I199: 1426.0314 | J199: 111066.21 | K199: 10603.812 | L199: 9177.7809
C200: 45323 | D200: 95003.537 | E200: 29187.81 | F200: 1528.1118 | H200: 7429.9765 | I200: 1364.3527 | J200: 110178.97 | K200: 10322.441 | L200: 8958.0882
C201: 45352 | D201: 91684.168 | E201: 27849.55 | F201: 1754.2763 | H201: 6999.6042 | I201: 1341.4793 | J201: 109209.03 | K201: 10095.36 | L201: 8753.8805
C202: 45383 | D202: 100424.8 | E202: 30546.356 | F202: 2033.5887 | H202: 7539.2139 | I202: 1233.1012 | J202: 117013.36 | K202: 10805.904 | L202: 9572.8026
C203: 45413 | D203: 96521.756 | E203: 29622.187 | F203: 1960.4913 | H203: 7400.506 | I203: 1316.0345 | J203: 112242.99 | K203: 10677.032 | L203: 9360.9973
C204: 45444 | D204: 91041.71 | E204: 29058.415 | F204: 1956.9395 | H204: 7269.4836 | I204: 1277.9313 | J204: 106349.6 | K204: 10504.354 | L204: 9226.4231
C205: 45474 | D205: 101998.07 | E205: 30154.958 | F205: 2162.5761 | H205: 6812.7845 | I205: 1246.9184 | J205: 120957.61 | K205: 10222.279 | L205: 8975.3605
C206: 45505 | D206: 94043.86 | E206: 28540.202 | F206: 2531.2797 | H206: 6694.9792 | I206: 1127.8795 | J206: 110163.62 | K206: 10354.138 | L206: 9226.2588
... C231: 46266 | D231: 110049.06 | E231: 31592.424 | F231: 1429.5263 | H231: 7152.3512 | I231: 467.54199 | J231: 127881.29 | K231: 9049.4195 | L231: 8581.8775
C233: Base auxiliar do gráfico
C235: month_label | D235: Energy reported | E235: Petrobras | F235: Ex-Petrobras dynamic | G235: Ex-Petrobras core (PRIO + Brava)
C236: 2008-01 | D236: =D7 | E236: =J7 | F236: =K7 | G236: =L7
C237: 2008-02 | D237: =D8 | E237: =J8 | F237: =K8 | G237: =L8
C238: 2008-03 | D238: =D9 | E238: =J9 | F238: =K9 | G238: =L9
C239: 2008-04 | D239: =D10 | E239: =J10 | F239: =K10 | G239: =L10
C240: 2008-05 | D240: =D11 | E240: =J11 | F240: =K11 | G240: =L11
C241: 2008-06 | D241: =D12 | E241: =J12 | F241: =K12 | G241: =L12
C242: 2008-07 | D242: =D13 | E242: =J13 | F242: =K13 | G242: =L13
C243: 2008-08 | D243: =D14 | E243: =J14 | F243: =K14 | G243: =L14
C244: 2008-09 | D244: =D15 | E244: =J15 | F244: =K15 | G244: =L15
C245: 2008-10 | D245: =D16 | E245: =J16 | F245: =K16 | G245: =L16
C246: 2008-11 | D246: =D17 | E246: =J17 | F246: =K17 | G246: =L17
C247: 2008-12 | D247: =D18 | E247: =J18 | F247: =K18 | G247: =L18
... C460: 2026-09 | D460: =D231 | E460: =J231 | F460: =K231 | G460: =L231

Sheet Macro IBOV
C2: Base macroeconômica e earnings do IBOV
C3: Variáveis contemporâneas, transformações de três meses e BEst EPS do índice.
C6: month | D6: eps | E6: y_rev3 | F6: ibov_constant_basket | G6: y_constant_basket_rev3 | H6: focus_pib | I6: d_focus_pib3 | J6: focus_ipca | K6: d_focus_ipca3 | L6: ipca12_available | M6: d_ipca12_3_available | N6: ipca3_flow_available | O6: bcom_usd | P6: d_bcom_usd3 | Q6: bcom_brl | R6: d_bcom_brl3 | S6: usdbrl | T6: d_usdbrl3 | U6: swap360 | V6: d_swap360_3 | W6: brent_usd | X6: d_brent3
C7: 36739 | O7: 108.1696 | U7: 17.058 | V7: -4.252 | W7: 35.08 | X7: 16.850637
C8: 36770 | O8: 106.975 | U8: 16.94 | V8: -1.919 | W8: 28.42 | X8: -10.543089
C9: 36800 | O9: 103.8204 | U9: 17.61 | V9: -0.24 | W9: 30.15 | X9: 17.538053
C10: 36831 | O10: 111.5902 | P10: 3.1132867 | U10: 18.39 | V10: 1.332 | W10: 32.53 | X10: -7.5468427
C11: 36861 | O11: 114.6134 | P11: 6.8969564 | U11: 16.66 | V11: -0.28 | W11: 22.58 | X11: -23.002856
C12: 36892 | O12: 111.3745 | P12: 7.0235913 | U12: 15.44 | V12: -2.17 | W12: 26.59 | X12: -12.564972
C13: 36923 | O13: 110.4787 | P13: -1.001049 | U13: 16.44 | V13: -1.95 | W13: 25.16 | X13: -25.690731
C14: 36951 | O14: 105.3717 | P14: -8.4070627 | U14: 19.82 | V14: 3.16 | W14: 23.5 | X14: 3.9935862
C15: 36982 | O15: 108.7085 | P15: -2.4228409 | U15: 21.49 | V15: 6.05 | W15: 27.21 | X15: 2.3049348
C16: 37012 | O16: 106.0908 | P16: -4.0527411 | U16: 22.99 | V16: 6.55 | W16: 28.55 | X16: 12.64015
C17: 37043 | O17: 101.5707 | P17: -3.6738991 | U17: 24.03 | V17: 4.21 | W17: 26.21 | X17: 10.91406
C18: 37073 | O18: 102.5699 | P18: -5.8125471 | U18: 25.65 | V18: 4.16 | W18: 24.35 | X18: -11.10527
C19: 37104 | O19: 102.2247 | P19: -3.7122 | U19: 24.56 | V19: 1.57 | W19: 26.8 | X19: -6.3255049
C20: 37135 | O20: 95.1071 | P20: -6.5751483 | U20: 25.92 | V20: 1.89 | W20: 21.87 | X20: -18.102518
C21: 37165 | O21: 90.4071 | P21: -12.622171 | U21: 24.55 | V21: -1.1 | W21: 19.63 | X21: -21.547284
... C71: 38687 | O71: 171.1493 | P71: -4.064293 | U71: 16.39 | V71: -1.52 | W71: 58.34 | X71: -5.5995966
C72: 38718 | D72: 3859.8472 | O72: 173.6687 | P72: 4.2055058 | Q72: 384.84984 | S72: 2.216 | U72: 15.83 | V72: -1.77 | W72: 63.19 | X72: 7.7632259
C73: 38749 | D73: 3877.8347 | O73: 162.2336 | P73: -2.5367473 | Q73: 346.44985 | S73: 2.1355 | U73: 15.22 | V73: -1.53 | W73: 59.78 | X73: 11.567335
C74: 38777 | D74: 3815.3765 | O74: 165.194 | P74: -3.5415734 | Q74: 358.86745 | S74: 2.1724 | U74: 14.84 | V74: -1.55 | W74: 66.06 | X74: 12.427546
C75: 38808 | D75: 3766.6218 | E75: -2.4449072 | O75: 175.7669 | P75: 1.2009224 | Q75: 367.21221 | R75: -4.6913327 | S75: 2.0892 | T75: -5.8922551 | U75: 14.68 | V75: -1.15 | W75: 72.15 | X75: 13.260122
C76: 38838 | D76: 3760.8328 | E76: -3.0636509 | O76: 176.6788 | P76: 8.5296123 | Q76: 406.44958 | R76: 15.97218 | S76: 2.3005 | T76: 7.4425679 | U76: 15.48 | V76: 0.26 | W76: 67.57 | X76: 12.249294
C77: 38869 | D77: 3633.9221 | E77: -4.8726816 | O77: 173.2354 | P77: 4.7530822 | Q77: 374.93338 | R77: 4.3795259 | S77: 2.1643 | T77: -0.37355636 | U77: 14.78 | V77: -0.06 | W77: 73.2 | X77: 10.2632
C78: 38899 | D78: 3607.4653 | E78: -4.3173133 | O78: 178.0322 | P78: 1.2805747 | Q78: 387.43367 | R78: 5.3604766 | S78: 2.1762 | T78: 4.0799019 | U78: 14.48 | V78: -0.2 | W78: 74.75 | X78: 3.5401927
C79: 38930 | D79: 3691.1313 | E79: -1.8707426 | O79: 170.8761 | P79: -3.3394662 | Q79: 365.4698 | R79: -10.627623 | S79: 2.1388 | T79: -7.2881567 | U79: 13.95 | V79: -1.53 | W79: 67.66 | X79: 0.13310658
C80: 38961 | D80: 3789.2095 | E80: 4.1844889 | O80: 159.9566 | P80: -7.9748835 | Q80: 347.77764 | R80: -7.5185038 | S80: 2.1742 | T80: 0.45637972 | U80: 13.57 | V80: -1.21 | W80: 59.09 | X80: -21.413372
C81: 38991 | D81: 3846.6716 | E81: 6.4202862 | O81: 166.8169 | P81: -6.5067629 | Q81: 357.48862 | R81: -8.0441149 | S81: 2.143 | T81: -1.537352 | U81: 13.01 | V81: -1.47 | W81: 56.13 | X81: -28.647878
C82: 39022 | D82: 3945.2307 | E82: 6.6574435 | O82: 175.214 | P82: 2.5069352 | Q82: 379.6537 | R82: 3.8075852 | S82: 2.1668 | T82: 1.3006501 | U82: 12.75 | V82: -1.2 | W82: 64.36 | X82: -5.0002841
C83: 39052 | D83: 4169.8652 | E83: 9.5726287 | O83: 166.5087 | P83: 4.0145032 | Q83: 355.9956 | R83: 2.3355064 | S83: 2.138 | T83: -1.6789968 | U83: 12.38 | V83: -1.19 | W83: 58.96 | X83: -0.22024575
C84: 39083 | D84: 4156.3594 | E84: 7.7431292 | O84: 166.0942 | P84: -0.43417065 | Q84: 352.90035 | R84: -1.2917807 | S84: 2.1247 | T84: -0.85761006 | U84: 12.357 | V84: -0.653 | W84: 56.52 | X84: 0.69241289
C85: 39114 | D85: 4270.0479 | E85: 7.9117613 | O85: 171.0131 | P85: -2.4267922 | Q85: 362.23995 | R85: -4.6952676 | S85: 2.1182 | T85: -2.2684753 | U85: 12.097 | V85: -0.653 | W85: 59.39 | X85: -8.036646
C86: 39142 | D86: 4370.8179 | E86: 4.7066445 | O86: 171.9626 | P86: 3.2229451 | Q86: 352.59212 | R86: -0.96064655 | S86: 2.0504 | T86: -4.1835917 | U86: 11.851 | V86: -0.529 | W86: 68.47 | X86: 14.953645
... C96: 39448 | D96: 5240.1118 | E96: 5.7634842 | O96: 192.2861 | P96: 4.6638373 | Q96: 338.48122 | R96: 5.5941297 | S96: 1.7603 | T96: 0.93029236 | U96: 12.078 | V96: 0.772 | W96: 91.58 | X96: 1.8848726
C97: 39479 | D97: 5341.6909 | E97: 7.130721 | L97: 4.56 | O97: 215.5208 | P97: 19.551431 | Q97: 362.78616 | R97: 13.758061 | S97: 1.6833 | T97: -5.7933706 | U97: 11.916 | V97: 0.33 | W97: 100.9 | X97: 12.87573
C98: 39508 | D98: 5442.8877 | E98: 8.3475151 | L98: 4.61 | O98: 201.5983 | P98: 8.6115892 | Q98: 352.61559 | R98: 7.3503522 | S98: 1.7491 | T98: -1.261237 | U98: 12.693 | V98: 0.641 | W98: 102.33 | X98: 8.8318166
C99: 39539 | D99: 5607.3096 | E99: 6.7728198 | L99: 4.73 | N99: 1.5176027 | O99: 208.5523 | P99: 8.1205482 | Q99: 351.86944 | R99: 3.8791583 | S99: 1.6872 | T99: -4.2413899 | U99: 13.208 | V99: 1.13 | W99: 111.12 | X99: 19.339779
C100: 39569 | D100: 5684.3027 | E100: 6.2166213 | L100: 5.04 | M100: 0.48 | N100: 1.5276999 | O100: 213.9473 | P100: -0.73277016 | Q100: 348.60573 | R100: -3.9872005 | S100: 1.6294 | T100: -3.2544304 | U100: 13.745 | V100: 1.829 | W100: 127.85 | X100: 23.672777
C101: 39600 | D101: 5735.8604 | E101: 5.2428018 | L101: 5.58 | M101: 0.97 | N101: 1.8307979 | O101: 233.0345 | P101: 14.490941 | Q101: 370.96762 | R101: 5.0736309 | S101: 1.5919 | T101: -9.4173099 | U101: 14.45 | V101: 1.757 | W101: 138.4 | X101: 30.194516
C102: 39630 | D102: 5850.1763 | E102: 4.2400765 | L102: 6.06 | M102: 1.33 | N102: 2.0942932 | O102: 205.1032 | P102: -1.6676582 | Q102: 321.31467 | R102: -9.0839266 | S102: 1.5666 | T102: -7.4162684 | U102: 14.655 | V102: 1.447 | W102: 124.1 | X102: 11.047699
C103: 39661 | D103: 5876.8691 | E103: 3.3315691 | L103: 6.37 | M103: 1.33 | N103: 2.073986 | O103: 189.8888 | P103: -11.929109 | Q103: 310.35425 | R103: -11.622717 | S103: 1.6344 | T103: 0.30639156 | U103: 14.573 | V103: 0.828 | W103: 113.49 | X103: -11.914297
C104: 39692 | D104: 6040.9141 | E104: 5.1817576 | L104: 6.17 | M104: 0.59 | N104: 1.557489 | O104: 167.7756 | P104: -32.855914 | Q104: 321.17283 | R104: -14.413539 | S104: 1.9143 | T104: 18.442375 | U104: 14.431 | V104: -0.019 | W104: 93.52 | X104: -39.197273
C105: 39722 | D105: 5805.9561 | E105: -0.75874931 | L105: 6.25 | M105: 0.19 | N105: 1.0735939 | O105: 131.9721 | P105: -44.092273 | Q105: 279.16058 | R105: -14.063375 | S105: 2.1153 | T105: 30.028898 | U105: 15.344 | V105: 0.689 | W105: 60 | X105: -72.674313
C106: 39753 | D106: 5620.083 | E106: -4.4677722 | L106: 6.41 | M106: 0.04 | N106: 0.99316128 | O106: 122.7531 | P106: -43.626362 | Q106: 286.39526 | R106: -8.0341526 | S106: 2.3331 | T106: 35.592209 | U106: 14.427 | V106: -0.146 | W106: 47.72 | X106: -86.636413
C107: 39783 | D107: 5186.624 | E107: -15.247234 | L107: 6.39 | M107: 0.22 | N107: 1.0737302 | O107: 117.2441 | P107: -35.836929 | Q107: 273.99946 | R107: -15.885325 | S107: 2.337 | T107: 19.951603 | U107: 12.168 | V107: -2.263 | W107: 35.82 | X107: -95.966892
C108: 39814 | D108: 4891.9946 | E108: -17.128419 | H108: 1.9666667 | J108: 4.5916667 | L108: 5.9 | M108: -0.35 | N108: 1.0938925 | O108: 110.9304 | P108: -17.368756 | Q108: 256.93699 | R108: -8.2956294 | S108: 2.3162 | T108: 9.0731265 | U108: 11.164 | V108: -4.18 | W108: 44.17 | X108: -30.629874
C109: 39845 | D109: 4762.7275 | E109: -16.552592 | H109: 1.8333333 | J109: 4.6333333 | L109: 5.84 | M109: -0.57 | N109: 1.1240848 | O109: 105.988 | P109: -14.684914 | Q109: 252.08186 | R109: -12.7619 | S109: 2.3784 | T109: 1.9230137 | U109: 10.62 | V109: -3.807 | W109: 44.41 | X109: -7.1885928
C110: 39873 | D110: 4397.8164 | E110: -16.497486 | H110: 0.86 | J110: 4.365 | L110: 5.9 | M110: -0.49 | N110: 1.3155314 | O110: 109.7822 | P110: -6.5759683 | Q110: 254.16775 | R110: -7.5131662 | S110: 2.3152 | T110: -0.93719787 | U110: 9.791 | V110: -2.377 | W110: 46.13 | X110: 25.29571
C111: 39904 | D111: 4386.1196 | E111: -10.91552 | H111: 0.96666667 | I111: -1 | J111: 4.3066667 | K111: -0.285 | L111: 5.61 | M111: -0.29 | N111: 1.2347053 | O111: 110.5712 | P111: -0.32433203 | Q111: 240.85724 | R111: -6.4626476 | S111: 2.1783 | T111: -6.1383156 | U111: 9.892 | V111: -1.272 | W111: 50.3 | X111: 12.995925
C112: 39934 | D112: 4291.2329 | E112: -10.424643 | H112: 1.0325 | I112: -0.80083333 | J112: 4.3175 | K112: -0.31583333 | L112: 5.53 | M112: -0.31 | N112: 1.2347053 | O112: 124.9324 | P112: 16.444691 | Q112: 246.49163 | R112: -2.2425855 | S112: 1.973 | T112: -18.687277 | U112: 9.339 | V112: -1.281 | W112: 64.98 | X112: 38.061486
C113: 39965 | D113: 4325.3525 | E113: -1.6614505 | H113: 1.505 | I113: 0.645 | J113: 4.37 | K113: 0.005 | L113: 5.2 | M113: -0.7 | N113: 1.1541605 | O113: 122.5361 | P113: 10.990728 | Q113: 239.14145 | R113: -6.093925 | S113: 1.9516 | T113: -17.084653 | U113: 9.226 | V113: -0.565 | W113: 68.11 | X113: 38.966055
C114: 39995 | D114: 4410.8643 | E114: 0.56257384 | H114: 1.9416667 | I114: 0.975 | J114: 4.4125 | K114: 0.10583333 | L114: 4.8 | M114: -0.81 | N114: 1.3156841 | O114: 126.4754 | P114: 13.438817 | Q114: 236.83783 | R114: -1.6828751 | S114: 1.8726 | T114: -15.121692 | U114: 9.205 | V114: -0.687 | W114: 70.08 | X114: 33.163237
C115: 40026 | D115: 4481.2793 | E115: 4.3334483 | H115: 2.6133333 | I115: 1.5808333 | J115: 4.3 | K115: -0.0175 | L115: 4.5 | M115: -1.03 | N115: 1.0736881 | O115: 125.7191 | P115: 0.62772621 | Q115: 237.15651 | R115: -3.8607714 | S115: 1.8864 | T115: -4.4884976 | U115: 9.197 | V115: -0.142 | W115: 69.02 | X115: 6.0316787
C116: 40057 | D116: 4591.853 | E116: 5.9790006 | H116: 3.375 | I116: 1.87 | J116: 4.375 | K116: 0.005 | L116: 4.36 | M116: -0.84 | N116: 0.7517653 | O116: 127.6833 | P116: 4.1147299 | Q116: 227.03368 | R116: -5.1956872 | S116: 1.7781 | T116: -9.310417 | U116: 9.648 | V116: 0.422 | W116: 65.82 | X116: -3.4200302
C117: 40087 | D117: 4706.8179 | E117: 6.4941418 | H117: 4.03 | I117: 2.0883333 | J117: 4.42 | K117: 0.0075 | L117: 4.34 | M117: -0.46 | N117: 0.63129686 | O117: 131.8621 | P117: 4.1708857 | Q117: 229.9675 | R117: -2.9437657 | S117: 1.744 | T117: -7.1146514 | U117: 9.932 | V117: 0.727 | W117: 74.91 | X117: 6.6649946
C118: 40118 | D118: 4877.7139 | E118: 8.4768083 | H118: 4.6 | I118: 1.9866667 | J118: 4.4425 | K118: 0.1425 | L118: 4.17 | M118: -0.33 | N118: 0.67145301 | O118: 136.4934 | P118: 8.2226209 | Q118: 238.9317 | R118: 0.74574193 | S118: 1.7505 | T118: -7.4768789 | U118: 10.122 | V118: 0.925 | W118: 77.77 | X118: 11.935944
C119: 40148 | D119: 5024.3701 | E119: 9.0016447 | H119: 5.2 | I119: 1.825 | J119: 4.5 | K119: 0.125 | L119: 4.22 | M119: -0.14 | N119: 0.93280676 | O119: 139.1873 | P119: 8.6267529 | Q119: 242.35293 | R119: 6.5296681 | S119: 1.7412 | T119: -2.0970848 | U119: 10.462 | V119: 0.814 | W119: 77.91 | X119: 16.863057
C120: 40179 | D120: 5092.3418 | E120: 7.8725729 | F120: 100 | H120: 5.2791667 | I120: 1.2491667 | J120: 4.61 | K120: 0.19 | L120: 4.31 | M120: -0.03 | N120: 1.0637052 | O120: 129.0506 | P120: -2.1552104 | Q120: 241.94406 | R120: 5.0768558 | S120: 1.8748 | T120: 7.2320662 | U120: 10.487 | V120: 0.555 | W120: 71.2 | X120: -5.0794575
C121: 40210 | D121: 5157.1104 | E121: 5.5699776 | F121: 100.30086 | H121: 5.3333333 | I121: 0.73333333 | J121: 4.8466667 | K121: 0.40416667 | L121: 4.59 | M121: 0.42 | N121: 1.5373784 | O121: 133.8318 | P121: -1.9692474 | Q121: 242.36939 | R121: 1.4285243 | S121: 1.811 | T121: 3.3977717 | U121: 10.749 | V121: 0.627 | W121: 76.36 | X121: -1.8296754
C122: 40238 | D122: 5539.7319 | E122: 9.7646013 | F122: 107.85584 | H122: 5.265 | I122: 0.065 | J122: 5.0825 | K122: 0.5825 | L122: 4.83 | M122: 0.61 | N122: 1.9115326 | O122: 132.1517 | P122: -5.1870003 | Q122: 235.36218 | R122: -2.9269529 | S122: 1.781 | T122: 2.2600474 | U122: 10.847 | V122: 0.385 | W122: 80.37 | X122: 3.1086658
C123: 40269 | D123: 5738.8687 | E123: 11.95243 | F123: 111.3309 | G123: 10.73367 | H123: 5.54 | I123: 0.26083333 | J123: 5.2133333 | K123: 0.60333333 | L123: 5.17 | M123: 0.86 | N123: 2.0638364 | O123: 134.7037 | P123: 4.2872976 | Q123: 233.11822 | R123: -3.7160842 | S123: 1.7306 | T123: -8.0033818 | U123: 11.664 | V123: 1.177 | W123: 86.19 | X123: 19.106134
C124: 40299 | D124: 5886.8281 | E124: 13.234091 | F124: 117.42158 | G124: 15.759641 | H124: 5.6841667 | I124: 0.35083333 | J124: 5.3075 | K124: 0.46083333 | L124: 5.26 | M124: 0.67 | N124: 1.8814891 | O124: 125.3626 | P124: -6.537345 | Q124: 227.74624 | R124: -6.223096 | S124: 1.8167 | T124: 0.31424896 | U124: 11.543 | V124: 0.794 | W124: 73 | X124: -4.4999558
C125: 40330 | D125: 6036.2388 | E125: 8.5834997 | F125: 120.71904 | G125: 11.267034 | H125: 5.84 | I125: 0.575 | J125: 5.175 | K125: 0.0925 | L125: 5.22 | M125: 0.39 | N125: 1.5276637 | O125: 125.7471 | P125: -4.9677758 | Q125: 226.5334 | R125: -3.8233111 | S125: 1.8015 | T125: 1.1444647 | U125: 11.861 | V125: 1.014 | W125: 74.94 | X125: -6.9953179
C126: 40360 | D126: 6179.5767 | E126: 7.3987674 | F126: 123.73957 | G126: 10.567223 | H126: 5.625 | I126: 0.085 | J126: 4.9958333 | K126: -0.2175 | L126: 4.84 | M126: -0.33 | N126: 1.002451 | O126: 134.2481 | P126: -0.33879709 | Q126: 235.90076 | R126: 1.1865493 | S126: 1.7572 | T126: 1.5253464 | U126: 11.159 | V126: -0.505 | W126: 77.5 | X126: -10.627623
C127: 40391 | D127: 6383.2007 | E127: 8.0952319 | F127: 127.89623 | G127: 8.5448502 | H127: 5.3666667 | I127: -0.3175 | J127: 4.9233333 | K127: -0.38416667 | L127: 4.6 | M127: -0.66 | N127: 0.440043 | O127: 130.8135 | P127: 4.2562307 | Q127: 229.70851 | R127: 0.85791334 | S127: 1.756 | T127: -3.3983173 | U127: 11.095 | V127: -0.448 | W127: 75.51 | X127: 3.3805657
C128: 40422 | D128: 6518.0547 | E128: 7.679487 | F128: 129.58581 | G128: 7.0877435 | H128: 5.2625 | I128: -0.5775 | J128: 4.985 | K128: -0.19 | L128: 4.49 | M128: -0.73 | N128: 0.050004 | O128: 140.2939 | P128: 10.946676 | Q128: 237.68593 | R128: 4.8057763 | S128: 1.6942 | T128: -6.1408998 | U128: 11.284 | V128: -0.577 | W128: 80.77 | X128: 7.4917816
C129: 40452 | D129: 6240.7466 | E129: 0.98500487 | F129: 131.47904 | G129: 6.066833 | H129: 5.0166667 | I129: -0.60833333 | J129: 5.04 | K129: 0.044166667 | L129: 4.7 | M129: -0.14 | N129: 0.50022902 | O129: 147.2686 | P129: 9.256855 | Q129: 250.5628 | R129: 6.0298358 | S129: 1.7014 | T129: -3.2270192 | U129: 11.209 | V129: 0.05 | W129: 82.47 | X129: 6.2156654
C130: 40483 | D130: 6366.9932 | E130: -0.25423156 | F130: 133.93617 | G130: 4.6144125 | H130: 4.7625 | I130: -0.60416667 | J130: 5.2466667 | K130: 0.32333333 | L130: 5.2 | M130: 0.6 | N130: 1.2438563 | O130: 146.7299 | P130: 11.482084 | Q130: 251.80318 | R130: 9.1836616 | S130: 1.7161 | T130: -2.2984221 | U130: 11.936 | V130: 0.841 | W130: 86.02 | X130: 13.031473
C131: 40513 | D131: 6515.8379 | E131: -0.034015932 | F131: 136.62852 | G131: 5.2922467 | H131: 4.5 | I131: -0.7625 | J131: 5.32 | K131: 0.335 | L131: 5.63 | M131: 1.14 | N131: 2.043363 | O131: 162.3929 | P131: 14.62792 | Q131: 270.57905 | R131: 12.961413 | S131: 1.6662 | T131: -1.6665068 | U131: 12.031 | V131: 0.747 | W131: 93.23 | X131: 14.346395
C132: 40544 | D132: 6453.5439 | E132: 3.3529599 | F132: 138.74927 | G132: 5.3821039 | H132: 4.5916667 | I132: -0.425 | J132: 5.5891667 | K132: 0.54916667 | L132: 5.91 | M132: 1.21 | N132: 2.2262182 | O132: 163.9999 | P132: 10.760769 | Q132: 274.43743 | R132: 9.1013731 | S132: 1.6734 | T132: -1.6593957 | U132: 12.441 | V132: 1.232 | W132: 98.97 | X132: 18.238218
C133: 40575 | D133: 6577.4609 | E133: 3.2521456 | F133: 140.79845 | G133: 4.9966121 | H133: 4.3333333 | I133: -0.42916667 | J133: 5.63 | K133: 0.38333333 | L133: 5.99 | M133: 0.79 | N133: 2.3073904 | O133: 166.1437 | P133: 12.425959 | Q133: 275.99791 | R133: 9.1745553 | S133: 1.6612 | T133: -3.2514042 | U133: 12.616 | V133: 0.68 | W133: 112.27 | X133: 26.632686
C134: 40603 | D134: 6617.4038 | E134: 1.5467305 | F134: 142.69494 | G134: 4.3443335 | H134: 4.075 | I134: -0.425 | J134: 5.765 | K134: 0.445 | L134: 6.01 | M134: 0.38 | N134: 2.2769508 | O134: 169.5579 | P134: 4.3175754 | Q134: 276.15895 | R134: 2.041232 | S134: 1.6287 | T134: -2.2763434 | U134: 12.279 | V134: 0.248 | W134: 116.94 | X134: 22.659142
... C318: 46204 | D318: 20993.697 | E318: 1.3659347 | F318: 315.17571 | G318: 0.67071929 | H318: 1.7453083 | I318: -0.071125 | J318: 4.556025 | K318: -0.039108333 | L318: 4.64 | M318: 0.5 | N318: 1.4158922 | O318: 132.0536 | P318: -6.2064355 | Q318: 670.47574 | R318: -4.444004 | S318: 5.0773 | T318: 1.7624315 | U318: 13.84104 | V318: -0.19895977 | W318: 96.95 | X318: -24.80198
C319: 46235 | D319: 21062.002 | E319: 1.3953969 | H319: 1.65 | I319: -0.16730833 | J319: 4.5087333 | K319: -0.136475 | O319: 138.9678 | P319: 2.8158911 | Q319: 715.85093 | R319: 4.6634961 | S319: 5.1512 | T319: 1.847605 | U319: 13.804447 | V319: -0.22555338 | W319: 89.75 | X319: -3.428031

Sheet Reg IBOV
C2: Regressões contemporâneas do IBOV
C3: OLS com erros HAC/Newey-West. Target direto: BEst EPS do IBOV.
C6: target | D6: sample | E6: specification | F6: n | G6: r2 | H6: adj_r2 | I6: variable | J6: beta | K6: beta_std | L6: se_hac | M6: t_hac | N6: p_hac
C7: IBOV BEst EPS | D7: full | E7: full contemporaneous | F7: 208 | G7: 0.23437637 | H7: 0.21542529 | I7: d_focus_pib3 | J7: 6.4291388 | K7: 0.4221339 | L7: 0.82958327 | M7: 7.7498415 | N7: 9.3258734e-15
C8: IBOV BEst EPS | D8: full | E8: full contemporaneous | F8: 208 | G8: 0.23437637 | H8: 0.21542529 | I8: d_bcom_usd3 | J8: 0.27454119 | K8: 0.15998298 | L8: 0.15725098 | M8: 1.7458791 | N8: 0.08083197
C9: IBOV BEst EPS | D9: full | E9: full contemporaneous | F9: 208 | G9: 0.23437637 | H9: 0.21542529 | I9: d_usdbrl3 | J9: 0.22558039 | K9: 0.12704611 | L9: 0.1970636 | M9: 1.1447086 | N9: 0.25232989
C10: IBOV BEst EPS | D10: full | E10: full contemporaneous | F10: 208 | G10: 0.23437637 | H10: 0.21542529 | I10: d_ipca12_3_available | J10: 2.0102947 | K10: 0.16359353 | L10: 1.068488 | M10: 1.8814386 | N10: 0.059912276
C11: IBOV BEst EPS | D11: full | E11: full contemporaneous | F11: 208 | G11: 0.23437637 | H11: 0.21542529 | I11: d_swap360_3 | J11: 0.8410337 | K11: 0.068898685 | L11: 1.1299511 | M11: 0.74430981 | N11: 0.45668907
C12: IBOV BEst EPS | D12: ex_2013_14 | E12: full contemporaneous | F12: 184 | G12: 0.49329249 | H12: 0.47905914 | I12: d_focus_pib3 | J12: 6.0030225 | K12: 0.59413688 | L12: 0.83785326 | M12: 7.1647659 | N12: 7.7915452e-13
C13: IBOV BEst EPS | D13: ex_2013_14 | E13: full contemporaneous | F13: 184 | G13: 0.49329249 | H13: 0.47905914 | I13: d_bcom_usd3 | J13: 0.13682963 | K13: 0.11629253 | L13: 0.13943863 | M13: 0.98128921 | N13: 0.32645014
C14: IBOV BEst EPS | D14: ex_2013_14 | E14: full contemporaneous | F14: 184 | G14: 0.49329249 | H14: 0.47905914 | I14: d_usdbrl3 | J14: 0.042763015 | K14: 0.035107739 | L14: 0.12443173 | M14: 0.34366649 | N14: 0.73109711
C15: IBOV BEst EPS | D15: ex_2013_14 | E15: full contemporaneous | F15: 184 | G15: 0.49329249 | H15: 0.47905914 | I15: d_ipca12_3_available | J15: 1.5469925 | K15: 0.19039122 | L15: 0.81508853 | M15: 1.8979441 | N15: 0.057703448
C16: IBOV BEst EPS | D16: ex_2013_14 | E16: full contemporaneous | F16: 184 | G16: 0.49329249 | H16: 0.47905914 | I16: d_swap360_3 | J16: 1.7314798 | K16: 0.2081525 | L16: 0.64880648 | M16: 2.6687153 | N16: 0.0076141961
C17: IBOV BEst EPS | D17: clean | E17: full contemporaneous | F17: 160 | G17: 0.18470927 | H17: 0.15823879 | I17: d_focus_pib3 | J17: 3.714619 | K17: 0.36941628 | L17: 0.67748519 | M17: 5.4829524 | N17: 4.1828558e-08
C18: IBOV BEst EPS | D18: clean | E18: full contemporaneous | F18: 160 | G18: 0.18470927 | H18: 0.15823879 | I18: d_bcom_usd3 | J18: 0.090429529 | K18: 0.10467003 | L18: 0.12756262 | M18: 0.70890304 | N18: 0.47838465
... C26: IBOV BEst EPS | D26: post2022 | E26: full contemporaneous | F26: 55 | G26: 0.41032053 | H26: 0.35014915 | I26: d_swap360_3 | J26: 0.1353737 | K26: 0.023996876 | L26: 0.90808564 | M26: 0.14907592 | N26: 0.88149373

Sheet Reg Setores
C2: Regressões contemporâneas por setor
C3: OLS com erros HAC/Newey-West e ajuste Benjamini-Hochberg entre setores.
C6: target | D6: sample | E6: start | F6: end | G6: n | H6: r2 | I6: adj_r2 | J6: invalid_nonpositive_windows_full | K6: d_focus_pib3_beta | L6: d_focus_pib3_beta_std | M6: d_focus_pib3_t | N6: d_focus_pib3_p | O6: d_focus_pib3_partial_r2 | P6: d_bcom_usd3_beta | Q6: d_bcom_usd3_beta_std | R6: d_bcom_usd3_t | S6: d_bcom_usd3_p | T6: d_bcom_usd3_partial_r2 | U6: d_usdbrl3_beta | V6: d_usdbrl3_beta_std | W6: d_usdbrl3_t | X6: d_usdbrl3_p | Y6: d_usdbrl3_partial_r2 | Z6: d_ipca12_3_available_beta | AA6: d_ipca12_3_available_beta_std | AB6: d_ipca12_3_available_t | AC6: d_ipca12_3_available_p | AD6: d_ipca12_3_available_partial_r2 | AE6: d_swap360_3_beta | AF6: d_swap360_3_beta_std | AG6: d_swap360_3_t | AH6: d_swap360_3_p | AI6: d_swap360_3_partial_r2 | AJ6: focus_ibov_same_sample | AK6: focus_difference_vs_ibov | AL6: focus_difference_p | AM6: d_focus_pib3_q_bh | AN6: d_bcom_usd3_q_bh | AO6: d_usdbrl3_q_bh | AP6: d_ipca12_3_available_q_bh | AQ6: d_swap360_3_q_bh | AR6: focus_difference_q_bh
C7: IBOV | D7: full | E7: 39904 | F7: 46204 | G7: 208 | H7: 0.4215624 | I7: 0.40724464 | J7: 0 | K7: 5.9689524 | L7: 0.40884433 | M7: 5.5149009 | N7: 3.4897659e-08 | O7: 0.1345873 | P7: 0.64256477 | Q7: 0.39061204 | R7: 3.570268 | S7: 0.00035661623 | T7: 0.083881617 | U7: 0.27966085 | V7: 0.16430627 | W7: 1.6408485 | X7: 0.10082888 | Y7: 0.013970485 | Z7: 3.1759078 | AA7: 0.26961046 | AB7: 2.9529467 | AC7: 0.0031475628 | AD7: 0.053235348 | AE7: 0.7937536 | AF7: 0.067833728 | AG7: 0.99832486 | AH7: 0.31812186 | AI7: 0.0030171706 | AJ7: 5.9689524 | AK7: 0
C8: IBOV | D8: ex_2013_14 | E8: 39904 | F8: 46204 | G8: 184 | H8: 0.43786187 | I8: 0.42207147 | J8: 0 | K8: 6.1790052 | L8: 0.43008864 | M8: 5.6797236 | N8: 1.3491261e-08 | O8: 0.14829969 | P8: 0.63897071 | Q8: 0.38192273 | R8: 3.2412438 | S8: 0.0011900935 | T8: 0.077393642 | U8: 0.30761287 | V8: 0.17760775 | W8: 1.6585011 | X8: 0.097216362 | Y8: 0.01617212 | Z8: 3.2093944 | AA8: 0.27778238 | AB8: 2.933375 | AC8: 0.0033529864 | AD8: 0.054243231 | AE8: 0.74129808 | AF8: 0.062672924 | AG8: 0.94543185 | AH8: 0.34443845 | AI8: 0.0024387251 | AJ8: 6.1790052 | AK8: 0
C9: IBOV | D9: ex_2020_21 | E9: 39904 | F9: 46204 | G9: 184 | H9: 0.24162811 | I9: 0.22032553 | J9: 0 | K9: 3.8491398 | L9: 0.23110054 | M9: 3.2048454 | N9: 0.0013513503 | O9: 0.044149732 | P9: 0.64404996 | Q9: 0.46031846 | R9: 3.7491514 | S9: 0.00017743394 | T9: 0.12753 | U9: 0.29165169 | V9: 0.20440352 | W9: 1.6992992 | X9: 0.089262829 | Y9: 0.02202491 | Z9: 2.1550161 | AA9: 0.20863911 | AB9: 1.9810197 | AC9: 0.047589066 | AD9: 0.033649904 | AE9: 0.55903573 | AF9: 0.052263912 | AG9: 0.63780261 | AH9: 0.52360218 | AI9: 0.0020580717 | AJ9: 3.8491398 | AK9: 0
C10: IBOV | D10: clean | E10: 39904 | F10: 46204 | G10: 160 | H10: 0.24994436 | I10: 0.2255919 | J10: 0 | K10: 4.1668007 | L10: 0.25487265 | M10: 3.3911467 | N10: 0.00069600846 | O10: 0.05412497 | P10: 0.63887903 | Q10: 0.45483039 | R10: 3.3488843 | S10: 0.00081137662 | T10: 0.12152881 | U10: 0.3272069 | V10: 0.22748048 | W10: 1.7043664 | X10: 0.08831266 | Y10: 0.027239858 | Z10: 2.1457206 | AA10: 0.21510962 | AB10: 1.9322015 | AC10: 0.053334637 | AD10: 0.034660979 | AE10: 0.4906674 | AF10: 0.04484376 | AG10: 0.57065054 | AH10: 0.56823655 | AI10: 0.0014784462 | AJ10: 4.1668007 | AK10: 0
C11: IBOV | D11: ex_seams | E11: 39904 | F11: 46204 | G11: 193 | H11: 0.46120247 | I11: 0.44679612 | J11: 0 | K11: 6.257301 | L11: 0.43455518 | M11: 5.9868328 | N11: 2.1396653e-09 | O11: 0.15400178 | P11: 0.60984866 | Q11: 0.36285411 | R11: 3.0118687 | S11: 0.0025964489 | T11: 0.075643551 | U11: 0.31370507 | V11: 0.18324079 | W11: 1.7904379 | X11: 0.073383544 | Y11: 0.018061079 | Z11: 4.0960215 | AA11: 0.34076955 | AB11: 3.9293752 | AC11: 8.5166872e-05 | AD11: 0.086283523 | AE11: 0.70303597 | AF11: 0.060050466 | AG11: 0.94237851 | AH11: 0.34599888 | AI11: 0.002420156 | AJ11: 6.257301 | AK11: 0
C12: IBOV | D12: audit_clean | E12: 39904 | F12: 46204 | G12: 151 | H12: 0.2947934 | I12: 0.27047593 | J12: 0 | K12: 4.4424881 | L12: 0.27774876 | M12: 3.3915207 | N12: 0.00069505917 | O12: 0.063878329 | P12: 0.64504593 | Q12: 0.46145056 | R12: 3.1072691 | S12: 0.0018882443 | T12: 0.12319027 | U12: 0.35596149 | V12: 0.25246773 | W12: 1.801418 | X12: 0.071637023 | Y12: 0.033096776 | Z12: 2.7647025 | AA12: 0.26958559 | AB12: 3.2540915 | AC12: 0.0011375562 | AD12: 0.057084106 | AE12: 0.93639823 | AF12: 0.08449023 | AG12: 1.2789754 | AH12: 0.20090572 | AI12: 0.005526305 | AJ12: 4.4424881 | AK12: 0
C13: IBOV | D13: since_2020 | E13: 43831 | F13: 46204 | G13: 79 | H13: 0.61992562 | I13: 0.59389313 | J13: 0 | K13: 6.5172664 | L13: 0.43090681 | M13: 4.8832492 | N13: 1.0435187e-06 | O13: 0.13612403 | P13: 0.85500466 | Q13: 0.45349554 | R13: 2.5617656 | S13: 0.010414156 | T13: 0.09919709 | U13: 0.40482318 | V13: 0.17702816 | W13: 1.3823404 | X13: 0.1668672 | Y13: 0.01567803 | Z13: 3.3842298 | AA13: 0.2807177 | AB13: 2.684465 | AC13: 0.0072645986 | AD13: 0.056850394 | AE13: 1.0210286 | AF13: 0.076150541 | AG13: 0.81298348 | AH13: 0.41622753 | AI13: 0.0035003946 | AJ13: 6.5172664 | AK13: 0
C14: IBOV | D14: since_2022 | E14: 44562 | F14: 46204 | G14: 55 | H14: 0.53948786 | I14: 0.49249683 | J14: 0 | K14: 0.29824028 | L14: 0.0078827421 | M14: 0.078798827 | N14: 0.93719264 | O14: 6.0261017e-05 | P14: 1.0652937 | Q14: 0.74548043 | R14: 3.6260121 | S14: 0.00028783189 | T14: 0.29596293 | U14: 0.66265911 | V14: 0.32388801 | W14: 2.289283 | X14: 0.022062917 | Y14: 0.050408482 | Z14: 2.4331403 | AA14: 0.26202956 | AB14: 2.0356796 | AC14: 0.041782536 | AD14: 0.061604595 | AE14: -0.0087017059 | AF14: -0.00072751684 | AG14: -0.0060105232 | AH14: 0.99520433 | AI14: 3.2166863e-07 | AJ14: 0.29824028 | AK14: 0
C15: IBOV | D15: since_2022_ex_seams | E15: 44562 | F15: 46204 | G15: 52 | H15: 0.56284619 | I15: 0.51532947 | J15: 0 | K15: -0.25374866 | L15: -0.0066952454 | M15: -0.067167884 | N15: 0.94644805 | O15: 4.3661811e-05 | P15: 1.160931 | Q15: 0.79562584 | R15: 3.8866852 | S15: 0.00010162241 | T15: 0.32143592 | U15: 0.75927007 | V15: 0.37246748 | W15: 2.5646772 | X15: 0.010327184 | Y15: 0.06292159 | Z15: 2.3570315 | AA15: 0.25372075 | AB15: 2.0169735 | AC15: 0.043698275 | AD15: 0.057732151 | AE15: -0.041408225 | AF15: -0.0034492522 | AG15: -0.027919874 | AH15: 0.97772606 | AI15: 7.2562538e-06 | AJ15: -0.25374866 | AK15: 0
C16: Communication Services | D16: full | E16: 39904 | F16: 46204 | G16: 208 | H16: 0.063171163 | I16: 0.039982331 | J16: 0 | K16: -0.88354001 | L16: -0.059416053 | M16: -0.85269266 | N16: 0.39382976 | O16: 0.0028424687 | P16: -0.031289258 | Q16: -0.018674187 | R16: -0.12556486 | S16: 0.90007638 | T16: 0.00019171625 | U16: -0.30819362 | V16: -0.17777219 | W16: -1.2553155 | X16: 0.20936427 | Y16: 0.016354258 | Z16: 2.7646552 | AA16: 0.2304239 | AB16: 2.3123877 | AC16: 0.020756327 | AD16: 0.038884963 | AE16: -0.31528329 | AF16: -0.026453226 | AG16: -0.25350598 | AH16: 0.79987724 | AI16: 0.00045884474 | AJ16: 5.9689524 | AK16: -6.8524924 | AL16: 2.4019729e-06 | AM16: 0.43321274 | AN16: 0.98667148 | AO16: 0.50331004 | AP16: 0.22467052 | AQ16: 0.83724133 | AR16: 8.8072339e-06
C17: Communication Services | D17: ex_2013_14 | E17: 39904 | F17: 46204 | G17: 184 | H17: 0.076070613 | I17: 0.05011754 | J17: 0 | K17: -1.0551455 | L17: -0.07550816 | M17: -0.94587222 | N17: 0.34421376 | O17: 0.0045710089 | P17: -0.13883138 | Q17: -0.085314786 | R17: -0.51678016 | S17: 0.60530963 | T17: 0.0038619166 | U17: -0.40675778 | V17: -0.24145456 | W17: -1.5090058 | X17: 0.13129731 | Y17: 0.029889176 | Z17: 2.7410222 | AA17: 0.24391375 | AB17: 2.2910071 | AC17: 0.021963004 | AD17: 0.041822378 | AE17: -0.13581286 | AF17: -0.011805112 | AG17: -0.11660739 | AH17: 0.90717118 | AI17: 8.6525306e-05 | AJ17: 6.1790052 | AK17: -7.2341507 | AL17: 7.8489619e-07 | AM17: 0.42070571 | AN17: 0.96625461 | AO17: 0.3610676 | AP17: 0.24159305 | AQ17: 0.96832275 | AR17: 2.8779527e-06
C18: Communication Services | D18: ex_2020_21 | E18: 39904 | F18: 46204 | G18: 184 | H18: 0.083213382 | I18: 0.057460949 | J18: 0 | K18: -0.73985679 | L18: -0.03306912 | M18: -0.42801143 | N18: 0.6686428 | O18: 0.00090400624 | P18: -0.0040099085 | Q18: -0.0021335902 | R18: -0.013955539 | S18: 0.98886545 | T18: 2.7397918e-06 | U18: -0.35286328 | V18: -0.18410605 | W18: -1.2269518 | X18: 0.21984071 | Y18: 0.017867899 | Z18: 3.5699441 | AA18: 0.25730268 | AB18: 2.5040113 | AC18: 0.012279411 | AD18: 0.051177731 | AE18: 0.29074363 | AF18: 0.020235329 | AG18: 0.18604113 | AH18: 0.8524125 | AI18: 0.00030851565 | AJ18: 3.8491398 | AK18: -4.5889966 | AL18: 0.026764239 | AM18: 0.74870983 | AN18: 0.98886545 | AO18: 0.42341853 | AP18: 0.067536759 | AQ18: 0.8524125 | AR18: 0.098135545
C19: Communication Services | D19: clean | E19: 39904 | F19: 46204 | G19: 160 | H19: 0.10191467 | I19: 0.072756057 | J19: 0 | K19: -1.4236058 | L19: -0.066425294 | M19: -0.7477053 | N19: 0.45463793 | O19: 0.0036763612 | P19: -0.15220094 | Q19: -0.08265543 | R19: -0.4824356 | S19: 0.62949654 | T19: 0.0040134982 | U19: -0.49140218 | V19: -0.26060454 | W19: -1.5309956 | X19: 0.12577049 | Y19: 0.03575037 | Z19: 3.492706 | AA19: 0.26709879 | AB19: 2.4886259 | AC19: 0.012823782 | AD19: 0.053439821 | AE19: 0.68114916 | AF19: 0.047487605 | AG19: 0.4751628 | AH19: 0.63467094 | AI19: 0.0016579141 | AJ19: 4.1668007 | AK19: -5.5904065 | AL19: 0.011568349 | AM19: 0.71443104 | AN19: 0.71816763 | AO19: 0.27372097 | AP19: 0.070530803 | AQ19: 0.69813803 | AR19: 0.063625919
C20: Communication Services | D20: ex_seams | E20: 39904 | F20: 46204 | G20: 193 | H20: 0.076692197 | I20: 0.052004823 | J20: 0 | K20: -0.45637954 | L20: -0.031181623 | M20: -0.41793581 | N20: 0.67599405 | O20: 0.00079292719 | P20: -0.12019341 | Q20: -0.070356673 | R20: -0.5241191 | S20: 0.6001957 | T20: 0.0028439267 | U20: -0.32432742 | V20: -0.18637985 | W20: -1.3160974 | X20: 0.18814134 | Y20: 0.018685179 | Z20: 3.3204804 | AA20: 0.2717779 | AB20: 2.6025376 | AC20: 0.0092536675 | AD20: 0.05488259 | AE20: -0.74778822 | AF20: -0.062839413 | AG20: -0.58995861 | AH20: 0.5552184 | AI20: 0.0026501767 | AJ20: 6.257301 | AK20: -6.7136805 | AL20: 7.3662516e-06 | AM20: 0.67599405 | AN20: 0.8090556 | AO20: 0.39477874 | AP20: 0.10179034 | AQ20: 0.67860027 | AR20: 2.7009589e-05
C21: Communication Services | D21: audit_clean | E21: 39904 | F21: 46204 | G21: 151 | H21: 0.10328106 | I21: 0.072359722 | J21: 0 | K21: -1.3415917 | L21: -0.062260558 | M21: -0.65010792 | N21: 0.51562251 | O21: 0.0032097802 | P21: -0.18061909 | Q21: -0.095910237 | R21: -0.60460065 | S21: 0.54544438 | T21: 0.0053217688 | U21: -0.50961146 | V21: -0.26829268 | W21: -1.5457111 | X21: 0.12217435 | Y21: 0.037375892 | Z21: 3.655278 | AA21: 0.26456687 | AB21: 2.543763 | AC21: 0.010966547 | AD21: 0.054978484 | AE21: 0.80994479 | AF21: 0.054246046 | AG21: 0.5413798 | AH21: 0.58824583 | AI21: 0.0022780227 | AJ21: 4.4424881 | AK21: -5.7840798 | AL21: 0.016406868 | AM21: 0.69927711 | AN21: 0.95814761 | AO21: 0.27322637 | AP21: 0.06031601 | AQ21: 0.64707041 | AR21: 0.060158516
C22: Communication Services | D22: since_2020 | E22: 43831 | F22: 46204 | G22: 79 | H22: 0.18628387 | I22: 0.13054989 | J22: 0 | K22: -0.053783203 | L22: -0.0097668555 | M22: -0.080166776 | N22: 0.93610461 | O22: 6.9932267e-05 | P22: 0.13015136 | Q22: 0.18960224 | R22: 1.0829583 | S22: 0.27882694 | T22: 0.01733963 | U22: -0.034908285 | V22: -0.041927186 | W22: -0.2897191 | X22: 0.77203114 | Y22: 0.00087942381 | Z22: 1.8253649 | AA22: 0.41586259 | AB22: 2.518404 | AC22: 0.011788803 | AD22: 0.12476524 | AE22: -1.5872727 | AF22: -0.32514483 | AG22: -1.7553537 | AH22: 0.079198819 | AI22: 0.063815288 | AJ22: 6.5172664 | AK22: -6.5710496 | AL22: 1.7365089e-05 | AM22: 0.93610461 | AN22: 0.55137209 | AO22: 0.83190499 | AP22: 0.064838416 | AQ22: 0.14519784 | AR22: 9.5507989e-05
C23: Communication Services | D23: since_2022 | E23: 44562 | F23: 46204 | G23: 55 | H23: 0.33832041 | I23: 0.27080208 | J23: 0 | K23: 4.0813764 | L23: 0.19333399 | M23: 1.3585496 | N23: 0.17428935 | O23: 0.036249184 | P23: 0.23246316 | Q23: 0.29154902 | R23: 3.1616252 | S23: 0.0015689134 | T23: 0.045267656 | U23: 0.10224464 | V23: 0.089564475 | W23: 0.48263305 | X23: 0.62935631 | Y23: 0.0038546543 | Z23: 2.1792817 | AA23: 0.42061722 | AB23: 2.9140183 | AC23: 0.0035680895 | AD23: 0.1587401 | AE23: -2.6386691 | AF23: -0.39537948 | AG23: -1.9991965 | AH23: 0.045587103 | AI23: 0.095005963 | AJ23: 0.29824028 | AK23: 3.7831361 | AL23: 0.4740158 | AM23: 0.63906096 | AN23: 0.0093534983 | AO23: 0.72319215 | AP23: 0.013082995 | AQ23: 0.16715271 | AR23: 0.97723115
C24: Communication Services | D24: since_2022_ex_seams | E24: 44562 | F24: 46204 | G24: 52 | H24: 0.34887438 | I24: 0.27809986 | J24: 0 | K24: 4.3851675 | L24: 0.20654765 | M24: 1.4812621 | N24: 0.13853675 | O24: 0.04155366 | P24: 0.22308752 | Q24: 0.27292861 | R24: 2.4906345 | S24: 0.012751523 | T24: 0.037824638 | U24: 0.10050022 | V24: 0.088009675 | W24: 0.48486008 | X24: 0.6277756 | Y24: 0.0035130457 | Z24: 2.2574288 | AA24: 0.43378646 | AB24: 3.0756175 | AC24: 0.0021006714 | AD24: 0.16875543 | AE24: -2.7232164 | AF24: -0.40494106 | AG24: -2.069348 | AH24: 0.038513438 | AI24: 0.10001064 | AJ24: -0.25374866 | AK24: 4.6389161 | AL24: 0.37531202 | AM24: 0.68456425 | AN24: 0.14026675 | AO24: 0.69055316 | AP24: 0.0077024618 | AQ24: 0.14121594 | AR24: 0.91277505
C25: Consumer Discretionary | D25: full | E25: 39904 | F25: 46204 | G25: 208 | H25: 0.19275513 | I25: 0.17277383 | J25: 0 | K25: 3.925595 | L25: 0.27568824 | M25: 3.3457687 | N25: 0.00082054823 | O25: 0.061196218 | P25: 0.015085837 | Q25: 0.0094026659 | R25: 0.069700518 | S25: 0.94443203 | T25: 4.860462e-05 | U25: -0.20256108 | V25: -0.1220201 | W25: -0.99348209 | X25: 0.32047508 | Y25: 0.0077048809 | Z25: 2.2831568 | AA25: 0.19872727 | AB25: 1.9691613 | AC25: 0.048934569 | AD25: 0.028922882 | AE25: 1.9040317 | AF25: 0.16683495 | AG25: 1.5358272 | AH25: 0.12458076 | AI25: 0.018250828 | AJ25: 5.9689524 | AK25: -2.0433574 | AL25: 0.23297112 | AM25: 0.0090260306 | AN25: 0.98667148 | AO25: 0.50331004 | AP25: 0.22467052 | AQ25: 0.36354797 | AR25: 0.28474248
C26: Consumer Discretionary | D26: ex_2013_14 | E26: 39904 | F26: 46204 | G26: 184 | H26: 0.26408326 | I26: 0.24341144 | J26: 0 | K26: 4.5389258 | L26: 0.35427917 | M26: 4.3825744 | N26: 1.1728507e-05 | O26: 0.10062724 | P26: 0.076172742 | Q26: 0.051056057 | R26: 0.38163701 | S26: 0.70273063 | T26: 0.0013830848 | U26: -0.14080318 | V26: -0.091163922 | W26: -0.73607907 | X26: 0.46168258 | Y26: 0.0042607802 | Z26: 2.2053776 | AA26: 0.21405121 | AB26: 1.8330333 | AC26: 0.066797614 | AD26: 0.032208576 | AE26: 1.6635306 | AF26: 0.15771428 | AG26: 1.3570325 | AH26: 0.17477089 | AI26: 0.015443472 | AJ26: 6.1790052 | AK26: -1.6400794 | AL26: 0.33350838 | AM26: 0.00012901358 | AN26: 0.96625461 | AO26: 0.56427871 | AP26: 0.2632026 | AQ26: 0.38882619 | AR26: 0.40762136
C27: Consumer Discretionary | D27: ex_2020_21 | E27: 39904 | F27: 46204 | G27: 184 | H27: 0.063649121 | I27: 0.03734713 | J27: 0 | K27: 2.4476718 | L27: 0.12598564 | M27: 1.1313291 | N27: 0.25791662 | O27: 0.01312104 | P27: 0.047207995 | Q27: 0.028925774 | R27: 0.19617761 | S27: 0.84447115 | T27: 0.00050357659 | U27: -0.11620186 | V27: -0.069818022 | W27: -0.49281767 | X27: 0.62214142 | Y27: 0.002569641 | Z27: 1.9373754 | AA27: 0.1608013 | AB27: 1.3776827 | AC27: 0.16830127 | AD27: 0.019988101 | AE27: 1.6145215 | AF27: 0.12940074 | AG27: 1.1757048 | AH27: 0.23971286 | AI27: 0.012616248 | AJ27: 3.8491398 | AK27: -1.401468 | AL27: 0.57354024 | AM27: 0.70438786 | AN27: 0.92891826 | AO27: 0.83730602 | AP27: 0.61710466 | AQ27: 0.43947358 | AR27: 0.63089426
... C114: Utilities | D114: since_2022_ex_seams | E114: 44562 | F114: 46204 | G114: 52 | H114: 0.13269693 | I114: 0.038424856 | J114: 0 | K114: 0.314343 | L114: 0.0098001198 | M114: 0.066063215 | N114: 0.9473275 | O114: 9.3547357e-05 | P114: 0.38332182 | Q114: 0.31040653 | R114: 1.3182923 | S114: 0.18740582 | T114: 0.048925846 | U114: 0.8804575 | V114: 0.51034671 | W114: 2.2315229 | X114: 0.025646516 | Y114: 0.11812821 | Z114: 0.87733281 | AA114: 0.1115886 | AB114: 0.66729389 | AC114: 0.50458443 | AD114: 0.011167229 | AE114: -2.1628522 | AF114: -0.21287763 | AG114: -1.1366454 | AH114: 0.25568656 | AI114: 0.027639017 | AJ114: -0.25374866 | AK114: 0.56809166 | AL114: 0.91277505 | AM114: 0.9473275 | AN114: 0.34357734 | AO114: 0.094037224 | AP114: 0.55504287 | AQ114: 0.6247004 | AR114: 0.91277505

Sheet Scatter Focus-Juros
C2: Earnings ao Focus × performance aos juros
C3: Setores GICS ajustados. Eixo X: beta mensal do earnings ao Focus PIB; eixo Y: beta diário de performance ao swap DI 360d, controlado pelo retorno do Ibovespa.
C6: Setor | D6: Beta Focus earnings (raw) | E6: Beta Focus earnings (pad.) | F6: Beta performance DI (pad.) | G6: Quadrante | H6: Earnings p | I6: Earnings q BH | J6: Performance t | K6: Performance p | L6: Earnings R² | M6: Performance R² | N6: n earnings
C7: Communication Services | D7: -1.0551455 | E7: -0.07550816 | F7: -0.021430184 | G7: Focus − / Juros − | H7: 0.34421376 | I7: 0.42070571 | J7: -1.4779563 | K7: 0.13941947 | L7: 0.076070613 | M7: 0.3275529 | N7: 184
C8: Consumer Discretionary | D8: 4.5389258 | E8: 0.35427917 | F8: -0.13140977 | G8: Focus + / Juros − | H8: 1.1728507e-05 | I8: 0.00012901358 | J8: -7.4342382 | K8: 1.0517229e-13 | L8: 0.26408326 | M8: 0.54782556 | N8: 184
C9: Consumer Staples | D9: 0.98885516 | E9: 0.09480916 | F9: -0.020474294 | G9: Focus + / Juros − | H9: 0.46188633 | I9: 0.50807497 | J9: -1.381494 | K9: 0.16712713 | L9: 0.10203261 | M9: 0.55216076 | N9: 184
C10: Energy | D10: 28.626538 | E10: 0.62963032 | F10: 0.046180245 | G10: Focus + / Juros + | H10: 0.0033552441 | I10: 0.018453842 | J10: 3.6728938 | K10: 0.00023981914 | L10: 0.49932929 | M10: 0.64888519 | N10: 182
C11: Financials | D11: 1.7070586 | E11: 0.25143288 | F11: -0.043510384 | G11: Focus + / Juros − | H11: 0.014363515 | I11: 0.052666221 | J11: -3.689253 | K11: 0.00022491345 | L11: 0.14121227 | M11: 0.80282039 | N11: 184
C12: Health Care | D12: -0.60449223 | E12: -0.053616639 | F12: -0.10450905 | G12: Focus − / Juros − | H12: 0.517913 | I12: 0.517913 | J12: -6.467868 | K12: 9.9395279e-11 | L12: 0.1443502 | M12: 0.41124583 | N12: 160
C13: Industrials | D13: 2.9979548 | E13: 0.26770028 | F13: -0.056890686 | G13: Focus + / Juros − | H13: 0.27721776 | I13: 0.38117442 | J13: -4.1522202 | K13: 3.2926524e-05 | L13: 0.1338146 | M13: 0.63833128 | N13: 184
C14: Information Technology | D14: -0.9401233 | E14: -0.10645217 | F14: -0.10496461 | G14: Focus − / Juros − | H14: 0.22986522 | I14: 0.36121677 | J14: -6.1315955 | K14: 8.7002081e-10 | L14: 0.024773621 | M14: 0.26992291 | N14: 76
C15: Materials | D15: 6.7736771 | E15: 0.16589956 | F15: 0.12510117 | G15: Focus + / Juros + | H15: 0.034772289 | I15: 0.095623794 | J15: 6.1628193 | K15: 7.1461044e-10 | L15: 0.031766264 | M15: 0.48035613 | N15: 182
C16: Real Estate | D16: 4.3536812 | E16: 0.38394265 | F16: -0.12076633 | G16: Focus + / Juros − | H16: 0.073194091 | I16: 0.161027 | J16: -7.253685 | K16: 4.0558266e-13 | L16: 0.27637675 | M16: 0.63860712 | N16: 152
C17: Utilities | D17: 1.4329922 | E17: 0.12531637 | F17: -0.1024264 | G17: Focus + / Juros − | H17: 0.15067302 | I17: 0.27623388 | J17: -8.6133934 | K17: 7.0929199e-18 | L17: 0.043120982 | M17: 0.60303524 | N17: 184
C39: Notas e fontes
C40: Earnings: regressão mensal das revisões de 3 meses do earnings 12m fwd, modelo completo com Focus PIB, BCOM USD, USD/BRL, IPCA realizado e swap DI; amostra ex_2013_14.
C41: Performance: regressão diária do retorno de cada índice setorial ao swap pré-DI 360d, controlando pelo retorno reconstruído do Ibovespa; HAC de cinco defasagens; 03/01/2011 a 12/08/2026.
C42: Leitura: os betas são associações condicionais, com frequências e janelas amostrais diferentes. O scatter não deve ser interpretado como relação causal.
C43: Fontes: aba Reg Setores do workbook; assimetry_score/outputs/gics_sector_daily_rate_beta_20260904; dados de mercado, composição IBOV e classificação GICS ajustada.

Sheet Swap Robustez
C2: Robustez do sinal do swap pré-DI
C3: O coeficiente positivo aparece em algumas especificações, mas perde magnitude e significância em outras janelas.
C6: Comparação do modelo completo - BEst EPS do IBOV
C7: Amostra | D7: n | E7: R² | F7: Beta swap | G7: Beta pad. | H7: p-valor HAC
C8: full | D8: =SUMIFS('Swap Robustez'!$F$21:$F$68,'Swap Robustez'!$C$21:$C$68,"IBOV BEst EPS",'Swap Robustez'!$D$21:$D$68,$C8,'Swap Robustez'!$E$21:$E$68,"full") | E8: =SUMIFS('Swap Robustez'!$G$21:$G$68,'Swap Robustez'!$C$21:$C$68,"IBOV BEst EPS",'Swap Robustez'!$D$21:$D$68,$C8,'Swap Robustez'!$E$21:$E$68,"full") | F8: =SUMIFS('Swap Robustez'!$H$21:$H$68,'Swap Robustez'!$C$21:$C$68,"IBOV BEst EPS",'Swap Robustez'!$D$21:$D$68,$C8,'Swap Robustez'!$E$21:$E$68,"full") | G8: =SUMIFS('Swap Robustez'!$I$21:$I$68,'Swap Robustez'!$C$21:$C$68,"IBOV BEst EPS",'Swap Robustez'!$D$21:$D$68,$C8,'Swap Robustez'!$E$21:$E$68,"full") | H8: =SUMIFS('Swap Robustez'!$L$21:$L$68,'Swap Robustez'!$C$21:$C$68,"IBOV BEst EPS",'Swap Robustez'!$D$21:$D$68,$C8,'Swap Robustez'!$E$21:$E$68,"full")
C9: ex_2013_14 | D9: =SUMIFS('Swap Robustez'!$F$21:$F$68,'Swap Robustez'!$C$21:$C$68,"IBOV BEst EPS",'Swap Robustez'!$D$21:$D$68,$C9,'Swap Robustez'!$E$21:$E$68,"full") | E9: =SUMIFS('Swap Robustez'!$G$21:$G$68,'Swap Robustez'!$C$21:$C$68,"IBOV BEst EPS",'Swap Robustez'!$D$21:$D$68,$C9,'Swap Robustez'!$E$21:$E$68,"full") | F9: =SUMIFS('Swap Robustez'!$H$21:$H$68,'Swap Robustez'!$C$21:$C$68,"IBOV BEst EPS",'Swap Robustez'!$D$21:$D$68,$C9,'Swap Robustez'!$E$21:$E$68,"full") | G9: =SUMIFS('Swap Robustez'!$I$21:$I$68,'Swap Robustez'!$C$21:$C$68,"IBOV BEst EPS",'Swap Robustez'!$D$21:$D$68,$C9,'Swap Robustez'!$E$21:$E$68,"full") | H9: =SUMIFS('Swap Robustez'!$L$21:$L$68,'Swap Robustez'!$C$21:$C$68,"IBOV BEst EPS",'Swap Robustez'!$D$21:$D$68,$C9,'Swap Robustez'!$E$21:$E$68,"full")
C10: ex_2020_21 | D10: =SUMIFS('Swap Robustez'!$F$21:$F$68,'Swap Robustez'!$C$21:$C$68,"IBOV BEst EPS",'Swap Robustez'!$D$21:$D$68,$C10,'Swap Robustez'!$E$21:$E$68,"full") | E10: =SUMIFS('Swap Robustez'!$G$21:$G$68,'Swap Robustez'!$C$21:$C$68,"IBOV BEst EPS",'Swap Robustez'!$D$21:$D$68,$C10,'Swap Robustez'!$E$21:$E$68,"full") | F10: =SUMIFS('Swap Robustez'!$H$21:$H$68,'Swap Robustez'!$C$21:$C$68,"IBOV BEst EPS",'Swap Robustez'!$D$21:$D$68,$C10,'Swap Robustez'!$E$21:$E$68,"full") | G10: =SUMIFS('Swap Robustez'!$I$21:$I$68,'Swap Robustez'!$C$21:$C$68,"IBOV BEst EPS",'Swap Robustez'!$D$21:$D$68,$C10,'Swap Robustez'!$E$21:$E$68,"full") | H10: =SUMIFS('Swap Robustez'!$L$21:$L$68,'Swap Robustez'!$C$21:$C$68,"IBOV BEst EPS",'Swap Robustez'!$D$21:$D$68,$C10,'Swap Robustez'!$E$21:$E$68,"full")
C11: clean | D11: =SUMIFS('Swap Robustez'!$F$21:$F$68,'Swap Robustez'!$C$21:$C$68,"IBOV BEst EPS",'Swap Robustez'!$D$21:$D$68,$C11,'Swap Robustez'!$E$21:$E$68,"full") | E11: =SUMIFS('Swap Robustez'!$G$21:$G$68,'Swap Robustez'!$C$21:$C$68,"IBOV BEst EPS",'Swap Robustez'!$D$21:$D$68,$C11,'Swap Robustez'!$E$21:$E$68,"full") | F11: =SUMIFS('Swap Robustez'!$H$21:$H$68,'Swap Robustez'!$C$21:$C$68,"IBOV BEst EPS",'Swap Robustez'!$D$21:$D$68,$C11,'Swap Robustez'!$E$21:$E$68,"full") | G11: =SUMIFS('Swap Robustez'!$I$21:$I$68,'Swap Robustez'!$C$21:$C$68,"IBOV BEst EPS",'Swap Robustez'!$D$21:$D$68,$C11,'Swap Robustez'!$E$21:$E$68,"full") | H11: =SUMIFS('Swap Robustez'!$L$21:$L$68,'Swap Robustez'!$C$21:$C$68,"IBOV BEst EPS",'Swap Robustez'!$D$21:$D$68,$C11,'Swap Robustez'!$E$21:$E$68,"full")
C12: post2022 | D12: =SUMIFS('Swap Robustez'!$F$21:$F$68,'Swap Robustez'!$C$21:$C$68,"IBOV BEst EPS",'Swap Robustez'!$D$21:$D$68,$C12,'Swap Robustez'!$E$21:$E$68,"full") | E12: =SUMIFS('Swap Robustez'!$G$21:$G$68,'Swap Robustez'!$C$21:$C$68,"IBOV BEst EPS",'Swap Robustez'!$D$21:$D$68,$C12,'Swap Robustez'!$E$21:$E$68,"full") | F12: =SUMIFS('Swap Robustez'!$H$21:$H$68,'Swap Robustez'!$C$21:$C$68,"IBOV BEst EPS",'Swap Robustez'!$D$21:$D$68,$C12,'Swap Robustez'!$E$21:$E$68,"full") | G12: =SUMIFS('Swap Robustez'!$I$21:$I$68,'Swap Robustez'!$C$21:$C$68,"IBOV BEst EPS",'Swap Robustez'!$D$21:$D$68,$C12,'Swap Robustez'!$E$21:$E$68,"full") | H12: =SUMIFS('Swap Robustez'!$L$21:$L$68,'Swap Robustez'!$C$21:$C$68,"IBOV BEst EPS",'Swap Robustez'!$D$21:$D$68,$C12,'Swap Robustez'!$E$21:$E$68,"full")
C14: Leitura | D14: O sinal do swap é sensível à janela. Na amostra ex_2013_14, beta = 1,73 e p = 0,008; na amostra limpa, beta = 1,31 e p = 0,085; desde 2022, o efeito é próximo de zero.
C18: Resultados completos
C20: target | D20: sample | E20: specification | F20: n | G20: r2 | H20: beta_swap | I20: beta_std_swap | J20: se_hac_swap | K20: t_hac_swap | L20: p_hac_swap
C21: IBOV BEst EPS | D21: full | E21: swap_only | F21: 245 | G21: 0.039309194 | H21: 2.2287365 | I21: 0.19826546 | J21: 1.1242885 | K21: 1.9823527 | L21: 0.047439777
C22: IBOV BEst EPS | D22: full | E22: focus_swap | F22: 209 | G22: 0.20049097 | H22: 2.4343815 | I22: 0.19945699 | J22: 0.94255981 | K22: 2.5827343 | L22: 0.0098020783
C23: IBOV BEst EPS | D23: full | E23: focus_bcom_fx_swap | F23: 209 | G23: 0.21478869 | H23: 1.8674867 | I23: 0.1530094 | J23: 0.99190353 | K23: 1.8827301 | L23: 0.059736948
C24: IBOV BEst EPS | D24: full | E24: full | F24: 208 | G24: 0.23437637 | H24: 0.8410337 | I24: 0.068898685 | J24: 1.1299511 | K24: 0.74430981 | L24: 0.45668907
C25: IBOV BEst EPS | D25: ex_2013_14 | E25: swap_only | F25: 221 | G25: 0.11219588 | H25: 2.6957984 | I25: 0.33495654 | J25: 1.0654575 | K25: 2.5301792 | L25: 0.011400429
C26: IBOV BEst EPS | D26: ex_2013_14 | E26: focus_swap | F26: 185 | G26: 0.46113158 | H26: 2.8460225 | I26: 0.34215289 | J26: 0.79596532 | K26: 3.5755609 | L26: 0.00034947779
C27: IBOV BEst EPS | D27: ex_2013_14 | E27: focus_bcom_fx_swap | F27: 185 | G27: 0.46784917 | H27: 2.587691 | I27: 0.31109591 | J27: 0.80521171 | K27: 3.2136778 | L27: 0.0013104663
C28: IBOV BEst EPS | D28: ex_2013_14 | E28: full | F28: 184 | G28: 0.49329249 | H28: 1.7314798 | I28: 0.2081525 | J28: 0.64880648 | K28: 2.6687153 | L28: 0.0076141961
C29: IBOV BEst EPS | D29: ex_2020_21 | E29: swap_only | F29: 221 | G29: 0.015026685 | H29: 1.4054515 | I29: 0.12258338 | J29: 1.2152927 | K29: 1.1564717 | L29: 0.24748829
C30: IBOV BEst EPS | D30: ex_2020_21 | E30: focus_swap | F30: 185 | G30: 0.045931639 | H30: 1.0601446 | I30: 0.082487669 | J30: 1.1443247 | K30: 0.92643682 | L30: 0.35421902
C31: IBOV BEst EPS | D31: ex_2020_21 | E31: focus_bcom_fx_swap | F31: 185 | G31: 0.061318882 | H31: 0.53220918 | I31: 0.041410102 | J31: 1.2083254 | K31: 0.44045188 | L31: 0.65960986
C32: IBOV BEst EPS | D32: ex_2020_21 | E32: full | F32: 184 | G32: 0.06590867 | H32: 0.16953602 | I32: 0.013190205 | J32: 1.427854 | K32: 0.11873484 | L32: 0.90548543
... C68: IBOV constant basket | D68: post2022 | E68: full | F68: 55 | G68: 0.38385016 | H68: 0.33223417 | I68: 0.047675268 | J68: 0.86134763 | K68: 0.38571438 | L68: 0.69970821

Sheet Reg Energia
C2: Regressões de Energia, Petrobras e Brent
C3: Especificações com BCOM ou Brent e diferentes janelas de robustez.
C6: target | D6: sample | E6: specification | F6: start | G6: end | H6: n | I6: r2 | J6: adj_r2 | K6: invalid_nonpositive_windows | L6: d_focus_pib3_beta | M6: d_focus_pib3_beta_std | N6: d_focus_pib3_t | O6: d_focus_pib3_p | P6: d_bcom_usd3_beta | Q6: d_bcom_usd3_beta_std | R6: d_bcom_usd3_t | S6: d_bcom_usd3_p | T6: d_usdbrl3_beta | U6: d_usdbrl3_beta_std | V6: d_usdbrl3_t | W6: d_usdbrl3_p | X6: d_ipca12_3_available_beta | Y6: d_ipca12_3_available_beta_std | Z6: d_ipca12_3_available_t | AA6: d_ipca12_3_available_p | AB6: d_swap360_3_beta | AC6: d_swap360_3_beta_std | AD6: d_swap360_3_t | AE6: d_swap360_3_p | AF6: d_brent3_beta | AG6: d_brent3_beta_std | AH6: d_brent3_t | AI6: d_brent3_p
C7: Energy reported | D7: primary | E7: BCOM | F7: 39904 | G7: 46204 | H7: 182 | I7: 0.49932929 | J7: 0.48510569 | K7: 2 | L7: 28.626538 | M7: 0.62963032 | N7: 2.933166 | O7: 0.0033552441 | P7: 0.64002933 | Q7: 0.12484535 | R7: 1.5420799 | S7: 0.12305419 | T7: 0.40457497 | U7: 0.076428366 | V7: 0.79632915 | W7: 0.42584074 | X7: 6.8431751 | Y7: 0.192058 | Z7: 1.8004949 | AA7: 0.071782528 | AB7: 6.8328618 | AC7: 0.18876383 | AD7: 1.6866494 | AE7: 0.091670796
C8: Energy reported | D8: primary | E8: Brent | F8: 39904 | G8: 46204 | H8: 182 | I8: 0.49312584 | J8: 0.478726 | K8: 2 | L8: 28.528349 | M8: 0.62747068 | N8: 2.5915902 | O8: 0.0095533493 | T8: 0.11951441 | U8: 0.022577499 | V8: 0.30361309 | W8: 0.76142268 | X8: 6.7310063 | Y8: 0.18890991 | Z8: 1.784513 | AA8: 0.074340352 | AB8: 7.8301577 | AC8: 0.21631501 | AD8: 1.8940689 | AE8: 0.05821586 | AF8: 0.091298031 | AG8: 0.054349297 | AH8: 0.38138902 | AI8: 0.70291461
C9: Energy reported | D9: clean | E9: BCOM | F9: 39904 | G9: 46204 | H9: 160 | I9: 0.16248799 | J9: 0.13529605 | K9: 2 | L9: 10.089313 | M9: 0.34188998 | N9: 2.4984526 | O9: 0.012473682 | P9: 0.58738923 | Q9: 0.23166536 | R9: 1.9373981 | S9: 0.052696703 | T9: 0.32613696 | U9: 0.12561051 | V9: 0.96016539 | W9: 0.33697198 | X9: 0.99137584 | Y9: 0.055059123 | Z9: 0.56649184 | AA9: 0.57105948 | AB9: 1.8143427 | AC9: 0.091862535 | AD9: 0.73587308 | AE9: 0.46180794
C10: Energy reported | D10: clean | E10: Brent | F10: 39904 | G10: 46204 | H10: 160 | I10: 0.1797696 | J10: 0.15313874 | K10: 2 | L10: 9.5663272 | M10: 0.32416791 | N10: 2.3814957 | O10: 0.017242493 | T10: 0.19961279 | U10: 0.076880167 | V10: 0.69129814 | W10: 0.4893782 | X10: 0.5801982 | Y10: 0.032223101 | Z10: 0.33580493 | AA10: 0.73701797 | AB10: 2.290304 | AC10: 0.11596107 | AD10: 0.94703195 | AE10: 0.3436225 | AF10: 0.25171563 | AG10: 0.24478808 | AH10: 2.1025322 | AI10: 0.03550668
C11: Energy reported | D11: audit_clean | E11: BCOM | F11: 39904 | G11: 46204 | H11: 151 | I11: 0.17821282 | J11: 0.14987534 | K11: 2 | L11: 9.9784555 | M11: 0.34514998 | N11: 2.385385 | O11: 0.017061255 | P11: 0.55154291 | Q11: 0.21828933 | R11: 1.6586329 | S11: 0.09718979 | T11: 0.29701723 | U11: 0.11654756 | V11: 0.85617511 | W11: 0.39190093 | X11: 1.529935 | Y11: 0.082535333 | Z11: 1.0782755 | AA11: 0.28091081 | AB11: 2.7910907 | AC11: 0.13932803 | AD11: 1.1541621 | AE11: 0.24843372
C12: Energy reported | D12: audit_clean | E12: Brent | F12: 39904 | G12: 46204 | H12: 151 | I12: 0.19145125 | J12: 0.16357026 | K12: 2 | L12: 9.457523 | M12: 0.32713117 | N12: 2.2566586 | O12: 0.024029415 | T12: 0.16521876 | U12: 0.064830727 | V12: 0.5739913 | W12: 0.56597369 | X12: 1.0922784 | Y12: 0.058925096 | Z12: 0.74892982 | AA12: 0.4538995 | AB12: 3.1965024 | AC12: 0.15956572 | AD12: 1.3373735 | AE12: 0.18110073 | AF12: 0.22777941 | AG12: 0.22369536 | AH12: 1.7914344 | AI12: 0.073223621
C13: Energy reported | D13: since_2022_ex_seams | E13: BCOM | F13: 44562 | G13: 46204 | H13: 52 | I13: 0.21281835 | J13: 0.12725512 | K13: 2 | L13: 2.6385849 | M13: 0.049870061 | N13: 0.44471144 | O13: 0.6565283 | P13: 0.83000694 | Q13: 0.40746496 | R13: 1.6541718 | S13: 0.09809261 | T13: 0.37434908 | U13: 0.13154518 | V13: 0.73910695 | W13: 0.45984206 | X13: 1.5105103 | Y13: 0.11647169 | Z13: 1.1275567 | AA13: 0.25950716 | AB13: 2.3155222 | AC13: 0.13816351 | AD13: 0.873412 | AE13: 0.38243855
C14: Energy reported | D14: since_2022_ex_seams | E14: Brent | F14: 44562 | G14: 46204 | H14: 52 | I14: 0.34905857 | J14: 0.27830407 | K14: 2 | L14: 0.62056107 | M14: 0.011728794 | N14: 0.13051925 | O14: 0.89615563 | T14: 0.18249927 | U14: 0.064129712 | V14: 0.52741646 | W14: 0.59790442 | X14: 1.1888154 | Y14: 0.091666598 | Z14: 0.93818613 | AA14: 0.34814876 | AB14: 2.3995421 | AC14: 0.14317685 | AD14: 1.2865582 | AE14: 0.19824831 | AF14: 0.41090144 | AG14: 0.5288755 | AH14: 3.0072354 | AI14: 0.0026363551
C15: IBOV | D15: primary | E15: BCOM | F15: 39904 | G15: 46204 | H15: 184 | I15: 0.43786187 | J15: 0.42207147 | K15: 0 | L15: 6.1790052 | M15: 0.43008864 | N15: 5.6797236 | O15: 1.3491261e-08 | P15: 0.63897071 | Q15: 0.38192273 | R15: 3.2412438 | S15: 0.0011900935 | T15: 0.30761287 | U15: 0.17760775 | V15: 1.6585011 | W15: 0.097216362 | X15: 3.2093944 | Y15: 0.27778238 | Z15: 2.933375 | AA15: 0.0033529864 | AB15: 0.74129808 | AC15: 0.062672924 | AD15: 0.94543185 | AE15: 0.34443845
C16: IBOV | D16: primary | E16: Brent | F16: 39904 | G16: 46204 | H16: 184 | I16: 0.38919148 | J16: 0.37203393 | K16: 0 | L16: 6.2185627 | M16: 0.43284203 | N16: 4.263605 | O16: 2.0115493e-05 | T16: 0.049650144 | U16: 0.028666715 | V16: 0.27423236 | W16: 0.78390606 | X16: 3.1688424 | Y16: 0.27427248 | Z16: 2.8565994 | AA16: 0.0042820594 | AB16: 1.6734551 | AC16: 0.14148199 | AD16: 1.9615695 | AE16: 0.049812627 | AF16: 0.10453966 | AG16: 0.19914334 | AH16: 1.2809063 | AI16: 0.20022659
C17: IBOV | D17: clean | E17: BCOM | F17: 39904 | G17: 46204 | H17: 160 | I17: 0.24994436 | J17: 0.2255919 | K17: 0 | L17: 4.1668007 | M17: 0.25487265 | N17: 3.3911467 | O17: 0.00069600846 | P17: 0.63887903 | Q17: 0.45483039 | R17: 3.3488843 | S17: 0.00081137662 | T17: 0.3272069 | U17: 0.22748048 | V17: 1.7043664 | W17: 0.08831266 | X17: 2.1457206 | Y17: 0.21510962 | Z17: 1.9322015 | AA17: 0.053334637 | AB17: 0.4906674 | AC17: 0.04484376 | AD17: 0.57065054 | AE17: 0.56823655
C18: IBOV | D18: clean | E18: Brent | F18: 39904 | G18: 46204 | H18: 160 | I18: 0.24428049 | J18: 0.21974414 | K18: 0 | L18: 3.7117043 | M18: 0.22703556 | N18: 2.6002112 | O18: 0.0093166406 | T18: 0.12801439 | U18: 0.088998042 | V18: 0.70771675 | W18: 0.47912117 | X18: 1.7872608 | Y18: 0.17917384 | Z18: 1.5756801 | AA18: 0.11509955 | AB18: 1.1670305 | AC18: 0.10665888 | AD18: 1.2734896 | AE18: 0.20284435 | AF18: 0.21485025 | AG18: 0.37714787 | AH18: 2.7855148 | AI18: 0.0053442793
C19: IBOV | D19: audit_clean | E19: BCOM | F19: 39904 | G19: 46204 | H19: 151 | I19: 0.2947934 | J19: 0.27047593 | K19: 0 | L19: 4.4424881 | M19: 0.27774876 | N19: 3.3915207 | O19: 0.00069505917 | P19: 0.64504593 | Q19: 0.46145056 | R19: 3.1072691 | S19: 0.0018882443 | T19: 0.35596149 | U19: 0.25246773 | V19: 1.801418 | W19: 0.071637023 | X19: 2.7647025 | Y19: 0.26958559 | Z19: 3.2540915 | AA19: 0.0011375562 | AB19: 0.93639823 | AC19: 0.08449023 | AD19: 1.2789754 | AE19: 0.20090572
C20: IBOV | D20: audit_clean | E20: Brent | F20: 39904 | G20: 46204 | H20: 151 | I20: 0.27448368 | J20: 0.24946587 | K20: 0 | L20: 3.9880655 | M20: 0.24933781 | N20: 2.6567471 | O20: 0.0078898599 | T20: 0.13471882 | U20: 0.095550101 | V20: 0.74129316 | W20: 0.45851571 | X20: 2.3486588 | Y20: 0.22901726 | Z20: 2.5515379 | AA20: 0.010724867 | AB20: 1.5903102 | AC20: 0.14349202 | AD20: 2.0015099 | AE20: 0.045337463 | AF20: 0.20009685 | AG20: 0.35519275 | AH20: 2.4361683 | AI20: 0.014843777
C21: IBOV | D21: since_2022_ex_seams | E21: BCOM | F21: 44562 | G21: 46204 | H21: 52 | I21: 0.56284619 | J21: 0.51532947 | K21: 0 | L21: -0.25374866 | M21: -0.0066952454 | N21: -0.067167884 | O21: 0.94644805 | P21: 1.160931 | Q21: 0.79562584 | R21: 3.8866852 | S21: 0.00010162241 | T21: 0.75927007 | U21: 0.37246748 | V21: 2.5646772 | W21: 0.010327184 | X21: 2.3570315 | Y21: 0.25372075 | Z21: 2.0169735 | AA21: 0.043698275 | AB21: -0.041408225 | AC21: -0.0034492522 | AD21: -0.027919874 | AE21: 0.97772606
C22: IBOV | D22: since_2022_ex_seams | E22: Brent | F22: 44562 | G22: 46204 | H22: 52 | I22: 0.65052912 | J22: 0.61254316 | K22: 0 | L22: -1.7821377 | M22: -0.047022313 | N22: -0.43250513 | O22: 0.66537432 | T22: 0.21614679 | U22: 0.10603296 | V22: 0.92544444 | W22: 0.35473477 | X22: 2.1561962 | Y22: 0.232102 | Z22: 2.0398499 | AA22: 0.041365274 | AB22: 1.2481731 | AC22: 0.10397122 | AD22: 1.1003047 | AE22: 0.27119937 | AF22: 0.40088419 | AG22: 0.72032524 | AH22: 5.8275894 | AI22: 5.6233715e-09
C23: Petrobras | D23: primary | E23: BCOM | F23: 39904 | G23: 46204 | H23: 182 | I23: 0.50804389 | J23: 0.49406786 | K23: 2 | L23: 28.771948 | M23: 0.63191462 | N23: 2.9522005 | O23: 0.0031551794 | P23: 0.61159828 | Q23: 0.11912724 | R23: 1.5314975 | S23: 0.12564649 | T23: 0.35613365 | U23: 0.067180141 | V23: 0.70576912 | W23: 0.48033173 | X23: 6.8958476 | Y23: 0.19325678 | Z23: 1.7291128 | AA23: 0.083788908 | AB23: 7.1728769 | AC23: 0.19787087 | AD23: 1.7269618 | AE23: 0.084174519
C24: Petrobras | D24: primary | E24: Brent | F24: 39904 | G24: 46204 | H24: 182 | I24: 0.50264594 | J24: 0.48851656 | K24: 2 | L24: 28.640701 | M24: 0.62903206 | N24: 2.6036557 | O24: 0.0092235352 | T24: 0.09184448 | U24: 0.017325307 | V24: 0.227892 | W24: 0.8197302 | X24: 6.7863004 | Y24: 0.19018671 | Z24: 1.7175222 | AA24: 0.085883809 | AB24: 8.0963885 | AC24: 0.22334684 | AD24: 1.8927829 | AE24: 0.05838674 | AF24: 0.093230322 | AG24: 0.055419428 | AH24: 0.38674 | AI24: 0.6989487
C25: Petrobras | D25: clean | E25: BCOM | F25: 39904 | G25: 46204 | H25: 160 | I25: 0.17682894 | J25: 0.1501026 | K25: 2 | L25: 10.246239 | M25: 0.3534708 | N25: 2.5734786 | O25: 0.010068186 | P25: 0.53286383 | Q25: 0.21395165 | R25: 1.8124632 | S25: 0.069914662 | T25: 0.23385543 | U25: 0.091693319 | V25: 0.68961448 | W25: 0.49043666 | X25: 1.1671048 | Y25: 0.065988016 | Z25: 0.69320132 | AA25: 0.48818322 | AB25: 2.2908925 | AC25: 0.11808319 | AD25: 0.88842355 | AE25: 0.37431296
C26: Petrobras | D26: clean | E26: Brent | F26: 39904 | G26: 46204 | H26: 160 | I26: 0.20159467 | J26: 0.17567242 | K26: 2 | L26: 9.7215935 | M26: 0.33537179 | N26: 2.4631166 | O26: 0.013773513 | T26: 0.14625906 | U26: 0.057347305 | V26: 0.49518522 | W26: 0.62046939 | X26: 0.75491231 | Y26: 0.042682686 | Z26: 0.45624815 | AA26: 0.64821154 | AB26: 2.6526237 | AC26: 0.13672849 | AD26: 1.058261 | AE26: 0.28993645 | AF26: 0.2543642 | AG26: 0.25182586 | AH26: 2.238363 | AI26: 0.025197395
C27: Petrobras | D27: audit_clean | E27: BCOM | F27: 39904 | G27: 46204 | H27: 151 | I27: 0.1953185 | J27: 0.16757086 | K27: 2 | L27: 10.156794 | M27: 0.35779613 | N27: 2.4481231 | O27: 0.014360257 | P27: 0.48315935 | Q27: 0.19475026 | R27: 1.499703 | S27: 0.13369135 | T27: 0.19419586 | U27: 0.077606117 | V27: 0.56540756 | W27: 0.57179658 | X27: 1.7082009 | Y27: 0.09385131 | Z27: 1.1480623 | AA27: 0.25094284 | AB27: 3.2755886 | AC27: 0.16652843 | AD27: 1.2592044 | AE27: 0.20795652
C28: Petrobras | D28: audit_clean | E28: Brent | F28: 39904 | G28: 46204 | H28: 151 | I28: 0.21611916 | J28: 0.18908879 | K28: 2 | L28: 9.631873 | M28: 0.33930459 | N28: 2.3270767 | O28: 0.019961185 | T28: 0.1084597 | U28: 0.04334354 | V28: 0.36750816 | W28: 0.71324001 | X28: 1.2823705 | Y28: 0.070455504 | Z28: 0.85026179 | AA28: 0.39517956 | AB28: 3.5511082 | AC28: 0.18053563 | AD28: 1.3915744 | AE28: 0.16405131 | AF28: 0.22890369 | AG28: 0.22894427 | AH28: 1.8910425 | AI28: 0.058618669
C29: Petrobras | D29: since_2022_ex_seams | E29: BCOM | F29: 44562 | G29: 46204 | H29: 52 | I29: 0.2206106 | J29: 0.13589436 | K29: 2 | L29: 2.433598 | M29: 0.046660921 | N29: 0.41482441 | O29: 0.67827045 | P29: 0.81655308 | Q29: 0.40665733 | R29: 1.7862954 | S29: 0.074051442 | T29: 0.25654014 | U29: 0.09145114 | V29: 0.53466244 | W29: 0.5928833 | X29: 0.98780116 | Y29: 0.077268388 | Z29: 0.71040404 | AA29: 0.47745362 | AB29: 2.8651141 | AC29: 0.1734291 | AD29: 1.0143096 | AE29: 0.31043505
C30: Petrobras | D30: since_2022_ex_seams | E30: Brent | F30: 44562 | G30: 46204 | H30: 52 | I30: 0.35306681 | J30: 0.28274799 | K30: 2 | L30: 0.47059198 | M30: 0.009022959 | N30: 0.10152164 | O30: 0.91913638 | T30: 0.06306398 | U30: 0.022480977 | V30: 0.19614003 | W30: 0.84450056 | X30: 0.67561447 | Y30: 0.052848329 | Z30: 0.49521522 | AA30: 0.62044821 | AB30: 2.9679735 | AC30: 0.17965532 | AD30: 1.5097363 | AE30: 0.13111073 | AF30: 0.40124466 | AG30: 0.52391483 | AH30: 3.2251128 | AI30: 0.0012592306
C31: Ex-Petrobras dynamic | D31: primary | E31: BCOM | F31: 40269 | G31: 46204 | H31: 94 | I31: 0.14484587 | J31: 0.096257567 | K31: 17 | L31: 3.7735072 | M31: 0.080310784 | N31: 0.6343499 | O31: 0.5258525 | P31: 0.63168275 | Q31: 0.19022314 | R31: 1.3509801 | S31: 0.17670179 | T31: -0.86922402 | U31: -0.20424028 | V31: -1.6950635 | W31: 0.090063379 | X31: -1.734499 | Y31: -0.081694365 | Z31: -0.56985218 | AA31: 0.56877796 | AB31: 2.7291734 | AC31: 0.12776537 | AD31: 0.8506351 | AE31: 0.39497209
C32: Ex-Petrobras dynamic | D32: primary | E32: Brent | F32: 40269 | G32: 46204 | H32: 94 | I32: 0.2512921 | J32: 0.20875187 | K32: 17 | L32: 1.6901848 | M32: 0.035971859 | N32: 0.32000186 | O32: 0.74896692 | T32: -0.81168874 | U32: -0.1907213 | V32: -1.8847891 | W32: 0.059458321 | X32: -2.9419478 | Y32: -0.13856483 | Z32: -0.90127459 | AA32: 0.36744234 | AB32: 2.6052787 | AC32: 0.12196528 | AD32: 0.97389543 | AE32: 0.33010846 | AF32: 0.57774897 | AG32: 0.39728324 | AH32: 3.8486937 | AI32: 0.0001187494
C33: Ex-Petrobras dynamic | D33: clean | E33: BCOM | F33: 40269 | G33: 46204 | H33: 81 | I33: 0.13194015 | J33: 0.074069496 | K33: 17 | L33: -1.9753938 | M33: -0.024060217 | N33: -0.18476875 | O33: 0.85341042 | P33: 0.31809709 | Q33: 0.09307109 | R33: 0.6808067 | S33: 0.49599381 | T33: -1.2377097 | U33: -0.27084164 | V33: -1.9622342 | W33: 0.049735222 | X33: -2.2879019 | Y33: -0.092400868 | Z33: -0.71827857 | AA33: 0.47258554 | AB33: 2.8486695 | AC33: 0.10192868 | AD33: 0.70217916 | AE33: 0.48256744
C34: Ex-Petrobras dynamic | D34: clean | E34: Brent | F34: 40269 | G34: 46204 | H34: 81 | I34: 0.22471886 | J34: 0.17303345 | K34: 17 | L34: -1.7513119 | M34: -0.021330909 | N34: -0.15847447 | O34: 0.87408294 | T34: -0.95705017 | U34: -0.20942636 | V34: -1.7623727 | W34: 0.078006341 | X34: -3.4915053 | Y34: -0.14101047 | Z34: -0.9890851 | AA34: 0.32262151 | AB34: 2.1685069 | AC34: 0.077591679 | AD34: 0.59940132 | AE34: 0.5489053 | AF34: 0.52079478 | AG34: 0.34494267 | AH34: 3.6542279 | AI34: 0.00025795708
C35: Ex-Petrobras dynamic | D35: audit_clean | E35: BCOM | F35: 40269 | G35: 46204 | H35: 75 | I35: 0.1377638 | J35: 0.075282917 | K35: 17 | L35: 3.4506214 | M35: 0.044826182 | N35: 0.29734049 | O35: 0.76620657 | P35: 0.11436701 | Q35: 0.03543771 | R35: 0.19681428 | S35: 0.84397287 | T35: -1.2881377 | U35: -0.308895 | V35: -1.7668806 | W35: 0.077248234 | X35: -3.2200705 | Y35: -0.13972297 | Z35: -1.0371747 | AA35: 0.29965445 | AB35: 2.585633 | AC35: 0.10006995 | AD35: 0.65795053 | AE35: 0.51056992
C36: Ex-Petrobras dynamic | D36: audit_clean | E36: Brent | F36: 40269 | G36: 46204 | H36: 75 | I36: 0.21243659 | J36: 0.15536678 | K36: 17 | L36: 3.4539092 | M36: 0.044868893 | N36: 0.27462073 | O36: 0.78360764 | T36: -0.95153134 | U36: -0.2281769 | V36: -1.5795863 | W36: 0.11420165 | X36: -4.0770876 | Y36: -0.17691003 | Z36: -1.1903549 | AA36: 0.23390694 | AB36: 1.7652393 | AC36: 0.068318825 | AD36: 0.47344967 | AE36: 0.6358924 | AF36: 0.42413281 | AG36: 0.30044977 | AH36: 3.411547 | AI36: 0.00064595374
C37: Ex-Petrobras dynamic | D37: since_2022_ex_seams | E37: BCOM | F37: 44562 | G37: 46204 | H37: 52 | I37: 0.20766465 | J37: 0.12154124 | K37: 17 | L37: -7.0031604 | M37: -0.08649811 | N37: -0.57645993 | O37: 0.56430435 | P37: 0.79221047 | Q37: 0.25415159 | R37: 1.2133134 | S37: 0.22501001 | T37: -0.95906018 | U37: -0.22023571 | V37: -0.77694749 | W37: 0.43718975 | X37: -3.8465383 | Y37: -0.1938253 | Z37: -0.99245162 | AA37: 0.32097727 | AB37: 3.9869304 | AC37: 0.1554629 | AD37: 0.46175497 | AE37: 0.64425704
C38: Ex-Petrobras dynamic | D38: since_2022_ex_seams | E38: Brent | F38: 44562 | G38: 46204 | H38: 52 | I38: 0.29121447 | J38: 0.21417257 | K38: 17 | L38: -9.4095063 | M38: -0.1162196 | N38: -0.96970683 | O38: 0.33219264 | T38: -1.0402161 | U38: -0.23887211 | V38: -1.1328301 | W38: 0.25728559 | X38: -4.2460192 | Y38: -0.21395496 | Z38: -1.0990174 | AA38: 0.27176048 | AB38: 3.6322331 | AC38: 0.14163215 | AD38: 0.54358025 | AE38: 0.58673036 | AF38: 0.45669433 | AG38: 0.3841361 | AH38: 3.5764606 | AI38: 0.00034827772
C39: Ex-Petrobras core (PRIO + Brava) | D39: primary | E39: BCOM | F39: 44652 | G39: 46204 | H39: 52 | I39: 0.14839769 | J39: 0.055832224 | K39: 0 | L39: 17.234069 | M39: 0.18706345 | N39: 0.99881882 | O39: 0.31788247 | P39: 0.56782935 | Q39: 0.20558945 | R39: 1.1401325 | S39: 0.25423109 | T39: -0.36431568 | U39: -0.092480366 | V39: -0.37408473 | W39: 0.70834128 | X39: -4.5675555 | Y39: -0.2879081 | Z39: -1.3513358 | AA39: 0.17658788 | AB39: 2.7001706 | AC39: 0.13065802 | AD39: 0.38783549 | AE39: 0.69813778
C40: Ex-Petrobras core (PRIO + Brava) | D40: primary | E40: Brent | F40: 44652 | G40: 46204 | H40: 52 | I40: 0.21245257 | J40: 0.12684959 | K40: 0 | L40: 11.229591 | M40: 0.12188915 | N40: 0.67961879 | O40: 0.49674587 | T40: -0.4655096 | U40: -0.11816812 | V40: -0.61165764 | W40: 0.54076429 | X40: -4.834049 | Y40: -0.30470606 | Z40: -1.469826 | AA40: 0.14160888 | AB40: 2.5766143 | AC40: 0.12467928 | AD40: 0.44486053 | AE40: 0.65642055 | AF40: 0.33680983 | AG40: 0.33209691 | AH40: 2.2689995 | AI40: 0.023268359
C41: Ex-Petrobras core (PRIO + Brava) | D41: clean | E41: BCOM | F41: 44652 | G41: 46204 | H41: 52 | I41: 0.14839769 | J41: 0.055832224 | K41: 0 | L41: 17.234069 | M41: 0.18706345 | N41: 0.99881882 | O41: 0.31788247 | P41: 0.56782935 | Q41: 0.20558945 | R41: 1.1401325 | S41: 0.25423109 | T41: -0.36431568 | U41: -0.092480366 | V41: -0.37408473 | W41: 0.70834128 | X41: -4.5675555 | Y41: -0.2879081 | Z41: -1.3513358 | AA41: 0.17658788 | AB41: 2.7001706 | AC41: 0.13065802 | AD41: 0.38783549 | AE41: 0.69813778
C42: Ex-Petrobras core (PRIO + Brava) | D42: clean | E42: Brent | F42: 44652 | G42: 46204 | H42: 52 | I42: 0.21245257 | J42: 0.12684959 | K42: 0 | L42: 11.229591 | M42: 0.12188915 | N42: 0.67961879 | O42: 0.49674587 | T42: -0.4655096 | U42: -0.11816812 | V42: -0.61165764 | W42: 0.54076429 | X42: -4.834049 | Y42: -0.30470606 | Z42: -1.469826 | AA42: 0.14160888 | AB42: 2.5766143 | AC42: 0.12467928 | AD42: 0.44486053 | AE42: 0.65642055 | AF42: 0.33680983 | AG42: 0.33209691 | AH42: 2.2689995 | AI42: 0.023268359
C43: Ex-Petrobras core (PRIO + Brava) | D43: audit_clean | E43: BCOM | F43: 44652 | G43: 46204 | H43: 49 | I43: 0.14998771 | J43: 0.051149074 | K43: 0 | L43: 17.053272 | M43: 0.18154029 | N43: 0.96202201 | O43: 0.33603855 | P43: 0.61561551 | Q43: 0.21632378 | R43: 1.1913257 | S43: 0.23352577 | T43: -0.31289955 | U43: -0.078823203 | V43: -0.31093602 | W43: 0.75584926 | X43: -4.5761332 | Y43: -0.28625785 | Z43: -1.3336002 | AA43: 0.18233492 | AB43: 2.6458862 | AC43: 0.12670566 | AD43: 0.36777413 | AE43: 0.71304166
C44: Ex-Petrobras core (PRIO + Brava) | D44: audit_clean | E44: Brent | F44: 44652 | G44: 46204 | H44: 49 | I44: 0.21236443 | J44: 0.1207789 | K44: 0 | L44: 11.171558 | M44: 0.11892662 | N44: 0.65736876 | O44: 0.51094383 | T44: -0.45753872 | U44: -0.11525957 | V44: -0.58296155 | W44: 0.55991919 | X44: -4.8243365 | Y44: -0.3017841 | Z44: -1.4578933 | AA44: 0.14486995 | AB44: 2.5484525 | AC44: 0.12203977 | AD44: 0.42726596 | AE44: 0.66918562 | AF44: 0.33814793 | AG44: 0.33242976 | AH44: 2.2606848 | AI44: 0.023778783
C45: Ex-Petrobras core (PRIO + Brava) | D45: since_2022_ex_seams | E45: BCOM | F45: 44652 | G45: 46204 | H45: 49 | I45: 0.14998771 | J45: 0.051149074 | K45: 0 | L45: 17.053272 | M45: 0.18154029 | N45: 0.96202201 | O45: 0.33603855 | P45: 0.61561551 | Q45: 0.21632378 | R45: 1.1913257 | S45: 0.23352577 | T45: -0.31289955 | U45: -0.078823203 | V45: -0.31093602 | W45: 0.75584926 | X45: -4.5761332 | Y45: -0.28625785 | Z45: -1.3336002 | AA45: 0.18233492 | AB45: 2.6458862 | AC45: 0.12670566 | AD45: 0.36777413 | AE45: 0.71304166
C46: Ex-Petrobras core (PRIO + Brava) | D46: since_2022_ex_seams | E46: Brent | F46: 44652 | G46: 46204 | H46: 49 | I46: 0.21236443 | J46: 0.1207789 | K46: 0 | L46: 11.171558 | M46: 0.11892662 | N46: 0.65736876 | O46: 0.51094383 | T46: -0.45753872 | U46: -0.11525957 | V46: -0.58296155 | W46: 0.55991919 | X46: -4.8243365 | Y46: -0.3017841 | Z46: -1.4578933 | AA46: 0.14486995 | AB46: 2.5484525 | AC46: 0.12203977 | AD46: 0.42726596 | AE46: 0.66918562 | AF46: 0.33814793 | AG46: 0.33242976 | AH46: 2.2606848 | AI46: 0.023778783
C47: PRIO | D47: primary | E47: BCOM | F47: 44166 | G47: 46204 | H47: 68 | I47: 0.13830833 | J47: 0.068817064 | K47: 0 | L47: 10.085129 | M47: 0.2947746 | N47: 1.6488057 | O47: 0.099187447 | P47: 0.63984532 | Q47: 0.23653652 | R47: 1.2349062 | S47: 0.21686541 | T47: -0.012142179 | U47: -0.0034170335 | V47: -0.01879428 | W47: 0.98500522 | X47: -2.3301442 | Y47: -0.15354711 | Z47: -0.73287965 | AA47: 0.46363183 | AB47: 2.5879233 | AC47: 0.15381648 | AD47: 0.52297521 | AE47: 0.6009915
C48: PRIO | D48: primary | E48: Brent | F48: 44166 | G48: 46204 | H48: 68 | I48: 0.22296182 | J48: 0.16029745 | K48: 0 | L48: 7.8935118 | M48: 0.2307166 | N48: 1.4283272 | O48: 0.1531977 | T48: -0.061066653 | U48: -0.017185285 | V48: -0.12473298 | W48: 0.90073495 | X48: -2.7368253 | Y48: -0.18034575 | Z48: -0.84237009 | AA48: 0.39958083 | AB48: 2.155935 | AC48: 0.12814071 | AD48: 0.52249178 | AE48: 0.60132797 | AF48: 0.40945048 | AG48: 0.38910729 | AH48: 2.600992 | AI48: 0.0092954629
C49: PRIO | D49: clean | E49: BCOM | F49: 44562 | G49: 46204 | H49: 55 | I49: 0.12582441 | J49: 0.036622822 | K49: 0 | L49: 15.818938 | M49: 0.22096012 | N49: 1.8842583 | O49: 0.059530044 | P49: 0.45472751 | Q49: 0.16816813 | R49: 0.84389621 | S49: 0.39872741 | T49: -0.21747957 | U49: -0.05617573 | V49: -0.27978613 | W49: 0.77964159 | X49: -4.1326712 | Y49: -0.23520121 | Z49: -1.4204514 | AA49: 0.1554763 | AB49: 0.085032417 | AC49: 0.0037570652 | AD49: 0.013876961 | AE49: 0.98892814
C50: PRIO | D50: clean | E50: Brent | F50: 44562 | G50: 46204 | H50: 55 | I50: 0.20243591 | J50: 0.12105182 | K50: 0 | L50: 13.572094 | M50: 0.18957603 | N50: 1.6204182 | O50: 0.10514247 | T50: -0.11600769 | U50: -0.029965191 | V50: -0.21905733 | W50: 0.82660539 | X50: -4.5393846 | Y50: -0.25834834 | Z50: -1.4965125 | AA50: 0.13452014 | AB50: -0.65352561 | AC50: -0.028875321 | AD50: -0.13290028 | AE50: 0.89427224 | AF50: 0.35944724 | AG50: 0.34017157 | AH50: 2.1271555 | AI50: 0.033407168
C51: PRIO | D51: audit_clean | E51: BCOM | F51: 44562 | G51: 46204 | H51: 52 | I51: 0.12784471 | J51: 0.033045225 | K51: 0 | L51: 15.682325 | M51: 0.21746322 | N51: 1.838637 | O51: 0.065968592 | P51: 0.54275544 | Q51: 0.19548762 | R51: 0.97332415 | S51: 0.33039222 | T51: -0.11136836 | U51: -0.028712203 | V51: -0.14342383 | W51: 0.88595547 | X51: -4.0768949 | Y51: -0.230639 | Z51: -1.3279153 | AA51: 0.18420609 | AB51: -0.1232386 | AC51: -0.0053950776 | AD51: -0.01963374 | AE51: 0.98433555
C52: PRIO | D52: audit_clean | E52: Brent | F52: 44562 | G52: 46204 | H52: 52 | I52: 0.20374677 | J52: 0.11719751 | K52: 0 | L52: 13.622169 | M52: 0.1888955 | N52: 1.6011064 | O52: 0.10935336 | T52: -0.07959501 | U52: -0.020520623 | V52: -0.15016387 | W52: 0.88063533 | X52: -4.4297996 | Y52: -0.2506036 | Z52: -1.3965072 | AA52: 0.16256181 | AB52: -0.73893546 | AC52: -0.032348746 | AD52: -0.14767934 | AE52: 0.88259584 | AF52: 0.36816648 | AG52: 0.34766948 | AH52: 2.1606321 | AI52: 0.030723767
C53: PRIO | D53: since_2022_ex_seams | E53: BCOM | F53: 44562 | G53: 46204 | H53: 52 | I53: 0.12784471 | J53: 0.033045225 | K53: 0 | L53: 15.682325 | M53: 0.21746322 | N53: 1.838637 | O53: 0.065968592 | P53: 0.54275544 | Q53: 0.19548762 | R53: 0.97332415 | S53: 0.33039222 | T53: -0.11136836 | U53: -0.028712203 | V53: -0.14342383 | W53: 0.88595547 | X53: -4.0768949 | Y53: -0.230639 | Z53: -1.3279153 | AA53: 0.18420609 | AB53: -0.1232386 | AC53: -0.0053950776 | AD53: -0.01963374 | AE53: 0.98433555
C54: PRIO | D54: since_2022_ex_seams | E54: Brent | F54: 44562 | G54: 46204 | H54: 52 | I54: 0.20374677 | J54: 0.11719751 | K54: 0 | L54: 13.622169 | M54: 0.1888955 | N54: 1.6011064 | O54: 0.10935336 | T54: -0.07959501 | U54: -0.020520623 | V54: -0.15016387 | W54: 0.88063533 | X54: -4.4297996 | Y54: -0.2506036 | Z54: -1.3965072 | AA54: 0.16256181 | AB54: -0.73893546 | AC54: -0.032348746 | AD54: -0.14767934 | AE54: 0.88259584 | AF54: 0.36816648 | AG54: 0.34766948 | AH54: 2.1606321 | AI54: 0.030723767
C55: Brava Energia | D55: primary | E55: BCOM | F55: 44652 | G55: 46204 | H55: 52 | I55: 0.14011961 | J55: 0.046654346 | K55: 0 | L55: 7.3957495 | M55: 0.068475087 | N55: 0.30495965 | O55: 0.76039688 | P55: 0.4784599 | Q55: 0.14776712 | R55: 0.74859283 | S55: 0.45410265 | T55: -0.13726396 | U55: -0.029721962 | V55: -0.13698302 | W55: 0.89104422 | X55: -4.3921067 | Y55: -0.23615232 | Z55: -1.006932 | AA55: 0.31396744 | AB55: 8.2153695 | AC55: 0.3390949 | AD55: 1.0625576 | AE55: 0.28798261
C56: Brava Energia | D56: primary | E56: Brent | F56: 44652 | G56: 46204 | H56: 52 | I56: 0.14137189 | J56: 0.048042748 | K56: 0 | L56: 4.8355327 | M56: 0.044770786 | N56: 0.19786013 | O56: 0.8431545 | T56: -0.36880458 | U56: -0.079857787 | V56: -0.48460234 | W56: 0.62795845 | X56: -4.4281288 | Y56: -0.23808914 | Z56: -1.0370931 | AA56: 0.29969246 | AB56: 8.8126676 | AC56: 0.36374878 | AD56: 1.3366293 | AE56: 0.18134367 | AF56: 0.1629821 | AG56: 0.13707848 | AH56: 0.8687203 | AI56: 0.38500013
C57: Brava Energia | D57: clean | E57: BCOM | F57: 44652 | G57: 46204 | H57: 52 | I57: 0.14011961 | J57: 0.046654346 | K57: 0 | L57: 7.3957495 | M57: 0.068475087 | N57: 0.30495965 | O57: 0.76039688 | P57: 0.4784599 | Q57: 0.14776712 | R57: 0.74859283 | S57: 0.45410265 | T57: -0.13726396 | U57: -0.029721962 | V57: -0.13698302 | W57: 0.89104422 | X57: -4.3921067 | Y57: -0.23615232 | Z57: -1.006932 | AA57: 0.31396744 | AB57: 8.2153695 | AC57: 0.3390949 | AD57: 1.0625576 | AE57: 0.28798261
C58: Brava Energia | D58: clean | E58: Brent | F58: 44652 | G58: 46204 | H58: 52 | I58: 0.14137189 | J58: 0.048042748 | K58: 0 | L58: 4.8355327 | M58: 0.044770786 | N58: 0.19786013 | O58: 0.8431545 | T58: -0.36880458 | U58: -0.079857787 | V58: -0.48460234 | W58: 0.62795845 | X58: -4.4281288 | Y58: -0.23808914 | Z58: -1.0370931 | AA58: 0.29969246 | AB58: 8.8126676 | AC58: 0.36374878 | AD58: 1.3366293 | AE58: 0.18134367 | AF58: 0.1629821 | AG58: 0.13707848 | AH58: 0.8687203 | AI58: 0.38500013
C59: Brava Energia | D59: audit_clean | E59: BCOM | F59: 44652 | G59: 46204 | H59: 49 | I59: 0.13905644 | J59: 0.038946725 | K59: 0 | L59: 6.5222173 | M59: 0.059392892 | N59: 0.26303283 | O59: 0.79252527 | P59: 0.44732626 | Q59: 0.13445996 | R59: 0.65120113 | S59: 0.51491666 | T59: -0.2151695 | U59: -0.046366438 | V59: -0.2026007 | W59: 0.83944715 | X59: -4.5413073 | Y59: -0.24300407 | Z59: -1.0893208 | AA59: 0.27601247 | AB59: 8.5292911 | AC59: 0.34939096 | AD59: 1.0725879 | AE59: 0.28345608
C60: Brava Energia | D60: audit_clean | E60: Brent | F60: 44652 | G60: 46204 | H60: 49 | I60: 0.14179233 | J60: 0.042000739 | K60: 0 | L60: 4.0828985 | M60: 0.037179864 | N60: 0.16402946 | O60: 0.86970795 | T60: -0.4340658 | U60: -0.093535957 | V60: -0.5592036 | W60: 0.57602278 | X60: -4.5918541 | Y60: -0.24570881 | Z60: -1.1363553 | AA60: 0.2558079 | AB60: 8.9951659 | AC60: 0.3684749 | AD60: 1.3190358 | AE60: 0.18715713 | AF60: 0.15521893 | AG60: 0.13053043 | AH60: 0.83678625 | AI60: 0.40271272
C61: Brava Energia | D61: since_2022_ex_seams | E61: BCOM | F61: 44652 | G61: 46204 | H61: 49 | I61: 0.13905644 | J61: 0.038946725 | K61: 0 | L61: 6.5222173 | M61: 0.059392892 | N61: 0.26303283 | O61: 0.79252527 | P61: 0.44732626 | Q61: 0.13445996 | R61: 0.65120113 | S61: 0.51491666 | T61: -0.2151695 | U61: -0.046366438 | V61: -0.2026007 | W61: 0.83944715 | X61: -4.5413073 | Y61: -0.24300407 | Z61: -1.0893208 | AA61: 0.27601247 | AB61: 8.5292911 | AC61: 0.34939096 | AD61: 1.0725879 | AE61: 0.28345608
C62: Brava Energia | D62: since_2022_ex_seams | E62: Brent | F62: 44652 | G62: 46204 | H62: 49 | I62: 0.14179233 | J62: 0.042000739 | K62: 0 | L62: 4.0828985 | M62: 0.037179864 | N62: 0.16402946 | O62: 0.86970795 | T62: -0.4340658 | U62: -0.093535957 | V62: -0.5592036 | W62: 0.57602278 | X62: -4.5918541 | Y62: -0.24570881 | Z62: -1.1363553 | AA62: 0.2558079 | AB62: 8.9951659 | AC62: 0.3684749 | AD62: 1.3190358 | AE62: 0.18715713 | AF62: 0.15521893 | AG62: 0.13053043 | AH62: 0.83678625 | AI62: 0.40271272
C63: PetroReconcavo | D63: primary | E63: BCOM | F63: 45261 | G63: 46204 | H63: 32 | I63: 0.22809526 | J63: 0.079652042 | K63: 0 | L63: 17.082197 | M63: 0.11890809 | N63: 0.83585465 | O63: 0.40323668 | P63: 0.21564128 | Q63: 0.064132265 | R63: 0.25988231 | S63: 0.79495456 | T63: -1.8454988 | U63: -0.40248154 | V63: -1.2977704 | W63: 0.19436626 | X63: 5.455026 | Y63: 0.12135523 | Z63: 0.41129524 | AA63: 0.68085606 | AB63: 11.884201 | AC63: 0.53044098 | AD63: 1.5399627 | AE63: 0.12356946
C64: PetroReconcavo | D64: primary | E64: Brent | F64: 45261 | G64: 46204 | H64: 32 | I64: 0.25577205 | J64: 0.11265129 | K64: 0 | L64: 12.759423 | M64: 0.088817537 | N64: 0.67954556 | O64: 0.49679225 | T64: -1.4956528 | U64: -0.32618424 | V64: -1.31256 | W64: 0.18933125 | X64: 9.1600605 | Y64: 0.20377928 | Z64: 0.74227629 | AA64: 0.45791996 | AB64: 9.694935 | AC64: 0.43272501 | AD64: 1.6419795 | AE64: 0.10059425 | AF64: 0.23421381 | AG64: 0.2276647 | AH64: 1.463211 | AI64: 0.14340965
C65: PetroReconcavo | D65: clean | E65: BCOM | F65: 45261 | G65: 46204 | H65: 32 | I65: 0.22809526 | J65: 0.079652042 | K65: 0 | L65: 17.082197 | M65: 0.11890809 | N65: 0.83585465 | O65: 0.40323668 | P65: 0.21564128 | Q65: 0.064132265 | R65: 0.25988231 | S65: 0.79495456 | T65: -1.8454988 | U65: -0.40248154 | V65: -1.2977704 | W65: 0.19436626 | X65: 5.455026 | Y65: 0.12135523 | Z65: 0.41129524 | AA65: 0.68085606 | AB65: 11.884201 | AC65: 0.53044098 | AD65: 1.5399627 | AE65: 0.12356946
C66: PetroReconcavo | D66: clean | E66: Brent | F66: 45261 | G66: 46204 | H66: 32 | I66: 0.25577205 | J66: 0.11265129 | K66: 0 | L66: 12.759423 | M66: 0.088817537 | N66: 0.67954556 | O66: 0.49679225 | T66: -1.4956528 | U66: -0.32618424 | V66: -1.31256 | W66: 0.18933125 | X66: 9.1600605 | Y66: 0.20377928 | Z66: 0.74227629 | AA66: 0.45791996 | AB66: 9.694935 | AC66: 0.43272501 | AD66: 1.6419795 | AE66: 0.10059425 | AF66: 0.23421381 | AG66: 0.2276647 | AH66: 1.463211 | AI66: 0.14340965
C67: PetroReconcavo | D67: audit_clean | E67: BCOM | F67: 45261 | G67: 46204 | H67: 32 | I67: 0.22809526 | J67: 0.079652042 | K67: 0 | L67: 17.082197 | M67: 0.11890809 | N67: 0.83585465 | O67: 0.40323668 | P67: 0.21564128 | Q67: 0.064132265 | R67: 0.25988231 | S67: 0.79495456 | T67: -1.8454988 | U67: -0.40248154 | V67: -1.2977704 | W67: 0.19436626 | X67: 5.455026 | Y67: 0.12135523 | Z67: 0.41129524 | AA67: 0.68085606 | AB67: 11.884201 | AC67: 0.53044098 | AD67: 1.5399627 | AE67: 0.12356946
C68: PetroReconcavo | D68: audit_clean | E68: Brent | F68: 45261 | G68: 46204 | H68: 32 | I68: 0.25577205 | J68: 0.11265129 | K68: 0 | L68: 12.759423 | M68: 0.088817537 | N68: 0.67954556 | O68: 0.49679225 | T68: -1.4956528 | U68: -0.32618424 | V68: -1.31256 | W68: 0.18933125 | X68: 9.1600605 | Y68: 0.20377928 | Z68: 0.74227629 | AA68: 0.45791996 | AB68: 9.694935 | AC68: 0.43272501 | AD68: 1.6419795 | AE68: 0.10059425 | AF68: 0.23421381 | AG68: 0.2276647 | AH68: 1.463211 | AI68: 0.14340965
C69: PetroReconcavo | D69: since_2022_ex_seams | E69: BCOM | F69: 45261 | G69: 46204 | H69: 32 | I69: 0.22809526 | J69: 0.079652042 | K69: 0 | L69: 17.082197 | M69: 0.11890809 | N69: 0.83585465 | O69: 0.40323668 | P69: 0.21564128 | Q69: 0.064132265 | R69: 0.25988231 | S69: 0.79495456 | T69: -1.8454988 | U69: -0.40248154 | V69: -1.2977704 | W69: 0.19436626 | X69: 5.455026 | Y69: 0.12135523 | Z69: 0.41129524 | AA69: 0.68085606 | AB69: 11.884201 | AC69: 0.53044098 | AD69: 1.5399627 | AE69: 0.12356946
C70: PetroReconcavo | D70: since_2022_ex_seams | E70: Brent | F70: 45261 | G70: 46204 | H70: 32 | I70: 0.25577205 | J70: 0.11265129 | K70: 0 | L70: 12.759423 | M70: 0.088817537 | N70: 0.67954556 | O70: 0.49679225 | T70: -1.4956528 | U70: -0.32618424 | V70: -1.31256 | W70: 0.18933125 | X70: 9.1600605 | Y70: 0.20377928 | Z70: 0.74227629 | AA70: 0.45791996 | AB70: 9.694935 | AC70: 0.43272501 | AD70: 1.6419795 | AE70: 0.10059425 | AF70: 0.23421381 | AG70: 0.2276647 | AH70: 1.463211 | AI70: 0.14340965
C71: Oleo e Gas Participacoes | D71: primary | E71: BCOM | F71: 40269 | G71: 41030 | H71: 26 | I71: 0.17871968 | J71: -0.0266004 | K71: 17 | L71: 20.266512 | M71: 0.2059156 | N71: 0.91183839 | O71: 0.3618538 | P71: -0.076363867 | Q71: -0.018540623 | R71: -0.073710594 | S71: 0.94124067 | T71: -2.6374271 | U71: -0.53638773 | V71: -2.0694765 | W71: 0.038501397 | X71: 8.7125502 | Y71: 0.1866187 | Z71: 1.0565133 | AA71: 0.29073378 | AB71: -8.8739854 | AC71: -0.26380494 | AD71: -0.78977427 | AE71: 0.42965961
C72: Oleo e Gas Participacoes | D72: primary | E72: Brent | F72: 40269 | G72: 41030 | H72: 26 | I72: 0.33126303 | J72: 0.16407879 | K72: 17 | L72: 40.953487 | M72: 0.41610326 | N72: 1.4901841 | O72: 0.13617584 | T72: -1.5020142 | U72: -0.3054727 | V72: -1.3815002 | W72: 0.16712521 | X72: 9.9102756 | Y72: 0.21227341 | Z72: 1.4094988 | AA72: 0.15868773 | AB72: -13.744082 | AC72: -0.40858268 | AD72: -1.1546003 | AE72: 0.24825415 | AF72: 1.578324 | AG72: 0.54702912 | AH72: 1.6762496 | AI72: 0.093689319
C73: Oleo e Gas Participacoes | D73: clean | E73: BCOM | F73: 40269 | G73: 41030 | H73: 26 | I73: 0.17871968 | J73: -0.0266004 | K73: 17 | L73: 20.266512 | M73: 0.2059156 | N73: 0.91183839 | O73: 0.3618538 | P73: -0.076363867 | Q73: -0.018540623 | R73: -0.073710594 | S73: 0.94124067 | T73: -2.6374271 | U73: -0.53638773 | V73: -2.0694765 | W73: 0.038501397 | X73: 8.7125502 | Y73: 0.1866187 | Z73: 1.0565133 | AA73: 0.29073378 | AB73: -8.8739854 | AC73: -0.26380494 | AD73: -0.78977427 | AE73: 0.42965961
C74: Oleo e Gas Participacoes | D74: clean | E74: Brent | F74: 40269 | G74: 41030 | H74: 26 | I74: 0.33126303 | J74: 0.16407879 | K74: 17 | L74: 40.953487 | M74: 0.41610326 | N74: 1.4901841 | O74: 0.13617584 | T74: -1.5020142 | U74: -0.3054727 | V74: -1.3815002 | W74: 0.16712521 | X74: 9.9102756 | Y74: 0.21227341 | Z74: 1.4094988 | AA74: 0.15868773 | AB74: -13.744082 | AC74: -0.40858268 | AD74: -1.1546003 | AE74: 0.24825415 | AF74: 1.578324 | AG74: 0.54702912 | AH74: 1.6762496 | AI74: 0.093689319

Sheet Seams
C2: Diagnóstico das emendas das séries
C3: Revisions de três meses que atravessam as mudanças entre arquivos-fonte.
C6: seam_start | D6: revision_month | E6: target | F6: revision_3m_log_pct
C7: 40544 | D7: 40544 | E7: IBOV | F7: 12.819552
C8: 40544 | D8: 40544 | E8: Communication Services | F8: 12.054874
C9: 40544 | D9: 40544 | E9: Consumer Discretionary | F9: 8.7488047
C10: 40544 | D10: 40544 | E10: Consumer Staples | F10: -1.769531
C11: 40544 | D11: 40544 | E11: Energy | F11: 5.9291748
C12: 40544 | D12: 40544 | E12: Financials | F12: 7.3308074
C13: 40544 | D13: 40544 | E13: Health Care
C14: 40544 | D14: 40544 | E14: Industrials | F14: 18.982669
C15: 40544 | D15: 40544 | E15: Information Technology
C16: 40544 | D16: 40544 | E16: Materials | F16: 8.7381702
C17: 40544 | D17: 40544 | E17: Real Estate
C18: 40544 | D18: 40544 | E18: Utilities | F18: -6.1527389
C19: 40544 | D19: 40575 | E19: IBOV | F19: 11.109557
C20: 40544 | D20: 40575 | E20: Communication Services | F20: 8.3063238
C21: 40544 | D21: 40575 | E21: Consumer Discretionary | F21: 6.8516313
C22: 40544 | D22: 40575 | E22: Consumer Staples | F22: -4.7002908
C23: 40544 | D23: 40575 | E23: Energy | F23: 1.3153922
C24: 40544 | D24: 40575 | E24: Financials | F24: 7.7389093
C25: 40544 | D25: 40575 | E25: Health Care
C26: 40544 | D26: 40575 | E26: Industrials | F26: 14.363271
C27: 40544 | D27: 40575 | E27: Information Technology
C28: 40544 | D28: 40575 | E28: Materials | F28: 5.525231
C29: 40544 | D29: 40575 | E29: Real Estate
C30: 40544 | D30: 40575 | E30: Utilities | F30: 1.1810283
C31: 40544 | D31: 40603 | E31: IBOV | F31: 4.7677691
C32: 40544 | D32: 40603 | E32: Communication Services | F32: 9.015118
C33: 40544 | D33: 40603 | E33: Consumer Discretionary | F33: 2.3945869
C34: 40544 | D34: 40603 | E34: Consumer Staples | F34: -5.8925242
C35: 40544 | D35: 40603 | E35: Energy | F35: -3.2929993
C36: 40544 | D36: 40603 | E36: Financials | F36: 6.3833764
C37: 40544 | D37: 40603 | E37: Health Care
C38: 40544 | D38: 40603 | E38: Industrials | F38: 2.6363086
C39: 40544 | D39: 40603 | E39: Information Technology
C40: 40544 | D40: 40603 | E40: Materials | F40: 2.5143455
C41: 40544 | D41: 40603 | E41: Real Estate
C42: 40544 | D42: 40603 | E42: Utilities | F42: 5.7412671
C43: 41640 | D43: 41640 | E43: IBOV | F43: 19.269185
C44: 41640 | D44: 41640 | E44: Communication Services | F44: 24.014277
C45: 41640 | D45: 41640 | E45: Consumer Discretionary | F45: 18.901307
C46: 41640 | D46: 41640 | E46: Consumer Staples | F46: 35.29451
C47: 41640 | D47: 41640 | E47: Energy | F47: 22.185638
C48: 41640 | D48: 41640 | E48: Financials | F48: 6.6419353
C49: 41640 | D49: 41640 | E49: Health Care | F49: -11.543306
C50: 41640 | D50: 41640 | E50: Industrials | F50: 16.268844
C51: 41640 | D51: 41640 | E51: Information Technology
C52: 41640 | D52: 41640 | E52: Materials | F52: 28.180463
C53: 41640 | D53: 41640 | E53: Real Estate | F53: -2.2620353
C54: 41640 | D54: 41640 | E54: Utilities | F54: 7.9839144
C55: 41640 | D55: 41671 | E55: IBOV | F55: 12.499467
C56: 41640 | D56: 41671 | E56: Communication Services | F56: 32.035034
C57: 41640 | D57: 41671 | E57: Consumer Discretionary | F57: 21.708955
C58: 41640 | D58: 41671 | E58: Consumer Staples | F58: 33.48998
C59: 41640 | D59: 41671 | E59: Energy | F59: -1.2026028
C60: 41640 | D60: 41671 | E60: Financials | F60: 9.453279
C61: 41640 | D61: 41671 | E61: Health Care | F61: -5.5994682
C62: 41640 | D62: 41671 | E62: Industrials | F62: 10.083582
C63: 41640 | D63: 41671 | E63: Information Technology
C64: 41640 | D64: 41671 | E64: Materials | F64: 22.944954
C65: 41640 | D65: 41671 | E65: Real Estate | F65: -6.6928035
C66: 41640 | D66: 41671 | E66: Utilities | F66: 11.196339
C67: 41640 | D67: 41699 | E67: IBOV | F67: 17.482205
C68: 41640 | D68: 41699 | E68: Communication Services | F68: 35.663362
C69: 41640 | D69: 41699 | E69: Consumer Discretionary | F69: 29.429157
C70: 41640 | D70: 41699 | E70: Consumer Staples | F70: 31.293762
C71: 41640 | D71: 41699 | E71: Energy | F71: -0.5937784
C72: 41640 | D72: 41699 | E72: Financials | F72: 9.5909894
C73: 41640 | D73: 41699 | E73: Health Care | F73: 5.0263253
C74: 41640 | D74: 41699 | E74: Industrials | F74: 9.6162596
C75: 41640 | D75: 41699 | E75: Information Technology
C76: 41640 | D76: 41699 | E76: Materials | F76: 28.404572
C77: 41640 | D77: 41699 | E77: Real Estate | F77: -8.648559
C78: 41640 | D78: 41699 | E78: Utilities | F78: 5.5528102
C79: 42736 | D79: 42736 | E79: IBOV | F79: 14.444666
C80: 42736 | D80: 42736 | E80: Communication Services | F80: 6.7043665
C81: 42736 | D81: 42736 | E81: Consumer Discretionary | F81: -1.597045
C82: 42736 | D82: 42736 | E82: Consumer Staples | F82: -1.3711247
C83: 42736 | D83: 42736 | E83: Energy | F83: 21.71893
C84: 42736 | D84: 42736 | E84: Financials | F84: 7.6221217
C85: 42736 | D85: 42736 | E85: Health Care | F85: 6.6554073
C86: 42736 | D86: 42736 | E86: Industrials | F86: 1.0804387
C87: 42736 | D87: 42736 | E87: Information Technology
C88: 42736 | D88: 42736 | E88: Materials | F88: 82.715626
C89: 42736 | D89: 42736 | E89: Real Estate | F89: 4.5545373
C90: 42736 | D90: 42736 | E90: Utilities | F90: 0.34556464
C91: 42736 | D91: 42767 | E91: IBOV | F91: 16.270811
C92: 42736 | D92: 42767 | E92: Communication Services | F92: 2.622181
C93: 42736 | D93: 42767 | E93: Consumer Discretionary | F93: -3.7234072
C94: 42736 | D94: 42767 | E94: Consumer Staples | F94: 6.3457729
C95: 42736 | D95: 42767 | E95: Energy | F95: 27.334757
C96: 42736 | D96: 42767 | E96: Financials | F96: 4.4987035
C97: 42736 | D97: 42767 | E97: Health Care | F97: 4.835011
C98: 42736 | D98: 42767 | E98: Industrials | F98: 9.8136067
C99: 42736 | D99: 42767 | E99: Information Technology
C100: 42736 | D100: 42767 | E100: Materials | F100: 79.65361
C101: 42736 | D101: 42767 | E101: Real Estate | F101: 9.2767534
C102: 42736 | D102: 42767 | E102: Utilities | F102: 8.5558205
C103: 42736 | D103: 42795 | E103: IBOV | F103: 14.039621
...

Sheet Fontes
C2: Fontes e rastreabilidade
C3: Arquivos, URLs, cobertura, classificação, métrica e hash SHA-256 quando disponível.
C6: source_file | D6: source_url | E6: start_date | F6: end_date | G6: months | H6: series | I6: currency | J6: benchmark | K6: classification | L6: metric | M6: sha256
C7: grid_20qvjmd3.xlsx | D7: https://researchxp1.s3.sa-east-1.amazonaws.com/grid_20qvjmd3.xlsx | E7: 39478 | F7: 40543 | G7: 36 | H7: 11 | I7: BRL | J7: IBOV | K7: GICS Sector | L7: BEst Net Inc | M7: c1b37e2a5da044fd089eb45dd5ca0f40e63781523e2a09c67b670f57d1128845
C8: grid_u4lflnxf.xlsx | D8: https://researchxp1.s3.sa-east-1.amazonaws.com/grid_u4lflnxf.xlsx | E8: 40574 | F8: 41639 | G8: 36 | H8: 12 | I8: BRL | J8: IBOV | K8: GICS Sector | L8: BEst Net Inc | M8: 7ed34657db550a54b2b6e35952e8cea3803d157d3bcd4656f10065798aef8138
C9: grid_vtqvtw11.xlsx | D9: https://researchxp1.s3.sa-east-1.amazonaws.com/grid_vtqvtw11.xlsx | E9: 41670 | F9: 42734 | G9: 36 | H9: 12 | I9: BRL | J9: IBOV | K9: GICS Sector | L9: BEst Net Inc | M9: b07e8c335aeed7f4131cd16da0014f34d9b1187c34f0bb65e4537f57e7dd6ee2
C10: grid_ovzcidwu.xlsx | D10: https://researchxp1.s3.sa-east-1.amazonaws.com/grid_ovzcidwu.xlsx | E10: 42766 | F10: 43830 | G10: 36 | H10: 12 | I10: BRL | J10: IBOV | K10: GICS Sector | L10: BEst Net Inc | M10: 0b77cacde0be9686941e9d2ca6d0d0d902d0be0528a11595d8f1017fb9a866c8
C11: grid_1mk3z2wn.xlsx | D11: https://researchxp1.s3.sa-east-1.amazonaws.com/grid_1mk3z2wn.xlsx | E11: 43861 | F11: 44925 | G11: 36 | H11: 13 | I11: BRL | J11: IBOV | K11: GICS Sector | L11: BEst Net Inc | M11: 477dd2d9a05cea515a92419c4a1345bd134024811585d80033286a331ef76d79
C12: grid_22fp35k1.xlsx | D12: https://researchxp1.s3.sa-east-1.amazonaws.com/grid_22fp35k1.xlsx | E12: 44957 | F12: 46268 | G12: 45 | H12: 12 | I12: BRL | J12: IBOV | K12: GICS Sector | L12: BEst Net Inc | M12: 7a8101c3d80a549a50ff17c5535e281b1deb2b6ee9b3337f72e3956480ea71a8
C13: Ibovespa Best EPS.xlsx | D13: Bloomberg export; local source | E13: 38748 | F13: 46265 | H13: BEst EPS | I13: BRL | J13: IBOV | K13: Index | L13: BEst EPS
C14: BCB Focus PIB Total / IPCA | D14: https://olinda.bcb.gov.br/olinda/servico/Expectativas/versao/v1/aplicacao#!/recursos | E14: 39815 | F14: 46255 | H14: Focus annual medians | K14: Macro | L14: PIB and IPCA expectations
C15: BCB SGS 13522 | D15: https://api.bcb.gov.br/dados/serie/bcdata.sgs.13522/dados?formato=json | E15: 36526 | F15: 46204 | H15: IPCA accumulated 12 months | K15: Macro | L15: percent
C16: BCB SGS 1 | D16: https://api.bcb.gov.br/dados/serie/bcdata.sgs.1/dados?formato=json | E16: 38718 | F16: 46265 | H16: USD/BRL | I16: BRL per USD | K16: Macro | L16: daily exchange rate
C17: BCOM.xlsx | D17: Bloomberg export; local source | E17: 38748 | F17: 46265 | H17: Bloomberg Commodity Index | I17: USD | J17: BCOM | K17: Macro | L17: last price
C18: swap_pre_di_360.csv | D18: https://researchxp1.s3.sa-east-1.amazonaws.com/bmf-swap.parquet | E18: 34608 | F18: 46265 | H18: Pre-DI swap 360 days | K18: Macro | L18: annual percent rate
C19: EIA RBRTE daily | D19: https://www.eia.gov/dnav/pet/hist/leafhandler.ashx?f=d&n=pet&s=rbrte | E19: 31917 | F19: 46266 | H19: Europe Brent Spot Price FOB | I19: USD per barrel | J19: Brent | K19: Macro | L19: daily spot price

Sheet Dicionario
C2: Dicionário, metodologia e manutenção
C3: Definições das variáveis, estrutura do workbook, amostras e histórico de versões.
C6: Metodologia
C7: Item | D7: Definição | E7: Unidade | F7: Observação
C8: Earnings 12m fwd | D8: Estimativa agregada de lucro líquido ou EPS para os próximos 12 meses | E8: BRL / índice | F8: A métrica depende da série
C9: Revision 3m | D9: 100 × log(Earnings_t / Earnings_t-3) | E9: % log | F9: Variação acumulada em três meses
C10: Δ macro 3m | D10: Valor no mês t menos valor no mês t-3 | E10: p.p. ou % | F10: Conforme a variável
C11: Regressão | D11: OLS contemporâneo com erros HAC/Newey-West | E11: - | F11: Associação, não causalidade
C12: Beta padronizado | D12: Mudança no target, em desvios-padrão, para 1 desvio-padrão do regressor | E12: desvios-padrão | F12: Comparável entre variáveis e setores
C13: q BH | D13: p-valor ajustado por Benjamini-Hochberg entre setores | E13: probabilidade | F13: Controle de falsos descobrimentos
C16: Amostras
C17: Nome | D17: Definição | E17: Uso | F17: Limitação
C18: full | D18: Todas as observações disponíveis | E18: Referência ampla | F18: Inclui episódios extremos
C19: ex_2013_14 | D19: Exclui 2013 e 2014 | E19: Amostra principal | F19: Escolha motivada por instabilidade histórica
C20: ex_2020_21 | D20: Exclui 2020 e 2021 | E20: Robustez à pandemia | F20: Mantém 2013-2014
C21: clean | D21: Exclui 2013-2014 e 2020-2021 | E21: Robustez conjunta | F21: Menor amostra
C22: ex_seams | D22: Exclui revisions que atravessam emendas | E22: Auditoria das séries setoriais | F22: Mantém choques macro
C23: since_2022 | D23: Janeiro de 2022 em diante | E23: Regime recente | F23: Poucas observações
C26: Variáveis principais
C27: Variável | D27: Descrição | E27: Unidade | F27: Transformação | G27: Origem
C28: eps | D28: BEst EPS 12 meses forward do IBOV | E28: BRL por ação | F28: nível | G28: Bloomberg
C29: y_rev3 | D29: Revision do BEst EPS do IBOV | E29: % log | F29: 100 × log(t/t-3) | G29: Calculado
C30: IBOV / setores | D30: BEst Net Income agregado | E30: BRL | F30: nível | G30: Grades XP/Bloomberg
C31: focus_pib | D31: Mediana Focus para crescimento do PIB anual | E31: % | F31: nível | G31: Banco Central do Brasil
C32: d_focus_pib3 | D32: Mudança da expectativa de PIB | E32: p.p. | F32: t menos t-3 | G32: Calculado
C33: focus_ipca | D33: Mediana Focus para IPCA anual | E33: % | F33: nível | G33: Banco Central do Brasil
C34: d_focus_ipca3 | D34: Mudança da expectativa de IPCA | E34: p.p. | F34: t menos t-3 | G34: Calculado
C35: ipca12_available | D35: IPCA acumulado em 12 meses disponível na data | E35: % | F35: nível | G35: BCB SGS 13522
C36: d_ipca12_3_available | D36: Mudança do IPCA 12 meses realizado | E36: p.p. | F36: t menos t-3 | G36: Calculado
C37: ipca3_flow_available | D37: Inflação acumulada no fluxo de três meses | E37: % | F37: fluxo 3m | G37: Calculado
C38: bcom_usd | D38: Bloomberg Commodity Index | E38: índice USD | F38: nível | G38: Bloomberg
... C50: r2 | D50: Coeficiente de determinação | E50: proporção | F50: OLS | G50: Calculado
C55: Mapa das abas
C56: Aba | D56: Conteúdo | E56: Tipo | F56: Uso
C57: Resumo | D57: Conclusões e coeficientes principais | E57: Saída | F57: Leitura executiva
C58: Painel Setorial | D58: Comparação de betas e significância | E58: Saída | F58: Ranking setorial
C59: Sens Focus-Swap | D59: Matriz formula-driven | E59: Saída | F59: Cenários conjuntos
C60: Inflacao | D60: Teste entre Focus e inflação realizada | E60: Saída + detalhe | F60: Seleção da variável
C61: Ex-Commodities | D61: IBOV, ex-commodities e commodities | E61: Saída + detalhe | F61: Comparação de exposição
C62: Energia | D62: Petrobras e Brent | E62: Saída | F62: Decomposição do setor
C63: Earnings 12M Fwd | D63: Séries setoriais consolidadas | E63: Dados | F63: Níveis
C64: Earnings Base 100 | D64: Séries normalizadas | E64: Dados + gráfico | F64: Comparação histórica
C65: Revisions 3M | D65: Revisions setoriais | E65: Dados | F65: Targets das regressões
C66: Series Energia | D66: Companhias do setor | E66: Dados + gráfico | F66: Decomposição
C67: Macro IBOV | D67: Earnings do índice e macro | E67: Dados | F67: Regressores
... C73: Fontes | D73: URLs e hashes | E73: Proveniência | F73: Rastreabilidade
C76: Histórico de versões
C77: Data | D77: Versão | E77: Alteração | F77: Responsável
C78: 46269 | D78: 1.0 | E78: Consolidação das séries, regressões, sensibilidades e documentação em um workbook. | F78: Codex
